Workbook
Name MORANTE: '[1]DISPATCHED (VT11)'!#REF!
Name MORANTE: 'DISPATCHED (VT11)'!$F$248
Name T: 'DISPATCHED (VT11)'!$E$707

Sheet LO TEXT UPDATE
B1: Team Good Morning,
B2: New Paranaque Region Delivery Update as of
B3: ='DISPATCHED (VT11)'!C4 -> 46125
B4: 07:00H
B6: Current | C6: PLAN | D6: DISP | E6: VAR | F6: %
B7: KA | C7: ='Report Summary'!R8 -> 89 | D7: ='Report Summary'!S8 -> 57 | E7: =C7-D7 -> 32 | F7: =D7/C7 -> 0.64044944
C8: ='Report Summary'!R39 -> 25665 | D8: ='Report Summary'!S39 -> 14252
B9: HOD | C9: ='Report Summary'!R11 -> 11 | D9: ='Report Summary'!S11 -> 3 | E9: =C9-D9 -> 8 | F9: =D9/C9 -> 0.27272727
C10: ='Report Summary'!R42 -> 3504 | D10: ='Report Summary'!S42 -> 921
B11: DP | C11: ='Report Summary'!R14 -> 27 | D11: ='Report Summary'!S14 -> 6 | E11: =C11-D11 -> 21 | F11: =D11/C11 -> 0.22222222
C12: ='Report Summary'!R45 -> 7184 | D12: ='Report Summary'!S45 -> 1495
B13: LWS | C13: ='Report Summary'!R17 -> 8 | D13: ='Report Summary'!S17 -> 3 | E13: =C13-D13 -> 5 | F13: =D13/C13 -> 0.375
C14: ='Report Summary'!R48 -> 1900 | D14: ='Report Summary'!S48 -> 777
B15: WS | C15: ='Report Summary'!R20 -> 21 | D15: ='Report Summary'!S20 -> 11 | E15: =C15-D15 -> 10 | F15: =D15/C15 -> 0.52380952
C16: ='Report Summary'!R51 -> 5796 | D16: ='Report Summary'!S51 -> 3003
B17: XDOCK | C17: ='Report Summary'!R23 -> 0 | D17: ='Report Summary'!S23 -> 0 | E17: =C17-D17 -> 0 | F17: =D17/C17 -> #DIV/0!
C18: ='Report Summary'!R54 -> 0 | D18: ='Report Summary'!S54 -> 0
B19: PICK UP | C19: ='Report Summary'!R26 -> 30 | D19: ='Report Summary'!S26 -> 3 | E19: =C19-D19 -> 27 | F19: =D19/C19 -> 0.1
C20: ='Report Summary'!R57 -> 14750 | D20: ='Report Summary'!S57 -> 1288
B22: TOTAL CURRENT | C22: =C11+C7+C13+C15+C9+C17+C19 -> 186 | D22: =D11+D7+D13+D15+D9+D17+D19 -> 83 | E22: =C22-D22 -> 103 | F22: =D22/C22 -> 0.44623656
C23: =C12+C8+C14+C16+C10+C18+C20 -> 58799 | D23: =D12+D8+D14+D16+D10+D18+D20 -> 21736
B25: ADVANCE:
B26: KA | C26: ='Report Summary'!R10 -> #REF! | D26: ='Report Summary'!S10 -> 0 | E26: =C26-D26 -> #REF! | F26: =D26/C26 -> #REF!
C27: ='Report Summary'!R41 -> 0 | D27: ='Report Summary'!S41 -> 0
B28: HOD | C28: ='Report Summary'!R13 -> #REF! | D28: ='Report Summary'!S13 -> 0 | E28: =C28-D28 -> #REF! | F28: =D28/C28 -> #REF!
C29: ='Report Summary'!R44 -> 0 | D29: ='Report Summary'!S44 -> 0
B30: DP | C30: ='Report Summary'!R16 -> #REF! | D30: ='Report Summary'!S16 -> 0 | E30: =C30-D30 -> #REF! | F30: =D30/C30 -> #REF!
C31: ='Report Summary'!R47 -> 0 | D31: ='Report Summary'!S47 -> 0
B32: LWS | C32: ='Report Summary'!R19 -> #REF! | D32: ='Report Summary'!S19 -> 0 | E32: =C32-D32 -> #REF! | F32: =D32/C32 -> #REF!
C33: ='Report Summary'!R50 -> 0 | D33: ='Report Summary'!S50 -> 0
B34: WS | C34: ='Report Summary'!R22 -> #REF! | D34: ='Report Summary'!S22 -> 0 | E34: =C34-D34 -> #REF! | F34: =D34/C34 -> #REF!
C35: ='Report Summary'!R53 -> 0 | D35: ='Report Summary'!S53 -> 0
B36: XDOCK | C36: ='Report Summary'!R25 -> 0 | D36: ='Report Summary'!S25 -> 0 | E36: =C36-D36 -> 0 | F36: =D36/C36 -> #DIV/0!
C37: ='Report Summary'!R56 -> 0 | D37: ='Report Summary'!S56 -> 0
B38: PICK UP | C38: ='Report Summary'!R28 -> #REF! | D38: ='Report Summary'!S28 -> 0 | E38: =C38-D38 -> #REF! | F38: =D38/C38 -> #REF!
C39: ='Report Summary'!R59 -> 0 | D39: ='Report Summary'!S59 -> 0
B41: TOTAL ADVANCE | C41: =C30+C26+C32+C34+C28+C36+C38 -> #REF! | D41: =D30+D26+D32+D34+D28+D36+D38 -> 0 | E41: =C41-D41 -> #REF! | F41: =D41/C41 -> #REF!
C42: =C31+C27+C33+C35+C29+C37+C39 -> 0 | D42: =D31+D27+D33+D35+D29+D37+D39 -> 0
B44: BACKLOG:
B45: KA | C45: ='Report Summary'!R9 -> #REF! | D45: ='Report Summary'!S9 -> 0 | E45: =C45-D45 -> #REF! | F45: =D45/C45 -> #REF!
C46: ='Report Summary'!R40 -> 0 | D46: ='Report Summary'!S40 -> 0
B47: HOD | C47: ='Report Summary'!R12 -> #REF! | D47: ='Report Summary'!S12 -> 0 | E47: =C47-D47 -> #REF! | F47: =D47/C47 -> #REF!
C48: ='Report Summary'!R43 -> 0 | D48: ='Report Summary'!S43 -> 0
B49: DP | C49: ='Report Summary'!R15 -> #REF! | D49: ='Report Summary'!S15 -> 0 | E49: =C49-D49 -> #REF! | F49: =D49/C49 -> #REF!
C50: ='Report Summary'!R46 -> 0 | D50: ='Report Summary'!S46 -> 0
B51: LWS | C51: ='Report Summary'!R18 -> #REF! | D51: ='Report Summary'!S18 -> 0 | E51: =C51-D51 -> #REF! | F51: =D51/C51 -> #REF!
C52: ='Report Summary'!R49 -> 0 | D52: ='Report Summary'!S49 -> 0
B53: WS | C53: ='Report Summary'!R21 -> #REF! | D53: ='Report Summary'!S21 -> 0 | E53: ='Report Summary'!T21 -> #REF! | F53: =D53/C53 -> #REF!
C54: ='Report Summary'!R52 -> 0 | D54: ='Report Summary'!S52 -> 0
B55: XDOCK | C55: ='Report Summary'!R24 -> 0 | D55: ='Report Summary'!S24 -> 0 | E55: =C55-D55 -> 0 | F55: =D55/C55 -> #DIV/0!
C56: ='Report Summary'!R55 -> 0 | D56: ='Report Summary'!S55 -> 0
B57: PICK UP | C57: ='Report Summary'!R27 -> #REF! | D57: ='Report Summary'!S27 -> 0 | E57: =C57-D57 -> #REF! | F57: =D57/C57 -> #REF!
C58: ='Report Summary'!R58 -> 0 | D58: ='Report Summary'!S58 -> 0
B60: TOTAL BACKLOG | C60: =C49+C45+C51+C53+C47+C55+C57 -> #REF! | D60: =D49+D45+D51+D53+D47+D55+D57 -> 0 | E60: =C60-D60 -> #REF! | F60: =D60/C60 -> #REF!
C61: =C50+C46+C52+C54+C48+C56+C58 -> 0 | D61: =D50+D46+D52+D54+D48+D56+D58 -> 0
B63: HAULING:
B64: CANLUBANG | C64: ='Report Summary'!R29 -> 0 | D64: ='Report Summary'!S29 -> 0 | E64: ='Report Summary'!T29 -> 0 | F64: ='Report Summary'!U29 -> #DIV/0!
C65: ='Report Summary'!R60 -> 0 | D65: ='Report Summary'!S60 -> 0
B66: SRC | C66: ='Report Summary'!R30 -> 0 | D66: ='Report Summary'!S30 -> 0 | E66: ='Report Summary'!T30 -> 0 | F66: ='Report Summary'!U30 -> #DIV/0!
C67: ='Report Summary'!R61 -> 0 | D67: ='Report Summary'!S61 -> 0
B70: GRAND TOTAL | C70: =C11+C7+C13+C15+C9+C17+C19+C30+C26+C32+C34+C28+C36+C38+C49+C45+C51+C53+C47+C55+C57 -> #REF! | D70: =D11+D7+D13+D15+D9+D17+D19+D30+D26+D32+D34+D28+D36+D38+D49+D45+D51+D53+D47+D55+D57 -> 83 | E70: =C70-D70 -> #REF! | F70: =D70/C70 -> #REF!
C71: =C12+C8+C14+C16+C10+C18+C20+C31+C27+C33+C35+C29+C37+C39+C50+C46+C52+C54+C48+C56+C58 -> 58799 | D71: =D12+D8+D14+D16+D10+D18+D20+D31+D27+D33+D35+D29+D37+D39+D50+D46+D52+D54+D48+D56+D58 -> 21736 | E71: =C71-D71 -> 37063 | F71: =D71/C71 -> 0.36966615
B73: RSM UPDATE:
B74: SGMA | C74: ='For RSM'!F11 -> #REF! | D74: ='For RSM'!G11 -> 7 | E74: =C74-D74 -> #REF! | F74: =D74/C74 -> #REF!
C75: ='For RSM'!B10 -> 4331 | D75: ='For RSM'!C10 -> 1387
B76: UPPER SOUTH | C76: ='For RSM'!#REF! -> #REF! | D76: ='For RSM'!#REF! -> #REF! | E76: =C76-D76 -> #REF! | F76: =D76/C76 -> #REF!
C77: ='For RSM'!B17 -> 11651 | D77: ='For RSM'!C17 -> 1889
B81: ATTENDANCE:
B82: CCBPI | C82: ='Report Summary'!C17 -> 109 | D82: ='Report Summary'!D17 -> 44 | E82: =C82-D82 -> 65 | F82: =D82/C82 -> 0.40366972
B84: LSP's:
B85: Rodmac | C85: ='Report Summary'!C25 -> 19 | D85: ='Report Summary'!D25 -> 8 | E85: =C85-D85 -> 11 | F85: =D85/C85 -> 0.42105263
B86: Ong | C86: ='Report Summary'!C26 -> 22 | D86: ='Report Summary'!D26 -> 9 | E86: =C86-D86 -> 13 | F86: =D86/C86 -> 0.40909091
B87: Benline | C87: ='Report Summary'!C27 -> 0 | D87: ='Report Summary'!D27 -> 0 | E87: =C87-D87 -> 0 | F87: =D87/C87 -> #DIV/0!
B88: GPTS | C88: ='Report Summary'!C29 -> 0 | D88: ='Report Summary'!D29 -> 0 | E88: =C88-D88 -> 0 | F88: =D88/C88 -> #DIV/0!
B91: Trip Sharing Update:
B93: Total Shipments: | C93: ='DISPATCHED (VT11)'!AT1 -> =
B95: Total Dispatched: | C95: ='DISPATCHED (VT11)'!AT2 -> 0
B97: Co-owned: | C97: ='DISPATCHED (VT11)'!AT3 -> 0 | D97: ='DISPATCHED (VT11)'!AT2 -> 0 | E97: ='DISPATCHED (VT11)'!AU3 -> #DIV/0!
B99: LSP: | C99: ='DISPATCHED (VT11)'!AT4 -> 0 | D99: ='DISPATCHED (VT11)'!AT2 -> 0 | E99: ='DISPATCHED (VT11)'!AU4 -> #DIV/0!
B101: *Ong | C101: ='DISPATCHED (VT11)'!AP1 -> 0 | D101: ='DISPATCHED (VT11)'!AQ1 -> #DIV/0!
B102: *Rodmac | C102: ='DISPATCHED (VT11)'!AP2 -> 0 | D102: ='DISPATCHED (VT11)'!AQ2 -> #DIV/0!
B103: *Gpts | C103: ='DISPATCHED (VT11)'!AP3 -> 0 | D103: ='DISPATCHED (VT11)'!AQ3 -> #DIV/0!
B104: *Benline | C104: ='DISPATCHED (VT11)'!AP4 -> 0 | D104: ='DISPATCHED (VT11)'!AQ4 -> #DIV/0!
B107: Reason of Balance Deliveries:
B109: * Pick Up
B110: - For tomorrow pick up schedule.
B113: Thanks,
B114: KCZ

Sheet Summarized Plan
A1: SHIPMENT | B1: OUTLET NAME | C1: Qty | D1: No. of Drops | E1: CUBES | G1: CG | H1: DATE | I1: VENDOR | J1: TSM | K1: KA CLUSTER | L1: 14P | M1: =COUNTIF(#REF!,14) -> #REF! | O1: Duplicated? | P1: =IF(COUNTIF('DISPATCHED (VT11)'!$E:$E,'Summarized Plan'!A1)=0,"",COUNTIF('DISPATCHED (VT11)'!$E:$E,'Summarized Plan'!A1)) | Q1: =IF(A1="","",IF(ISNA(VLOOKUP(A1,'DISPATCHED (VT11)'!$E:$M,9,0)),"",VLOOKUP(A1,'DISPATCHED (VT11)'!$E:$M,9,0))) | R1: =IF(H1="","",IF(H1<#REF!,1,0)) -> #REF! | S1: =IF(H1="","",IF(H1>#REF!,1,0)) -> #REF! | T1: =IF(H1="","",IF(H1=#REF!,1,0)) -> #REF! | U1: =IF(I1="","",1) -> 1 | W1: =SUM(#REF!) -> #REF! | Z1: PLATE
A2: 30978993 | B2: CARRY ALL FOOD ENTERPRISES INC. | F2: PULLOUT EMPTIES | H2: 46114 | M2: =VLOOKUP(B2,REFERENCE!$A$2:D209,4,0) -> #N/A | N2: =VLOOKUP(B2,REFERENCE!A:C,3,FALSE) -> TAG-PUP | O2: =COUNTIF($A:$A,A2) -> 1 | P2: =IF(COUNTIF('DISPATCHED (VT11)'!$E:$E,'Summarized Plan'!A2)=0,"",COUNTIF('DISPATCHED (VT11)'!$E:$E,'Summarized Plan'!A2)) | Q2: =IF(A2="","",IF(ISNA(VLOOKUP(A2,'DISPATCHED (VT11)'!$E:$M,9,0)),"",VLOOKUP(A2,'DISPATCHED (VT11)'!$E:$M,9,0))) | R2: =IF(H2="","",IF(H2<#REF!,1,0)) -> #REF! | S2: =IF(H2="","",IF(H2>#REF!,1,0)) -> #REF! | T2: =IF(H2="","",IF(H2=#REF!,1,0)) -> #REF! | U2: =IF(I2="","",1)
A3: 30978994 | B3: CARRY ALL FOOD ENTERPRISES INC. | F3: PULLOUT EMPTIES | H3: 46114 | M3: =VLOOKUP(B3,REFERENCE!$A$2:D210,4,0) -> #N/A | N3: =VLOOKUP(B3,REFERENCE!A:C,3,FALSE) -> TAG-PUP | O3: =COUNTIF($A:$A,A3) -> 1 | P3: =IF(COUNTIF('DISPATCHED (VT11)'!$E:$E,'Summarized Plan'!A3)=0,"",COUNTIF('DISPATCHED (VT11)'!$E:$E,'Summarized Plan'!A3)) | Q3: =IF(A3="","",IF(ISNA(VLOOKUP(A3,'DISPATCHED (VT11)'!$E:$M,9,0)),"",VLOOKUP(A3,'DISPATCHED (VT11)'!$E:$M,9,0))) | R3: =IF(H3="","",IF(H3<#REF!,1,0)) -> #REF! | S3: =IF(H3="","",IF(H3>#REF!,1,0)) -> #REF! | T3: =IF(H3="","",IF(H3=#REF!,1,0)) -> #REF! | U3: =IF(I3="","",1)
A4: 30978995 | B4: CARRY ALL FOOD ENTERPRISES INC. | F4: PULLOUT EMPTIES | H4: 46114 | M4: =VLOOKUP(B4,REFERENCE!$A$2:D211,4,0) -> #N/A | N4: =VLOOKUP(B4,REFERENCE!A:C,3,FALSE) -> TAG-PUP | O4: =COUNTIF($A:$A,A4) -> 1 | P4: =IF(COUNTIF('DISPATCHED (VT11)'!$E:$E,'Summarized Plan'!A4)=0,"",COUNTIF('DISPATCHED (VT11)'!$E:$E,'Summarized Plan'!A4)) | Q4: =IF(A4="","",IF(ISNA(VLOOKUP(A4,'DISPATCHED (VT11)'!$E:$M,9,0)),"",VLOOKUP(A4,'DISPATCHED (VT11)'!$E:$M,9,0))) | R4: =IF(H4="","",IF(H4<#REF!,1,0)) -> #REF! | S4: =IF(H4="","",IF(H4>#REF!,1,0)) -> #REF! | T4: =IF(H4="","",IF(H4=#REF!,1,0)) -> #REF! | U4: =IF(I4="","",1)
A5: 30978996 | B5: CARRY ALL FOOD ENTERPRISES INC. | F5: PULLOUT EMPTIES | H5: 46114 | M5: =VLOOKUP(B5,REFERENCE!$A$2:D212,4,0) -> #N/A | N5: =VLOOKUP(B5,REFERENCE!A:C,3,FALSE) -> TAG-PUP | O5: =COUNTIF($A:$A,A5) -> 1 | P5: =IF(COUNTIF('DISPATCHED (VT11)'!$E:$E,'Summarized Plan'!A5)=0,"",COUNTIF('DISPATCHED (VT11)'!$E:$E,'Summarized Plan'!A5)) | Q5: =IF(A5="","",IF(ISNA(VLOOKUP(A5,'DISPATCHED (VT11)'!$E:$M,9,0)),"",VLOOKUP(A5,'DISPATCHED (VT11)'!$E:$M,9,0))) | R5: =IF(H5="","",IF(H5<#REF!,1,0)) -> #REF! | S5: =IF(H5="","",IF(H5>#REF!,1,0)) -> #REF! | T5: =IF(H5="","",IF(H5=#REF!,1,0)) -> #REF! | U5: =IF(I5="","",1)
A6: 30978997 | B6: CARRY ALL FOOD ENTERPRISES INC. | F6: PULLOUT EMPTIES | H6: 46114 | M6: =VLOOKUP(B6,REFERENCE!$A$2:D213,4,0) -> #N/A | N6: =VLOOKUP(B6,REFERENCE!A:C,3,FALSE) -> TAG-PUP | O6: =COUNTIF($A:$A,A6) -> 1 | P6: =IF(COUNTIF('DISPATCHED (VT11)'!$E:$E,'Summarized Plan'!A6)=0,"",COUNTIF('DISPATCHED (VT11)'!$E:$E,'Summarized Plan'!A6)) | Q6: =IF(A6="","",IF(ISNA(VLOOKUP(A6,'DISPATCHED (VT11)'!$E:$M,9,0)),"",VLOOKUP(A6,'DISPATCHED (VT11)'!$E:$M,9,0))) | R6: =IF(H6="","",IF(H6<#REF!,1,0)) -> #REF! | S6: =IF(H6="","",IF(H6>#REF!,1,0)) -> #REF! | T6: =IF(H6="","",IF(H6=#REF!,1,0)) -> #REF! | U6: =IF(I6="","",1)
A7: 30978998 | B7: CARRY ALL FOOD ENTERPRISES INC. | F7: PULLOUT EMPTIES | H7: 46114 | M7: =VLOOKUP(B7,REFERENCE!$A$2:D214,4,0) -> #N/A | N7: =VLOOKUP(B7,REFERENCE!A:C,3,FALSE) -> TAG-PUP | O7: =COUNTIF($A:$A,A7) -> 1 | P7: =IF(COUNTIF('DISPATCHED (VT11)'!$E:$E,'Summarized Plan'!A7)=0,"",COUNTIF('DISPATCHED (VT11)'!$E:$E,'Summarized Plan'!A7)) | Q7: =IF(A7="","",IF(ISNA(VLOOKUP(A7,'DISPATCHED (VT11)'!$E:$M,9,0)),"",VLOOKUP(A7,'DISPATCHED (VT11)'!$E:$M,9,0))) | R7: =IF(H7="","",IF(H7<#REF!,1,0)) -> #REF! | S7: =IF(H7="","",IF(H7>#REF!,1,0)) -> #REF! | T7: =IF(H7="","",IF(H7=#REF!,1,0)) -> #REF! | U7: =IF(I7="","",1)
A8: 30978999 | B8: CARRY ALL FOOD ENTERPRISES INC. | F8: PULLOUT EMPTIES | H8: 46114 | M8: =VLOOKUP(B8,REFERENCE!$A$2:D215,4,0) -> #N/A | N8: =VLOOKUP(B8,REFERENCE!A:C,3,FALSE) -> TAG-PUP | O8: =COUNTIF($A:$A,A8) -> 1 | P8: =IF(COUNTIF('DISPATCHED (VT11)'!$E:$E,'Summarized Plan'!A8)=0,"",COUNTIF('DISPATCHED (VT11)'!$E:$E,'Summarized Plan'!A8)) | Q8: =IF(A8="","",IF(ISNA(VLOOKUP(A8,'DISPATCHED (VT11)'!$E:$M,9,0)),"",VLOOKUP(A8,'DISPATCHED (VT11)'!$E:$M,9,0))) | R8: =IF(H8="","",IF(H8<#REF!,1,0)) -> #REF! | S8: =IF(H8="","",IF(H8>#REF!,1,0)) -> #REF! | T8: =IF(H8="","",IF(H8=#REF!,1,0)) -> #REF! | U8: =IF(I8="","",1)
A9: 30979020 | B9: CARRY ALL FOOD ENTERPRISES INC. | F9: PULLOUT EMPTIES | H9: 46114 | M9: =VLOOKUP(B9,REFERENCE!$A$2:D216,4,0) -> #N/A | N9: =VLOOKUP(B9,REFERENCE!A:C,3,FALSE) -> TAG-PUP | O9: =COUNTIF($A:$A,A9) -> 1 | P9: =IF(COUNTIF('DISPATCHED (VT11)'!$E:$E,'Summarized Plan'!A9)=0,"",COUNTIF('DISPATCHED (VT11)'!$E:$E,'Summarized Plan'!A9)) | Q9: =IF(A9="","",IF(ISNA(VLOOKUP(A9,'DISPATCHED (VT11)'!$E:$M,9,0)),"",VLOOKUP(A9,'DISPATCHED (VT11)'!$E:$M,9,0))) | R9: =IF(H9="","",IF(H9<#REF!,1,0)) -> #REF! | S9: =IF(H9="","",IF(H9>#REF!,1,0)) -> #REF! | T9: =IF(H9="","",IF(H9=#REF!,1,0)) -> #REF! | U9: =IF(I9="","",1)
A10: 30979021 | B10: CARRY ALL FOOD ENTERPRISES INC. | F10: PULLOUT EMPTIES | H10: 46114 | M10: =VLOOKUP(B10,REFERENCE!$A$2:D217,4,0) -> #N/A | N10: =VLOOKUP(B10,REFERENCE!A:C,3,FALSE) -> TAG-PUP | O10: =COUNTIF($A:$A,A10) -> 1 | P10: =IF(COUNTIF('DISPATCHED (VT11)'!$E:$E,'Summarized Plan'!A10)=0,"",COUNTIF('DISPATCHED (VT11)'!$E:$E,'Summarized Plan'!A10)) | Q10: =IF(A10="","",IF(ISNA(VLOOKUP(A10,'DISPATCHED (VT11)'!$E:$M,9,0)),"",VLOOKUP(A10,'DISPATCHED (VT11)'!$E:$M,9,0))) | R10: =IF(H10="","",IF(H10<#REF!,1,0)) -> #REF! | S10: =IF(H10="","",IF(H10>#REF!,1,0)) -> #REF! | T10: =IF(H10="","",IF(H10=#REF!,1,0)) -> #REF! | U10: =IF(I10="","",1)
A11: 30979022 | B11: CARRY ALL FOOD ENTERPRISES INC. | F11: PULLOUT EMPTIES | H11: 46114 | M11: =VLOOKUP(B11,REFERENCE!$A$2:D218,4,0) -> #N/A | N11: =VLOOKUP(B11,REFERENCE!A:C,3,FALSE) -> TAG-PUP | O11: =COUNTIF($A:$A,A11) -> 1 | P11: =IF(COUNTIF('DISPATCHED (VT11)'!$E:$E,'Summarized Plan'!A11)=0,"",COUNTIF('DISPATCHED (VT11)'!$E:$E,'Summarized Plan'!A11)) | Q11: =IF(A11="","",IF(ISNA(VLOOKUP(A11,'DISPATCHED (VT11)'!$E:$M,9,0)),"",VLOOKUP(A11,'DISPATCHED (VT11)'!$E:$M,9,0))) | R11: =IF(H11="","",IF(H11<#REF!,1,0)) -> #REF! | S11: =IF(H11="","",IF(H11>#REF!,1,0)) -> #REF! | T11: =IF(H11="","",IF(H11=#REF!,1,0)) -> #REF! | U11: =IF(I11="","",1)
A12: 30979023 | B12: CARRY ALL FOOD ENTERPRISES INC. | F12: PULLOUT EMPTIES | H12: 46114 | M12: =VLOOKUP(B12,REFERENCE!$A$2:D219,4,0) -> #N/A | N12: =VLOOKUP(B12,REFERENCE!A:C,3,FALSE) -> TAG-PUP | O12: =COUNTIF($A:$A,A12) -> 1 | P12: =IF(COUNTIF('DISPATCHED (VT11)'!$E:$E,'Summarized Plan'!A12)=0,"",COUNTIF('DISPATCHED (VT11)'!$E:$E,'Summarized Plan'!A12)) | Q12: =IF(A12="","",IF(ISNA(VLOOKUP(A12,'DISPATCHED (VT11)'!$E:$M,9,0)),"",VLOOKUP(A12,'DISPATCHED (VT11)'!$E:$M,9,0))) | R12: =IF(H12="","",IF(H12<#REF!,1,0)) -> #REF! | S12: =IF(H12="","",IF(H12>#REF!,1,0)) -> #REF! | T12: =IF(H12="","",IF(H12=#REF!,1,0)) -> #REF! | U12: =IF(I12="","",1)
A13: 30979024 | B13: CARRY ALL FOOD ENTERPRISES INC. | F13: PULLOUT EMPTIES | H13: 46114 | M13: =VLOOKUP(B13,REFERENCE!$A$2:D220,4,0) -> #N/A | N13: =VLOOKUP(B13,REFERENCE!A:C,3,FALSE) -> TAG-PUP | O13: =COUNTIF($A:$A,A13) -> 1 | P13: =IF(COUNTIF('DISPATCHED (VT11)'!$E:$E,'Summarized Plan'!A13)=0,"",COUNTIF('DISPATCHED (VT11)'!$E:$E,'Summarized Plan'!A13)) | Q13: =IF(A13="","",IF(ISNA(VLOOKUP(A13,'DISPATCHED (VT11)'!$E:$M,9,0)),"",VLOOKUP(A13,'DISPATCHED (VT11)'!$E:$M,9,0))) | R13: =IF(H13="","",IF(H13<#REF!,1,0)) -> #REF! | S13: =IF(H13="","",IF(H13>#REF!,1,0)) -> #REF! | T13: =IF(H13="","",IF(H13=#REF!,1,0)) -> #REF! | U13: =IF(I13="","",1)
... A60: 31002652 | B60: EBON GEN MDSE | F60: PULLOUT EMPTIES | H60: 46120 | M60: =VLOOKUP(B60,REFERENCE!$A$2:D267,4,0) -> ANDRE GORDONCILLO | N60: =VLOOKUP(B60,REFERENCE!A:C,3,FALSE) -> LP-LWS | O60: =COUNTIF($A:$A,A60) -> 1 | P60: =IF(COUNTIF('DISPATCHED (VT11)'!$E:$E,'Summarized Plan'!A60)=0,"",COUNTIF('DISPATCHED (VT11)'!$E:$E,'Summarized Plan'!A60)) | Q60: =IF(A60="","",IF(ISNA(VLOOKUP(A60,'DISPATCHED (VT11)'!$E:$M,9,0)),"",VLOOKUP(A60,'DISPATCHED (VT11)'!$E:$M,9,0))) | R60: =IF(H60="","",IF(H60<#REF!,1,0)) -> #REF! | S60: =IF(H60="","",IF(H60>#REF!,1,0)) -> #REF! | T60: =IF(H60="","",IF(H60=#REF!,1,0)) -> #REF! | U60: =IF(I60="","",1)
A61: 31002724 | B61: PRINCESS DANAE MARKETING | F61: PULLOUT EMPTIES | H61: 46120 | M61: =VLOOKUP(B61,REFERENCE!$A$2:D269,4,0) -> ANDRE GORDONCILLO | N61: =VLOOKUP(B61,REFERENCE!A:C,3,FALSE) -> LP-WS | O61: =COUNTIF($A:$A,A61) -> 1 | P61: =IF(COUNTIF('DISPATCHED (VT11)'!$E:$E,'Summarized Plan'!A61)=0,"",COUNTIF('DISPATCHED (VT11)'!$E:$E,'Summarized Plan'!A61)) | Q61: =IF(A61="","",IF(ISNA(VLOOKUP(A61,'DISPATCHED (VT11)'!$E:$M,9,0)),"",VLOOKUP(A61,'DISPATCHED (VT11)'!$E:$M,9,0))) | R61: =IF(H61="","",IF(H61<#REF!,1,0)) -> #REF! | S61: =IF(H61="","",IF(H61>#REF!,1,0)) -> #REF! | T61: =IF(H61="","",IF(H61=#REF!,1,0)) -> #REF! | U61: =IF(I61="","",1)
A62: 31002725 | B62: PRINCESS DANAE MARKETING | F62: PULLOUT EMPTIES | H62: 46120 | M62: =VLOOKUP(B62,REFERENCE!$A$2:D270,4,0) -> ANDRE GORDONCILLO | N62: =VLOOKUP(B62,REFERENCE!A:C,3,FALSE) -> LP-WS | O62: =COUNTIF($A:$A,A62) -> 1 | P62: =IF(COUNTIF('DISPATCHED (VT11)'!$E:$E,'Summarized Plan'!A62)=0,"",COUNTIF('DISPATCHED (VT11)'!$E:$E,'Summarized Plan'!A62)) | Q62: =IF(A62="","",IF(ISNA(VLOOKUP(A62,'DISPATCHED (VT11)'!$E:$M,9,0)),"",VLOOKUP(A62,'DISPATCHED (VT11)'!$E:$M,9,0))) | R62: =IF(H62="","",IF(H62<#REF!,1,0)) -> #REF! | S62: =IF(H62="","",IF(H62>#REF!,1,0)) -> #REF! | T62: =IF(H62="","",IF(H62=#REF!,1,0)) -> #REF! | U62: =IF(I62="","",1)
A63: 31002726 | B63: PRINCESS DANAE MARKETING | F63: PULLOUT EMPTIES | H63: 46120 | M63: =VLOOKUP(B63,REFERENCE!$A$2:D271,4,0) -> ANDRE GORDONCILLO | N63: =VLOOKUP(B63,REFERENCE!A:C,3,FALSE) -> LP-WS | O63: =COUNTIF($A:$A,A63) -> 1 | P63: =IF(COUNTIF('DISPATCHED (VT11)'!$E:$E,'Summarized Plan'!A63)=0,"",COUNTIF('DISPATCHED (VT11)'!$E:$E,'Summarized Plan'!A63)) | Q63: =IF(A63="","",IF(ISNA(VLOOKUP(A63,'DISPATCHED (VT11)'!$E:$M,9,0)),"",VLOOKUP(A63,'DISPATCHED (VT11)'!$E:$M,9,0))) | R63: =IF(H63="","",IF(H63<#REF!,1,0)) -> #REF! | S63: =IF(H63="","",IF(H63>#REF!,1,0)) -> #REF! | T63: =IF(H63="","",IF(H63=#REF!,1,0)) -> #REF! | U63: =IF(I63="","",1)
A64: 31002732 | B64: RICAFORTZ CONSUMER GOODS TRADING | F64: BASBAS | H64: 46120 | M64: =VLOOKUP(B64,REFERENCE!$A$2:D273,4,0) -> #N/A | N64: =VLOOKUP(B64,REFERENCE!A:C,3,FALSE) -> #N/A | O64: =COUNTIF($A:$A,A64) -> 1 | P64: =IF(COUNTIF('DISPATCHED (VT11)'!$E:$E,'Summarized Plan'!A64)=0,"",COUNTIF('DISPATCHED (VT11)'!$E:$E,'Summarized Plan'!A64)) | Q64: =IF(A64="","",IF(ISNA(VLOOKUP(A64,'DISPATCHED (VT11)'!$E:$M,9,0)),"",VLOOKUP(A64,'DISPATCHED (VT11)'!$E:$M,9,0))) | R64: =IF(H64="","",IF(H64<#REF!,1,0)) -> #REF! | S64: =IF(H64="","",IF(H64>#REF!,1,0)) -> #REF! | T64: =IF(H64="","",IF(H64=#REF!,1,0)) -> #REF! | U64: =IF(I64="","",1)
A65: 31002733 | B65: RICAFORTZ CONSUMER GOODS TRADING | F65: PULLOUT EMPTIES | H65: 46120 | M65: =VLOOKUP(B65,REFERENCE!$A$2:D274,4,0) -> #N/A | N65: =VLOOKUP(B65,REFERENCE!A:C,3,FALSE) -> #N/A | O65: =COUNTIF($A:$A,A65) -> 1 | P65: =IF(COUNTIF('DISPATCHED (VT11)'!$E:$E,'Summarized Plan'!A65)=0,"",COUNTIF('DISPATCHED (VT11)'!$E:$E,'Summarized Plan'!A65)) | Q65: =IF(A65="","",IF(ISNA(VLOOKUP(A65,'DISPATCHED (VT11)'!$E:$M,9,0)),"",VLOOKUP(A65,'DISPATCHED (VT11)'!$E:$M,9,0))) | R65: =IF(H65="","",IF(H65<#REF!,1,0)) -> #REF! | S65: =IF(H65="","",IF(H65>#REF!,1,0)) -> #REF! | T65: =IF(H65="","",IF(H65=#REF!,1,0)) -> #REF! | U65: =IF(I65="","",1)
A66: 31002734 | B66: RICAFORTZ CONSUMER GOODS TRADING | F66: PULLOUT EMPTIES | H66: 46120 | M66: =VLOOKUP(B66,REFERENCE!$A$2:D275,4,0) -> #N/A | N66: =VLOOKUP(B66,REFERENCE!A:C,3,FALSE) -> #N/A | O66: =COUNTIF($A:$A,A66) -> 1 | P66: =IF(COUNTIF('DISPATCHED (VT11)'!$E:$E,'Summarized Plan'!A66)=0,"",COUNTIF('DISPATCHED (VT11)'!$E:$E,'Summarized Plan'!A66)) | Q66: =IF(A66="","",IF(ISNA(VLOOKUP(A66,'DISPATCHED (VT11)'!$E:$M,9,0)),"",VLOOKUP(A66,'DISPATCHED (VT11)'!$E:$M,9,0))) | R66: =IF(H66="","",IF(H66<#REF!,1,0)) -> #REF! | S66: =IF(H66="","",IF(H66>#REF!,1,0)) -> #REF! | T66: =IF(H66="","",IF(H66=#REF!,1,0)) -> #REF! | U66: =IF(I66="","",1)
A67: 31002735 | B67: RICAFORTZ CONSUMER GOODS TRADING | F67: PULLOUT EMPTIES | H67: 46120 | M67: =VLOOKUP(B67,REFERENCE!$A$2:D276,4,0) -> #N/A | N67: =VLOOKUP(B67,REFERENCE!A:C,3,FALSE) -> #N/A | O67: =COUNTIF($A:$A,A67) -> 1 | P67: =IF(COUNTIF('DISPATCHED (VT11)'!$E:$E,'Summarized Plan'!A67)=0,"",COUNTIF('DISPATCHED (VT11)'!$E:$E,'Summarized Plan'!A67)) | Q67: =IF(A67="","",IF(ISNA(VLOOKUP(A67,'DISPATCHED (VT11)'!$E:$M,9,0)),"",VLOOKUP(A67,'DISPATCHED (VT11)'!$E:$M,9,0))) | R67: =IF(H67="","",IF(H67<#REF!,1,0)) -> #REF! | S67: =IF(H67="","",IF(H67>#REF!,1,0)) -> #REF! | T67: =IF(H67="","",IF(H67=#REF!,1,0)) -> #REF! | U67: =IF(I67="","",1)
A68: 31002736 | B68: RICAFORTZ CONSUMER GOODS TRADING | F68: PULLOUT EMPTIES | H68: 46120 | M68: =VLOOKUP(B68,REFERENCE!$A$2:D277,4,0) -> #N/A | N68: =VLOOKUP(B68,REFERENCE!A:C,3,FALSE) -> #N/A | O68: =COUNTIF($A:$A,A68) -> 1 | P68: =IF(COUNTIF('DISPATCHED (VT11)'!$E:$E,'Summarized Plan'!A68)=0,"",COUNTIF('DISPATCHED (VT11)'!$E:$E,'Summarized Plan'!A68)) | Q68: =IF(A68="","",IF(ISNA(VLOOKUP(A68,'DISPATCHED (VT11)'!$E:$M,9,0)),"",VLOOKUP(A68,'DISPATCHED (VT11)'!$E:$M,9,0))) | R68: =IF(H68="","",IF(H68<#REF!,1,0)) -> #REF! | S68: =IF(H68="","",IF(H68>#REF!,1,0)) -> #REF! | T68: =IF(H68="","",IF(H68=#REF!,1,0)) -> #REF! | U68: =IF(I68="","",1)
A69: 31002737 | B69: RICAFORTZ CONSUMER GOODS TRADING | F69: PULLOUT EMPTIES | H69: 46120 | M69: =VLOOKUP(B69,REFERENCE!$A$2:D278,4,0) -> #N/A | N69: =VLOOKUP(B69,REFERENCE!A:C,3,FALSE) -> #N/A | O69: =COUNTIF($A:$A,A69) -> 1 | P69: =IF(COUNTIF('DISPATCHED (VT11)'!$E:$E,'Summarized Plan'!A69)=0,"",COUNTIF('DISPATCHED (VT11)'!$E:$E,'Summarized Plan'!A69)) | Q69: =IF(A69="","",IF(ISNA(VLOOKUP(A69,'DISPATCHED (VT11)'!$E:$M,9,0)),"",VLOOKUP(A69,'DISPATCHED (VT11)'!$E:$M,9,0))) | R69: =IF(H69="","",IF(H69<#REF!,1,0)) -> #REF! | S69: =IF(H69="","",IF(H69>#REF!,1,0)) -> #REF! | T69: =IF(H69="","",IF(H69=#REF!,1,0)) -> #REF! | U69: =IF(I69="","",1)
A70: 31002738 | B70: RICAFORTZ CONSUMER GOODS TRADING | F70: PULLOUT EMPTIES | H70: 46120 | M70: =VLOOKUP(B70,REFERENCE!$A$2:D279,4,0) -> #N/A | N70: =VLOOKUP(B70,REFERENCE!A:C,3,FALSE) -> #N/A | O70: =COUNTIF($A:$A,A70) -> 1 | P70: =IF(COUNTIF('DISPATCHED (VT11)'!$E:$E,'Summarized Plan'!A70)=0,"",COUNTIF('DISPATCHED (VT11)'!$E:$E,'Summarized Plan'!A70)) | Q70: =IF(A70="","",IF(ISNA(VLOOKUP(A70,'DISPATCHED (VT11)'!$E:$M,9,0)),"",VLOOKUP(A70,'DISPATCHED (VT11)'!$E:$M,9,0))) | R70: =IF(H70="","",IF(H70<#REF!,1,0)) -> #REF! | S70: =IF(H70="","",IF(H70>#REF!,1,0)) -> #REF! | T70: =IF(H70="","",IF(H70=#REF!,1,0)) -> #REF! | U70: =IF(I70="","",1)
A71: 31002739 | B71: RICAFORTZ CONSUMER GOODS TRADING | F71: PULLOUT EMPTIES | H71: 46120 | M71: =VLOOKUP(B71,REFERENCE!$A$2:D280,4,0) -> #N/A | N71: =VLOOKUP(B71,REFERENCE!A:C,3,FALSE) -> #N/A | O71: =COUNTIF($A:$A,A71) -> 1 | P71: =IF(COUNTIF('DISPATCHED (VT11)'!$E:$E,'Summarized Plan'!A71)=0,"",COUNTIF('DISPATCHED (VT11)'!$E:$E,'Summarized Plan'!A71)) | Q71: =IF(A71="","",IF(ISNA(VLOOKUP(A71,'DISPATCHED (VT11)'!$E:$M,9,0)),"",VLOOKUP(A71,'DISPATCHED (VT11)'!$E:$M,9,0))) | R71: =IF(H71="","",IF(H71<#REF!,1,0)) -> #REF! | S71: =IF(H71="","",IF(H71>#REF!,1,0)) -> #REF! | T71: =IF(H71="","",IF(H71=#REF!,1,0)) -> #REF! | U71: =IF(I71="","",1)
A72: 31002750 | B72: RICAFORTZ CONSUMER GOODS TRADING | F72: PULLOUT EMPTIES | H72: 46120 | M72: =VLOOKUP(B72,REFERENCE!$A$2:D281,4,0) -> #N/A | N72: =VLOOKUP(B72,REFERENCE!A:C,3,FALSE) -> #N/A | O72: =COUNTIF($A:$A,A72) -> 1 | P72: =IF(COUNTIF('DISPATCHED (VT11)'!$E:$E,'Summarized Plan'!A72)=0,"",COUNTIF('DISPATCHED (VT11)'!$E:$E,'Summarized Plan'!A72)) | Q72: =IF(A72="","",IF(ISNA(VLOOKUP(A72,'DISPATCHED (VT11)'!$E:$M,9,0)),"",VLOOKUP(A72,'DISPATCHED (VT11)'!$E:$M,9,0))) | R72: =IF(H72="","",IF(H72<#REF!,1,0)) -> #REF! | S72: =IF(H72="","",IF(H72>#REF!,1,0)) -> #REF! | T72: =IF(H72="","",IF(H72=#REF!,1,0)) -> #REF! | U72: =IF(I72="","",1)
A73: 31002751 | B73: RICAFORTZ CONSUMER GOODS TRADING | F73: PULLOUT EMPTIES | H73: 46120 | M73: =VLOOKUP(B73,REFERENCE!$A$2:D282,4,0) -> #N/A | N73: =VLOOKUP(B73,REFERENCE!A:C,3,FALSE) -> #N/A | O73: =COUNTIF($A:$A,A73) -> 1 | P73: =IF(COUNTIF('DISPATCHED (VT11)'!$E:$E,'Summarized Plan'!A73)=0,"",COUNTIF('DISPATCHED (VT11)'!$E:$E,'Summarized Plan'!A73)) | Q73: =IF(A73="","",IF(ISNA(VLOOKUP(A73,'DISPATCHED (VT11)'!$E:$M,9,0)),"",VLOOKUP(A73,'DISPATCHED (VT11)'!$E:$M,9,0))) | R73: =IF(H73="","",IF(H73<#REF!,1,0)) -> #REF! | S73: =IF(H73="","",IF(H73>#REF!,1,0)) -> #REF! | T73: =IF(H73="","",IF(H73=#REF!,1,0)) -> #REF! | U73: =IF(I73="","",1)
A74: 31002752 | B74: RICAFORTZ CONSUMER GOODS TRADING | F74: PULLOUT EMPTIES | H74: 46120 | M74: =VLOOKUP(B74,REFERENCE!$A$2:D283,4,0) -> #N/A | N74: =VLOOKUP(B74,REFERENCE!A:C,3,FALSE) -> #N/A | O74: =COUNTIF($A:$A,A74) -> 1 | P74: =IF(COUNTIF('DISPATCHED (VT11)'!$E:$E,'Summarized Plan'!A74)=0,"",COUNTIF('DISPATCHED (VT11)'!$E:$E,'Summarized Plan'!A74)) | Q74: =IF(A74="","",IF(ISNA(VLOOKUP(A74,'DISPATCHED (VT11)'!$E:$M,9,0)),"",VLOOKUP(A74,'DISPATCHED (VT11)'!$E:$M,9,0))) | R74: =IF(H74="","",IF(H74<#REF!,1,0)) -> #REF! | S74: =IF(H74="","",IF(H74>#REF!,1,0)) -> #REF! | T74: =IF(H74="","",IF(H74=#REF!,1,0)) -> #REF! | U74: =IF(I74="","",1)
A75: 31002753 | B75: RICAFORTZ CONSUMER GOODS TRADING | F75: PULLOUT EMPTIES | H75: 46120 | M75: =VLOOKUP(B75,REFERENCE!$A$2:D284,4,0) -> #N/A | N75: =VLOOKUP(B75,REFERENCE!A:C,3,FALSE) -> #N/A | O75: =COUNTIF($A:$A,A75) -> 1 | P75: =IF(COUNTIF('DISPATCHED (VT11)'!$E:$E,'Summarized Plan'!A75)=0,"",COUNTIF('DISPATCHED (VT11)'!$E:$E,'Summarized Plan'!A75)) | Q75: =IF(A75="","",IF(ISNA(VLOOKUP(A75,'DISPATCHED (VT11)'!$E:$M,9,0)),"",VLOOKUP(A75,'DISPATCHED (VT11)'!$E:$M,9,0))) | R75: =IF(H75="","",IF(H75<#REF!,1,0)) -> #REF! | S75: =IF(H75="","",IF(H75>#REF!,1,0)) -> #REF! | T75: =IF(H75="","",IF(H75=#REF!,1,0)) -> #REF! | U75: =IF(I75="","",1)
... A89: 31021829 | B89: GRACE AND BETCHAY GROCERY PRODUCTS | F89: PULLOUT EMPTIES | H89: 46123 | M89: =VLOOKUP(B89,REFERENCE!$A$2:D298,4,0) -> FERDINAND ALVAREZ | N89: =VLOOKUP(B89,REFERENCE!A:C,3,FALSE) -> TAG-LWS | O89: =COUNTIF($A:$A,A89) -> 1 | P89: =IF(COUNTIF('DISPATCHED (VT11)'!$E:$E,'Summarized Plan'!A89)=0,"",COUNTIF('DISPATCHED (VT11)'!$E:$E,'Summarized Plan'!A89)) | Q89: =IF(A89="","",IF(ISNA(VLOOKUP(A89,'DISPATCHED (VT11)'!$E:$M,9,0)),"",VLOOKUP(A89,'DISPATCHED (VT11)'!$E:$M,9,0))) | R89: =IF(H89="","",IF(H89<#REF!,1,0)) -> #REF! | S89: =IF(H89="","",IF(H89>#REF!,1,0)) -> #REF! | T89: =IF(H89="","",IF(H89=#REF!,1,0)) -> #REF! | U89: =IF(I89="","",1)
A90: 31015462 | B90: RETCHY STORE | C90: 240 | E90: 8 | G90: TAG-PUP | H90: 46122 | M90: =VLOOKUP(B90,REFERENCE!$A$2:D301,4,0) -> FERDINAND ALVAREZ | N90: =VLOOKUP(B90,REFERENCE!A:C,3,FALSE) -> TAG-PUP | O90: =COUNTIF($A:$A,A90) -> 1 | P90: =IF(COUNTIF('DISPATCHED (VT11)'!$E:$E,'Summarized Plan'!A90)=0,"",COUNTIF('DISPATCHED (VT11)'!$E:$E,'Summarized Plan'!A90)) | Q90: =IF(A90="","",IF(ISNA(VLOOKUP(A90,'DISPATCHED (VT11)'!$E:$M,9,0)),"",VLOOKUP(A90,'DISPATCHED (VT11)'!$E:$M,9,0))) | R90: =IF(H90="","",IF(H90<#REF!,1,0)) -> #REF! | S90: =IF(H90="","",IF(H90>#REF!,1,0)) -> #REF! | T90: =IF(H90="","",IF(H90=#REF!,1,0)) -> #REF! | U90: =IF(I90="","",1)
A91: 31015463 | B91: RVD MERCHANDISING BEVERAGE WHOLESAL | C91: 446 | E91: 14 | G91: LP-PUP | H91: 46122 | M91: =VLOOKUP(B91,REFERENCE!$A$2:D302,4,0) -> ANDRE GORDONCILLO | N91: =VLOOKUP(B91,REFERENCE!A:C,3,FALSE) -> LP-PUP | O91: =COUNTIF($A:$A,A91) -> 1 | P91: =IF(COUNTIF('DISPATCHED (VT11)'!$E:$E,'Summarized Plan'!A91)=0,"",COUNTIF('DISPATCHED (VT11)'!$E:$E,'Summarized Plan'!A91)) -> 1 | Q91: =IF(A91="","",IF(ISNA(VLOOKUP(A91,'DISPATCHED (VT11)'!$E:$M,9,0)),"",VLOOKUP(A91,'DISPATCHED (VT11)'!$E:$M,9,0))) -> 446 | R91: =IF(H91="","",IF(H91<#REF!,1,0)) -> #REF! | S91: =IF(H91="","",IF(H91>#REF!,1,0)) -> #REF! | T91: =IF(H91="","",IF(H91=#REF!,1,0)) -> #REF! | U91: =IF(I91="","",1)
A92: 30860399 | B92: CCBPI_PARAÑAQUE DC | C92: 8 | D92: 1 | E92: 0.04 | H92: 46093 | I92: PICKUP | M92: =VLOOKUP(B92,REFERENCE!$A$2:D305,4,0) -> #N/A | N92: =VLOOKUP(B92,REFERENCE!A:C,3,FALSE) -> #N/A | O92: =COUNTIF($A:$A,A92) -> 1 | P92: =IF(COUNTIF('DISPATCHED (VT11)'!$E:$E,'Summarized Plan'!A92)=0,"",COUNTIF('DISPATCHED (VT11)'!$E:$E,'Summarized Plan'!A92)) | Q92: =IF(A92="","",IF(ISNA(VLOOKUP(A92,'DISPATCHED (VT11)'!$E:$M,9,0)),"",VLOOKUP(A92,'DISPATCHED (VT11)'!$E:$M,9,0))) | R92: =IF(H92="","",IF(H92<#REF!,1,0)) -> #REF! | S92: =IF(H92="","",IF(H92>#REF!,1,0)) -> #REF! | T92: =IF(H92="","",IF(H92=#REF!,1,0)) -> #REF! | U92: =IF(I92="","",1) -> 1
A93: 31021616 | B93: 4K SOFTDRINKS STORE | C93: 413 | E93: 10.16 | G93: LP-PUP | H93: 46123 | M93: =VLOOKUP(B93,REFERENCE!$A$2:D306,4,0) -> ANDRE GORDONCILLO | N93: =VLOOKUP(B93,REFERENCE!A:C,3,FALSE) -> LP-PUP | O93: =COUNTIF($A:$A,A93) -> 1 | P93: =IF(COUNTIF('DISPATCHED (VT11)'!$E:$E,'Summarized Plan'!A93)=0,"",COUNTIF('DISPATCHED (VT11)'!$E:$E,'Summarized Plan'!A93)) | Q93: =IF(A93="","",IF(ISNA(VLOOKUP(A93,'DISPATCHED (VT11)'!$E:$M,9,0)),"",VLOOKUP(A93,'DISPATCHED (VT11)'!$E:$M,9,0))) | R93: =IF(H93="","",IF(H93<#REF!,1,0)) -> #REF! | S93: =IF(H93="","",IF(H93>#REF!,1,0)) -> #REF! | T93: =IF(H93="","",IF(H93=#REF!,1,0)) -> #REF! | U93: =IF(I93="","",1)
A94: 31021619 | B94: CARRY ALL FOOD ENTERPRISES INC. | C94: 784 | E94: 14 | G94: TAG-PUP | H94: 46123 | M94: =VLOOKUP(B94,REFERENCE!$A$2:D307,4,0) -> FERDINAND ALVAREZ | N94: =VLOOKUP(B94,REFERENCE!A:C,3,FALSE) -> TAG-PUP | O94: =COUNTIF($A:$A,A94) -> 1 | P94: =IF(COUNTIF('DISPATCHED (VT11)'!$E:$E,'Summarized Plan'!A94)=0,"",COUNTIF('DISPATCHED (VT11)'!$E:$E,'Summarized Plan'!A94)) | Q94: =IF(A94="","",IF(ISNA(VLOOKUP(A94,'DISPATCHED (VT11)'!$E:$M,9,0)),"",VLOOKUP(A94,'DISPATCHED (VT11)'!$E:$M,9,0))) | R94: =IF(H94="","",IF(H94<#REF!,1,0)) -> #REF! | S94: =IF(H94="","",IF(H94>#REF!,1,0)) -> #REF! | T94: =IF(H94="","",IF(H94=#REF!,1,0)) -> #REF! | U94: =IF(I94="","",1)
A95: 31021626 | B95: DOCOLA GENERAL MERCHANDISE | C95: 570 | E95: 14.07 | G95: TAG-PUP | H95: 46123 | M95: =VLOOKUP(B95,REFERENCE!$A$2:D308,4,0) -> FERDINAND ALVAREZ | N95: =VLOOKUP(B95,REFERENCE!A:C,3,FALSE) -> TAG-PUP | O95: =COUNTIF($A:$A,A95) -> 1 | P95: =IF(COUNTIF('DISPATCHED (VT11)'!$E:$E,'Summarized Plan'!A95)=0,"",COUNTIF('DISPATCHED (VT11)'!$E:$E,'Summarized Plan'!A95)) | Q95: =IF(A95="","",IF(ISNA(VLOOKUP(A95,'DISPATCHED (VT11)'!$E:$M,9,0)),"",VLOOKUP(A95,'DISPATCHED (VT11)'!$E:$M,9,0))) | R95: =IF(H95="","",IF(H95<#REF!,1,0)) -> #REF! | S95: =IF(H95="","",IF(H95>#REF!,1,0)) -> #REF! | T95: =IF(H95="","",IF(H95=#REF!,1,0)) -> #REF! | U95: =IF(I95="","",1)
A96: 31021630 | B96: GIRON STORE 2 | C96: 144 | E96: 2.57 | G96: TAG-PUP | H96: 46123 | M96: =VLOOKUP(B96,REFERENCE!$A$2:D309,4,0) -> FERDINAND ALVAREZ | N96: =VLOOKUP(B96,REFERENCE!A:C,3,FALSE) -> TAG-PUP | O96: =COUNTIF($A:$A,A96) -> 1 | P96: =IF(COUNTIF('DISPATCHED (VT11)'!$E:$E,'Summarized Plan'!A96)=0,"",COUNTIF('DISPATCHED (VT11)'!$E:$E,'Summarized Plan'!A96)) | Q96: =IF(A96="","",IF(ISNA(VLOOKUP(A96,'DISPATCHED (VT11)'!$E:$M,9,0)),"",VLOOKUP(A96,'DISPATCHED (VT11)'!$E:$M,9,0))) | R96: =IF(H96="","",IF(H96<#REF!,1,0)) -> #REF! | S96: =IF(H96="","",IF(H96>#REF!,1,0)) -> #REF! | T96: =IF(H96="","",IF(H96=#REF!,1,0)) -> #REF! | U96: =IF(I96="","",1)
A97: 31021635 | B97: PERRY AND DORY STORE | C97: 472 | E97: 3.45 | G97: PAR-PUP | H97: 46123 | M97: =VLOOKUP(B97,REFERENCE!$A$2:D310,4,0) -> RONNIE ROMERO | N97: =VLOOKUP(B97,REFERENCE!A:C,3,FALSE) -> PAR-PUP | O97: =COUNTIF($A:$A,A97) -> 1 | P97: =IF(COUNTIF('DISPATCHED (VT11)'!$E:$E,'Summarized Plan'!A97)=0,"",COUNTIF('DISPATCHED (VT11)'!$E:$E,'Summarized Plan'!A97)) | Q97: =IF(A97="","",IF(ISNA(VLOOKUP(A97,'DISPATCHED (VT11)'!$E:$M,9,0)),"",VLOOKUP(A97,'DISPATCHED (VT11)'!$E:$M,9,0))) | R97: =IF(H97="","",IF(H97<#REF!,1,0)) -> #REF! | S97: =IF(H97="","",IF(H97>#REF!,1,0)) -> #REF! | T97: =IF(H97="","",IF(H97=#REF!,1,0)) -> #REF! | U97: =IF(I97="","",1)
A98: 31021636 | B98: RETCHY STORE | C98: 240 | E98: 8 | G98: TAG-PUP | H98: 46123 | M98: =VLOOKUP(B98,REFERENCE!$A$2:D311,4,0) -> FERDINAND ALVAREZ | N98: =VLOOKUP(B98,REFERENCE!A:C,3,FALSE) -> TAG-PUP | O98: =COUNTIF($A:$A,A98) -> 1 | P98: =IF(COUNTIF('DISPATCHED (VT11)'!$E:$E,'Summarized Plan'!A98)=0,"",COUNTIF('DISPATCHED (VT11)'!$E:$E,'Summarized Plan'!A98)) | Q98: =IF(A98="","",IF(ISNA(VLOOKUP(A98,'DISPATCHED (VT11)'!$E:$M,9,0)),"",VLOOKUP(A98,'DISPATCHED (VT11)'!$E:$M,9,0))) | R98: =IF(H98="","",IF(H98<#REF!,1,0)) -> #REF! | S98: =IF(H98="","",IF(H98>#REF!,1,0)) -> #REF! | T98: =IF(H98="","",IF(H98=#REF!,1,0)) -> #REF! | U98: =IF(I98="","",1)
A99: 31021640 | B99: RVD MERCHANDISING BEVERAGE WHOLESAL | C99: 440 | E99: 7.86 | G99: LP-PUP | H99: 46123 | M99: =VLOOKUP(B99,REFERENCE!$A$2:D312,4,0) -> ANDRE GORDONCILLO | N99: =VLOOKUP(B99,REFERENCE!A:C,3,FALSE) -> LP-PUP | O99: =COUNTIF($A:$A,A99) -> 1 | P99: =IF(COUNTIF('DISPATCHED (VT11)'!$E:$E,'Summarized Plan'!A99)=0,"",COUNTIF('DISPATCHED (VT11)'!$E:$E,'Summarized Plan'!A99)) -> 1 | Q99: =IF(A99="","",IF(ISNA(VLOOKUP(A99,'DISPATCHED (VT11)'!$E:$M,9,0)),"",VLOOKUP(A99,'DISPATCHED (VT11)'!$E:$M,9,0))) -> 440 | R99: =IF(H99="","",IF(H99<#REF!,1,0)) -> #REF! | S99: =IF(H99="","",IF(H99>#REF!,1,0)) -> #REF! | T99: =IF(H99="","",IF(H99=#REF!,1,0)) -> #REF! | U99: =IF(I99="","",1)
A100: 31021641 | B100: RVD MERCHANDISING BEVERAGE WHOLESAL | C100: 446 | E100: 14 | G100: LP-PUP | H100: 46123 | M100: =VLOOKUP(B100,REFERENCE!$A$2:D313,4,0) -> ANDRE GORDONCILLO | N100: =VLOOKUP(B100,REFERENCE!A:C,3,FALSE) -> LP-PUP | O100: =COUNTIF($A:$A,A100) -> 1 | P100: =IF(COUNTIF('DISPATCHED (VT11)'!$E:$E,'Summarized Plan'!A100)=0,"",COUNTIF('DISPATCHED (VT11)'!$E:$E,'Summarized Plan'!A100)) | Q100: =IF(A100="","",IF(ISNA(VLOOKUP(A100,'DISPATCHED (VT11)'!$E:$M,9,0)),"",VLOOKUP(A100,'DISPATCHED (VT11)'!$E:$M,9,0))) | R100: =IF(H100="","",IF(H100<#REF!,1,0)) -> #REF! | S100: =IF(H100="","",IF(H100>#REF!,1,0)) -> #REF! | T100: =IF(H100="","",IF(H100=#REF!,1,0)) -> #REF! | U100: =IF(I100="","",1)
A101: 31021642 | B101: RVD MERCHANDISING BEVERAGE WHOLESAL | C101: 275 | E101: 5.57 | G101: LP-PUP | H101: 46123 | M101: =VLOOKUP(B101,REFERENCE!$A$2:D314,4,0) -> ANDRE GORDONCILLO | N101: =VLOOKUP(B101,REFERENCE!A:C,3,FALSE) -> LP-PUP | O101: =COUNTIF($A:$A,A101) -> 1 | P101: =IF(COUNTIF('DISPATCHED (VT11)'!$E:$E,'Summarized Plan'!A101)=0,"",COUNTIF('DISPATCHED (VT11)'!$E:$E,'Summarized Plan'!A101)) -> 1 | Q101: =IF(A101="","",IF(ISNA(VLOOKUP(A101,'DISPATCHED (VT11)'!$E:$M,9,0)),"",VLOOKUP(A101,'DISPATCHED (VT11)'!$E:$M,9,0))) -> 275 | R101: =IF(H101="","",IF(H101<#REF!,1,0)) -> #REF! | S101: =IF(H101="","",IF(H101>#REF!,1,0)) -> #REF! | T101: =IF(H101="","",IF(H101=#REF!,1,0)) -> #REF! | U101: =IF(I101="","",1)
A102: 31023965 | B102: E.P. MERCADO TRADING | C102: 16 | E102: 0.48 | G102: LP-PUP | H102: 46123 | M102: =VLOOKUP(B102,REFERENCE!$A$2:D315,4,0) -> ANDRE GORDONCILLO | N102: =VLOOKUP(B102,REFERENCE!A:C,3,FALSE) -> LP-PUP | O102: =COUNTIF($A:$A,A102) -> 1 | P102: =IF(COUNTIF('DISPATCHED (VT11)'!$E:$E,'Summarized Plan'!A102)=0,"",COUNTIF('DISPATCHED (VT11)'!$E:$E,'Summarized Plan'!A102)) | Q102: =IF(A102="","",IF(ISNA(VLOOKUP(A102,'DISPATCHED (VT11)'!$E:$M,9,0)),"",VLOOKUP(A102,'DISPATCHED (VT11)'!$E:$M,9,0))) | R102: =IF(H102="","",IF(H102<#REF!,1,0)) -> #REF! | S102: =IF(H102="","",IF(H102>#REF!,1,0)) -> #REF! | T102: =IF(H102="","",IF(H102=#REF!,1,0)) -> #REF! | U102: =IF(I102="","",1)
A103: 31025266 | B103: DOCOLA GENERAL MERCHANDISE | G103: TAG-PUP | H103: 46123 | M103: =VLOOKUP(B103,REFERENCE!$A$2:D316,4,0) -> FERDINAND ALVAREZ | N103: =VLOOKUP(B103,REFERENCE!A:C,3,FALSE) -> TAG-PUP | O103: =COUNTIF($A:$A,A103) -> 1 | P103: =IF(COUNTIF('DISPATCHED (VT11)'!$E:$E,'Summarized Plan'!A103)=0,"",COUNTIF('DISPATCHED (VT11)'!$E:$E,'Summarized Plan'!A103)) | Q103: =IF(A103="","",IF(ISNA(VLOOKUP(A103,'DISPATCHED (VT11)'!$E:$M,9,0)),"",VLOOKUP(A103,'DISPATCHED (VT11)'!$E:$M,9,0))) | R103: =IF(H103="","",IF(H103<#REF!,1,0)) -> #REF! | S103: =IF(H103="","",IF(H103>#REF!,1,0)) -> #REF! | T103: =IF(H103="","",IF(H103=#REF!,1,0)) -> #REF! | U103: =IF(I103="","",1)
A104: 31028304 | B104: DOKLET SOFTDRINKS STORE | F104: PULLOUT EMPTIES | H104: 46125 | M104: =VLOOKUP(B104,REFERENCE!$A$2:D317,4,0) -> RONNIE ROMERO | N104: =VLOOKUP(B104,REFERENCE!A:C,3,FALSE) -> PAR-WS | O104: =COUNTIF($A:$A,A104) -> 1 | P104: =IF(COUNTIF('DISPATCHED (VT11)'!$E:$E,'Summarized Plan'!A104)=0,"",COUNTIF('DISPATCHED (VT11)'!$E:$E,'Summarized Plan'!A104)) | Q104: =IF(A104="","",IF(ISNA(VLOOKUP(A104,'DISPATCHED (VT11)'!$E:$M,9,0)),"",VLOOKUP(A104,'DISPATCHED (VT11)'!$E:$M,9,0))) | R104: =IF(H104="","",IF(H104<#REF!,1,0)) -> #REF! | S104: =IF(H104="","",IF(H104>#REF!,1,0)) -> #REF! | T104: =IF(H104="","",IF(H104=#REF!,1,0)) -> #REF! | U104: =IF(I104="","",1)
A105: 31028305 | B105: DOKLET SOFTDRINKS STORE | F105: PULLOUT EMPTIES | H105: 46125 | M105: =VLOOKUP(B105,REFERENCE!$A$2:D318,4,0) -> RONNIE ROMERO | N105: =VLOOKUP(B105,REFERENCE!A:C,3,FALSE) -> PAR-WS | O105: =COUNTIF($A:$A,A105) -> 1 | P105: =IF(COUNTIF('DISPATCHED (VT11)'!$E:$E,'Summarized Plan'!A105)=0,"",COUNTIF('DISPATCHED (VT11)'!$E:$E,'Summarized Plan'!A105)) | Q105: =IF(A105="","",IF(ISNA(VLOOKUP(A105,'DISPATCHED (VT11)'!$E:$M,9,0)),"",VLOOKUP(A105,'DISPATCHED (VT11)'!$E:$M,9,0))) | R105: =IF(H105="","",IF(H105<#REF!,1,0)) -> #REF! | S105: =IF(H105="","",IF(H105>#REF!,1,0)) -> #REF! | T105: =IF(H105="","",IF(H105=#REF!,1,0)) -> #REF! | U105: =IF(I105="","",1)
A106: 31028306 | B106: ERWIN S. OLIVA SARI SARI STORE | F106: PULLOUT EMPTIES | H106: 46125 | M106: =VLOOKUP(B106,REFERENCE!$A$2:D319,4,0) -> FERDINAND ALVAREZ | N106: =VLOOKUP(B106,REFERENCE!A:C,3,FALSE) -> TAG-DP | O106: =COUNTIF($A:$A,A106) -> 1 | P106: =IF(COUNTIF('DISPATCHED (VT11)'!$E:$E,'Summarized Plan'!A106)=0,"",COUNTIF('DISPATCHED (VT11)'!$E:$E,'Summarized Plan'!A106)) | Q106: =IF(A106="","",IF(ISNA(VLOOKUP(A106,'DISPATCHED (VT11)'!$E:$M,9,0)),"",VLOOKUP(A106,'DISPATCHED (VT11)'!$E:$M,9,0))) | R106: =IF(H106="","",IF(H106<#REF!,1,0)) -> #REF! | S106: =IF(H106="","",IF(H106>#REF!,1,0)) -> #REF! | T106: =IF(H106="","",IF(H106=#REF!,1,0)) -> #REF! | U106: =IF(I106="","",1)
A107: 31028307 | B107: ERWIN S. OLIVA SARI SARI STORE | F107: PULLOUT EMPTIES | H107: 46125 | M107: =VLOOKUP(B107,REFERENCE!$A$2:D320,4,0) -> FERDINAND ALVAREZ | N107: =VLOOKUP(B107,REFERENCE!A:C,3,FALSE) -> TAG-DP | O107: =COUNTIF($A:$A,A107) -> 1 | P107: =IF(COUNTIF('DISPATCHED (VT11)'!$E:$E,'Summarized Plan'!A107)=0,"",COUNTIF('DISPATCHED (VT11)'!$E:$E,'Summarized Plan'!A107)) | Q107: =IF(A107="","",IF(ISNA(VLOOKUP(A107,'DISPATCHED (VT11)'!$E:$M,9,0)),"",VLOOKUP(A107,'DISPATCHED (VT11)'!$E:$M,9,0))) | R107: =IF(H107="","",IF(H107<#REF!,1,0)) -> #REF! | S107: =IF(H107="","",IF(H107>#REF!,1,0)) -> #REF! | T107: =IF(H107="","",IF(H107=#REF!,1,0)) -> #REF! | U107: =IF(I107="","",1)
A108: 31028308 | B108: ERWIN S. OLIVA SARI SARI STORE | F108: PULLOUT EMPTIES | H108: 46125 | M108: =VLOOKUP(B108,REFERENCE!$A$2:D321,4,0) -> FERDINAND ALVAREZ | N108: =VLOOKUP(B108,REFERENCE!A:C,3,FALSE) -> TAG-DP | O108: =COUNTIF($A:$A,A108) -> 1 | P108: =IF(COUNTIF('DISPATCHED (VT11)'!$E:$E,'Summarized Plan'!A108)=0,"",COUNTIF('DISPATCHED (VT11)'!$E:$E,'Summarized Plan'!A108)) | Q108: =IF(A108="","",IF(ISNA(VLOOKUP(A108,'DISPATCHED (VT11)'!$E:$M,9,0)),"",VLOOKUP(A108,'DISPATCHED (VT11)'!$E:$M,9,0))) | R108: =IF(H108="","",IF(H108<#REF!,1,0)) -> #REF! | S108: =IF(H108="","",IF(H108>#REF!,1,0)) -> #REF! | T108: =IF(H108="","",IF(H108=#REF!,1,0)) -> #REF! | U108: =IF(I108="","",1)
A109: 31028309 | B109: ERWIN S. OLIVA SARI SARI STORE | F109: PULLOUT EMPTIES | H109: 46125 | M109: =VLOOKUP(B109,REFERENCE!$A$2:D322,4,0) -> FERDINAND ALVAREZ | N109: =VLOOKUP(B109,REFERENCE!A:C,3,FALSE) -> TAG-DP | O109: =COUNTIF($A:$A,A109) -> 1 | P109: =IF(COUNTIF('DISPATCHED (VT11)'!$E:$E,'Summarized Plan'!A109)=0,"",COUNTIF('DISPATCHED (VT11)'!$E:$E,'Summarized Plan'!A109)) | Q109: =IF(A109="","",IF(ISNA(VLOOKUP(A109,'DISPATCHED (VT11)'!$E:$M,9,0)),"",VLOOKUP(A109,'DISPATCHED (VT11)'!$E:$M,9,0))) | R109: =IF(H109="","",IF(H109<#REF!,1,0)) -> #REF! | S109: =IF(H109="","",IF(H109>#REF!,1,0)) -> #REF! | T109: =IF(H109="","",IF(H109=#REF!,1,0)) -> #REF! | U109: =IF(I109="","",1)
A110: 31028350 | B110: M.D CALO GEN. MERCHANDISE | F110: PULLOUT EMPTIES | H110: 46125 | M110: =VLOOKUP(B110,REFERENCE!$A$2:D323,4,0) -> FERDINAND ALVAREZ | N110: =VLOOKUP(B110,REFERENCE!A:C,3,FALSE) -> TAG-WS | O110: =COUNTIF($A:$A,A110) -> 1 | P110: =IF(COUNTIF('DISPATCHED (VT11)'!$E:$E,'Summarized Plan'!A110)=0,"",COUNTIF('DISPATCHED (VT11)'!$E:$E,'Summarized Plan'!A110)) | Q110: =IF(A110="","",IF(ISNA(VLOOKUP(A110,'DISPATCHED (VT11)'!$E:$M,9,0)),"",VLOOKUP(A110,'DISPATCHED (VT11)'!$E:$M,9,0))) | R110: =IF(H110="","",IF(H110<#REF!,1,0)) -> #REF! | S110: =IF(H110="","",IF(H110>#REF!,1,0)) -> #REF! | T110: =IF(H110="","",IF(H110=#REF!,1,0)) -> #REF! | U110: =IF(I110="","",1)
A111: 31028351 | B111: NERYMART MINI GROCERY | F111: PULLOUT EMPTIES | H111: 46125 | M111: =VLOOKUP(B111,REFERENCE!$A$2:D324,4,0) -> FERDINAND ALVAREZ | N111: =VLOOKUP(B111,REFERENCE!A:C,3,FALSE) -> TAG-DP | O111: =COUNTIF($A:$A,A111) -> 1 | P111: =IF(COUNTIF('DISPATCHED (VT11)'!$E:$E,'Summarized Plan'!A111)=0,"",COUNTIF('DISPATCHED (VT11)'!$E:$E,'Summarized Plan'!A111)) | Q111: =IF(A111="","",IF(ISNA(VLOOKUP(A111,'DISPATCHED (VT11)'!$E:$M,9,0)),"",VLOOKUP(A111,'DISPATCHED (VT11)'!$E:$M,9,0))) | R111: =IF(H111="","",IF(H111<#REF!,1,0)) -> #REF! | S111: =IF(H111="","",IF(H111>#REF!,1,0)) -> #REF! | T111: =IF(H111="","",IF(H111=#REF!,1,0)) -> #REF! | U111: =IF(I111="","",1)
A112: 31028352 | B112: NERYMART MINI GROCERY | F112: PULLOUT EMPTIES | H112: 46125 | M112: =VLOOKUP(B112,REFERENCE!$A$2:D325,4,0) -> FERDINAND ALVAREZ | N112: =VLOOKUP(B112,REFERENCE!A:C,3,FALSE) -> TAG-DP | O112: =COUNTIF($A:$A,A112) -> 1 | P112: =IF(COUNTIF('DISPATCHED (VT11)'!$E:$E,'Summarized Plan'!A112)=0,"",COUNTIF('DISPATCHED (VT11)'!$E:$E,'Summarized Plan'!A112)) | Q112: =IF(A112="","",IF(ISNA(VLOOKUP(A112,'DISPATCHED (VT11)'!$E:$M,9,0)),"",VLOOKUP(A112,'DISPATCHED (VT11)'!$E:$M,9,0))) | R112: =IF(H112="","",IF(H112<#REF!,1,0)) -> #REF! | S112: =IF(H112="","",IF(H112>#REF!,1,0)) -> #REF! | T112: =IF(H112="","",IF(H112=#REF!,1,0)) -> #REF! | U112: =IF(I112="","",1)
A113: 31027627 | B113: 4K SOFTDRINKS STORE | C113: 490 | D113: 1 | E113: 12 | H113: 46125 | M113: =VLOOKUP(B113,REFERENCE!$A$2:D326,4,0) -> ANDRE GORDONCILLO | N113: =VLOOKUP(B113,REFERENCE!A:C,3,FALSE) -> LP-PUP | O113: =COUNTIF($A:$A,A113) -> 1 | P113: =IF(COUNTIF('DISPATCHED (VT11)'!$E:$E,'Summarized Plan'!A113)=0,"",COUNTIF('DISPATCHED (VT11)'!$E:$E,'Summarized Plan'!A113)) -> 1 | Q113: =IF(A113="","",IF(ISNA(VLOOKUP(A113,'DISPATCHED (VT11)'!$E:$M,9,0)),"",VLOOKUP(A113,'DISPATCHED (VT11)'!$E:$M,9,0))) -> 490 | R113: =IF(H113="","",IF(H113<#REF!,1,0)) -> #REF! | S113: =IF(H113="","",IF(H113>#REF!,1,0)) -> #REF! | T113: =IF(H113="","",IF(H113=#REF!,1,0)) -> #REF! | U113: =IF(I113="","",1)
A114: 31027628 | B114: 4K SOFTDRINKS STORE | C114: 73 | D114: 1 | E114: 2.23 | G114: =+N114 -> LP-PUP | H114: 46125 | M114: =VLOOKUP(B114,REFERENCE!$A$2:D327,4,0) -> ANDRE GORDONCILLO | N114: =VLOOKUP(B114,REFERENCE!A:C,3,FALSE) -> LP-PUP | O114: =COUNTIF($A:$A,A114) -> 1 | P114: =IF(COUNTIF('DISPATCHED (VT11)'!$E:$E,'Summarized Plan'!A114)=0,"",COUNTIF('DISPATCHED (VT11)'!$E:$E,'Summarized Plan'!A114)) | Q114: =IF(A114="","",IF(ISNA(VLOOKUP(A114,'DISPATCHED (VT11)'!$E:$M,9,0)),"",VLOOKUP(A114,'DISPATCHED (VT11)'!$E:$M,9,0))) | R114: =IF(H114="","",IF(H114<#REF!,1,0)) -> #REF! | S114: =IF(H114="","",IF(H114>#REF!,1,0)) -> #REF! | T114: =IF(H114="","",IF(H114=#REF!,1,0)) -> #REF! | U114: =IF(I114="","",1)
A115: 31027629 | B115: CARRY ALL FOOD ENTERPRISES INC. | C115: 420 | D115: 1 | E115: 14 | G115: =+N115 -> TAG-PUP | H115: 46125 | M115: =VLOOKUP(B115,REFERENCE!$A$2:D328,4,0) -> FERDINAND ALVAREZ | N115: =VLOOKUP(B115,REFERENCE!A:C,3,FALSE) -> TAG-PUP | O115: =COUNTIF($A:$A,A115) -> 1 | P115: =IF(COUNTIF('DISPATCHED (VT11)'!$E:$E,'Summarized Plan'!A115)=0,"",COUNTIF('DISPATCHED (VT11)'!$E:$E,'Summarized Plan'!A115)) | Q115: =IF(A115="","",IF(ISNA(VLOOKUP(A115,'DISPATCHED (VT11)'!$E:$M,9,0)),"",VLOOKUP(A115,'DISPATCHED (VT11)'!$E:$M,9,0))) | R115: =IF(H115="","",IF(H115<#REF!,1,0)) -> #REF! | S115: =IF(H115="","",IF(H115>#REF!,1,0)) -> #REF! | T115: =IF(H115="","",IF(H115=#REF!,1,0)) -> #REF! | U115: =IF(I115="","",1)
A116: 31027650 | B116: CARRY ALL FOOD ENTERPRISES INC. | C116: 420 | D116: 1 | E116: 14 | G116: =+N116 -> TAG-PUP | H116: 46125 | M116: =VLOOKUP(B116,REFERENCE!$A$2:D329,4,0) -> FERDINAND ALVAREZ | N116: =VLOOKUP(B116,REFERENCE!A:C,3,FALSE) -> TAG-PUP | O116: =COUNTIF($A:$A,A116) -> 1 | P116: =IF(COUNTIF('DISPATCHED (VT11)'!$E:$E,'Summarized Plan'!A116)=0,"",COUNTIF('DISPATCHED (VT11)'!$E:$E,'Summarized Plan'!A116)) | Q116: =IF(A116="","",IF(ISNA(VLOOKUP(A116,'DISPATCHED (VT11)'!$E:$M,9,0)),"",VLOOKUP(A116,'DISPATCHED (VT11)'!$E:$M,9,0))) | R116: =IF(H116="","",IF(H116<#REF!,1,0)) -> #REF! | S116: =IF(H116="","",IF(H116>#REF!,1,0)) -> #REF! | T116: =IF(H116="","",IF(H116=#REF!,1,0)) -> #REF! | U116: =IF(I116="","",1)
A117: 31027651 | B117: CARRY ALL FOOD ENTERPRISES INC. | C117: 420 | D117: 1 | E117: 14 | G117: =+N117 -> TAG-PUP | H117: 46125 | M117: =VLOOKUP(B117,REFERENCE!$A$2:D330,4,0) -> FERDINAND ALVAREZ | N117: =VLOOKUP(B117,REFERENCE!A:C,3,FALSE) -> TAG-PUP | O117: =COUNTIF($A:$A,A117) -> 1 | P117: =IF(COUNTIF('DISPATCHED (VT11)'!$E:$E,'Summarized Plan'!A117)=0,"",COUNTIF('DISPATCHED (VT11)'!$E:$E,'Summarized Plan'!A117)) -> 1 | Q117: =IF(A117="","",IF(ISNA(VLOOKUP(A117,'DISPATCHED (VT11)'!$E:$M,9,0)),"",VLOOKUP(A117,'DISPATCHED (VT11)'!$E:$M,9,0))) -> 420 | R117: =IF(H117="","",IF(H117<#REF!,1,0)) -> #REF! | S117: =IF(H117="","",IF(H117>#REF!,1,0)) -> #REF! | T117: =IF(H117="","",IF(H117=#REF!,1,0)) -> #REF! | U117: =IF(I117="","",1)
A118: 31027652 | B118: CARRY ALL FOOD ENTERPRISES INC. | C118: 420 | D118: 1 | E118: 14 | G118: =+N118 -> TAG-PUP | H118: 46125 | M118: =VLOOKUP(B118,REFERENCE!$A$2:D331,4,0) -> FERDINAND ALVAREZ | N118: =VLOOKUP(B118,REFERENCE!A:C,3,FALSE) -> TAG-PUP | O118: =COUNTIF($A:$A,A118) -> 1 | P118: =IF(COUNTIF('DISPATCHED (VT11)'!$E:$E,'Summarized Plan'!A118)=0,"",COUNTIF('DISPATCHED (VT11)'!$E:$E,'Summarized Plan'!A118)) -> 1 | Q118: =IF(A118="","",IF(ISNA(VLOOKUP(A118,'DISPATCHED (VT11)'!$E:$M,9,0)),"",VLOOKUP(A118,'DISPATCHED (VT11)'!$E:$M,9,0))) -> 420 | R118: =IF(H118="","",IF(H118<#REF!,1,0)) -> #REF! | S118: =IF(H118="","",IF(H118>#REF!,1,0)) -> #REF! | T118: =IF(H118="","",IF(H118=#REF!,1,0)) -> #REF! | U118: =IF(I118="","",1)
A119: 31027653 | B119: CARRY ALL FOOD ENTERPRISES INC. | C119: 784 | D119: 1 | E119: 14 | G119: =+N119 -> TAG-PUP | H119: 46125 | M119: =VLOOKUP(B119,REFERENCE!$A$2:D332,4,0) -> FERDINAND ALVAREZ | N119: =VLOOKUP(B119,REFERENCE!A:C,3,FALSE) -> TAG-PUP | O119: =COUNTIF($A:$A,A119) -> 1 | P119: =IF(COUNTIF('DISPATCHED (VT11)'!$E:$E,'Summarized Plan'!A119)=0,"",COUNTIF('DISPATCHED (VT11)'!$E:$E,'Summarized Plan'!A119)) | Q119: =IF(A119="","",IF(ISNA(VLOOKUP(A119,'DISPATCHED (VT11)'!$E:$M,9,0)),"",VLOOKUP(A119,'DISPATCHED (VT11)'!$E:$M,9,0))) | R119: =IF(H119="","",IF(H119<#REF!,1,0)) -> #REF! | S119: =IF(H119="","",IF(H119>#REF!,1,0)) -> #REF! | T119: =IF(H119="","",IF(H119=#REF!,1,0)) -> #REF! | U119: =IF(I119="","",1)
A120: 31027654 | B120: CARRY ALL FOOD ENTERPRISES INC. | C120: 784 | D120: 1 | E120: 14 | G120: =+N120 -> TAG-PUP | H120: 46125 | M120: =VLOOKUP(B120,REFERENCE!$A$2:D333,4,0) -> FERDINAND ALVAREZ | N120: =VLOOKUP(B120,REFERENCE!A:C,3,FALSE) -> TAG-PUP | O120: =COUNTIF($A:$A,A120) -> 1 | P120: =IF(COUNTIF('DISPATCHED (VT11)'!$E:$E,'Summarized Plan'!A120)=0,"",COUNTIF('DISPATCHED (VT11)'!$E:$E,'Summarized Plan'!A120)) | Q120: =IF(A120="","",IF(ISNA(VLOOKUP(A120,'DISPATCHED (VT11)'!$E:$M,9,0)),"",VLOOKUP(A120,'DISPATCHED (VT11)'!$E:$M,9,0))) | R120: =IF(H120="","",IF(H120<#REF!,1,0)) -> #REF! | S120: =IF(H120="","",IF(H120>#REF!,1,0)) -> #REF! | T120: =IF(H120="","",IF(H120=#REF!,1,0)) -> #REF! | U120: =IF(I120="","",1)
A121: 31027655 | B121: CARRY ALL FOOD ENTERPRISES INC. | C121: 92 | D121: 1 | E121: 1.64 | G121: =+N121 -> TAG-PUP | H121: 46125 | M121: =VLOOKUP(B121,REFERENCE!$A$2:D334,4,0) -> FERDINAND ALVAREZ | N121: =VLOOKUP(B121,REFERENCE!A:C,3,FALSE) -> TAG-PUP | O121: =COUNTIF($A:$A,A121) -> 1 | P121: =IF(COUNTIF('DISPATCHED (VT11)'!$E:$E,'Summarized Plan'!A121)=0,"",COUNTIF('DISPATCHED (VT11)'!$E:$E,'Summarized Plan'!A121)) | Q121: =IF(A121="","",IF(ISNA(VLOOKUP(A121,'DISPATCHED (VT11)'!$E:$M,9,0)),"",VLOOKUP(A121,'DISPATCHED (VT11)'!$E:$M,9,0))) | R121: =IF(H121="","",IF(H121<#REF!,1,0)) -> #REF! | S121: =IF(H121="","",IF(H121>#REF!,1,0)) -> #REF! | T121: =IF(H121="","",IF(H121=#REF!,1,0)) -> #REF! | U121: =IF(I121="","",1)
A122: 31027656 | B122: CARRY ALL FOOD ENTERPRISES INC. | C122: 1530 | D122: 1 | E122: 12.5 | G122: =+N122 -> TAG-PUP | H122: 46125 | M122: =VLOOKUP(B122,REFERENCE!$A$2:D335,4,0) -> FERDINAND ALVAREZ | N122: =VLOOKUP(B122,REFERENCE!A:C,3,FALSE) -> TAG-PUP | O122: =COUNTIF($A:$A,A122) -> 1 | P122: =IF(COUNTIF('DISPATCHED (VT11)'!$E:$E,'Summarized Plan'!A122)=0,"",COUNTIF('DISPATCHED (VT11)'!$E:$E,'Summarized Plan'!A122)) | Q122: =IF(A122="","",IF(ISNA(VLOOKUP(A122,'DISPATCHED (VT11)'!$E:$M,9,0)),"",VLOOKUP(A122,'DISPATCHED (VT11)'!$E:$M,9,0))) | R122: =IF(H122="","",IF(H122<#REF!,1,0)) -> #REF! | S122: =IF(H122="","",IF(H122>#REF!,1,0)) -> #REF! | T122: =IF(H122="","",IF(H122=#REF!,1,0)) -> #REF! | U122: =IF(I122="","",1)
A123: 31027657 | B123: CARRY ALL FOOD ENTERPRISES INC. | C123: 670 | D123: 1 | E123: 13.4 | G123: =+N123 -> TAG-PUP | H123: 46125 | M123: =VLOOKUP(B123,REFERENCE!$A$2:D336,4,0) -> FERDINAND ALVAREZ | N123: =VLOOKUP(B123,REFERENCE!A:C,3,FALSE) -> TAG-PUP | O123: =COUNTIF($A:$A,A123) -> 1 | P123: =IF(COUNTIF('DISPATCHED (VT11)'!$E:$E,'Summarized Plan'!A123)=0,"",COUNTIF('DISPATCHED (VT11)'!$E:$E,'Summarized Plan'!A123)) | Q123: =IF(A123="","",IF(ISNA(VLOOKUP(A123,'DISPATCHED (VT11)'!$E:$M,9,0)),"",VLOOKUP(A123,'DISPATCHED (VT11)'!$E:$M,9,0))) | R123: =IF(H123="","",IF(H123<#REF!,1,0)) -> #REF! | S123: =IF(H123="","",IF(H123>#REF!,1,0)) -> #REF! | T123: =IF(H123="","",IF(H123=#REF!,1,0)) -> #REF! | U123: =IF(I123="","",1)
A124: 31027658 | B124: CARRY ALL FOOD ENTERPRISES INC. | C124: 392 | D124: 1 | E124: 2.79 | G124: =+N124 -> TAG-PUP | H124: 46125 | M124: =VLOOKUP(B124,REFERENCE!$A$2:D337,4,0) -> FERDINAND ALVAREZ | N124: =VLOOKUP(B124,REFERENCE!A:C,3,FALSE) -> TAG-PUP | O124: =COUNTIF($A:$A,A124) -> 1 | P124: =IF(COUNTIF('DISPATCHED (VT11)'!$E:$E,'Summarized Plan'!A124)=0,"",COUNTIF('DISPATCHED (VT11)'!$E:$E,'Summarized Plan'!A124)) | Q124: =IF(A124="","",IF(ISNA(VLOOKUP(A124,'DISPATCHED (VT11)'!$E:$M,9,0)),"",VLOOKUP(A124,'DISPATCHED (VT11)'!$E:$M,9,0))) | R124: =IF(H124="","",IF(H124<#REF!,1,0)) -> #REF! | S124: =IF(H124="","",IF(H124>#REF!,1,0)) -> #REF! | T124: =IF(H124="","",IF(H124=#REF!,1,0)) -> #REF! | U124: =IF(I124="","",1)
A125: 31027659 | B125: DOCOLA GENERAL MERCHANDISE | C125: 868 | D125: 2 | E125: 12.23 | G125: =+N125 -> TAG-PUP | H125: 46125 | M125: =VLOOKUP(B125,REFERENCE!$A$2:D338,4,0) -> FERDINAND ALVAREZ | N125: =VLOOKUP(B125,REFERENCE!A:C,3,FALSE) -> TAG-PUP | O125: =COUNTIF($A:$A,A125) -> 1 | P125: =IF(COUNTIF('DISPATCHED (VT11)'!$E:$E,'Summarized Plan'!A125)=0,"",COUNTIF('DISPATCHED (VT11)'!$E:$E,'Summarized Plan'!A125)) | Q125: =IF(A125="","",IF(ISNA(VLOOKUP(A125,'DISPATCHED (VT11)'!$E:$M,9,0)),"",VLOOKUP(A125,'DISPATCHED (VT11)'!$E:$M,9,0))) | R125: =IF(H125="","",IF(H125<#REF!,1,0)) -> #REF! | S125: =IF(H125="","",IF(H125>#REF!,1,0)) -> #REF! | T125: =IF(H125="","",IF(H125=#REF!,1,0)) -> #REF! | U125: =IF(I125="","",1)
... A129: 31027661 | B129: EP. MERCADO TRADING | C129: 352 | D129: 1 | E129: 10 | G129: =+N129 -> LP-PUP | H129: 46125 | M129: =VLOOKUP(B129,REFERENCE!$A$2:D342,4,0) -> FERDINAND ALVAREZ | N129: =VLOOKUP(B129,REFERENCE!A:C,3,FALSE) -> LP-PUP | O129: =COUNTIF($A:$A,A129) -> 1 | P129: =IF(COUNTIF('DISPATCHED (VT11)'!$E:$E,'Summarized Plan'!A129)=0,"",COUNTIF('DISPATCHED (VT11)'!$E:$E,'Summarized Plan'!A129)) | Q129: =IF(A129="","",IF(ISNA(VLOOKUP(A129,'DISPATCHED (VT11)'!$E:$M,9,0)),"",VLOOKUP(A129,'DISPATCHED (VT11)'!$E:$M,9,0))) | R129: =IF(H129="","",IF(H129<#REF!,1,0)) -> #REF! | S129: =IF(H129="","",IF(H129>#REF!,1,0)) -> #REF! | T129: =IF(H129="","",IF(H129=#REF!,1,0)) -> #REF! | U129: =IF(I129="","",1)
A130: 31032031 | B130: DP GENERO ENTERPRISE | C130: 600 | D130: 1 | G130: =+N130 -> LP-PUP | H130: 46125 | M130: =VLOOKUP(B130,REFERENCE!$A$2:D343,4,0) -> ANDRE GORDONCILLO | N130: =VLOOKUP(B130,REFERENCE!A:C,3,FALSE) -> LP-PUP | O130: =COUNTIF($A:$A,A130) -> 1 | P130: =IF(COUNTIF('DISPATCHED (VT11)'!$E:$E,'Summarized Plan'!A130)=0,"",COUNTIF('DISPATCHED (VT11)'!$E:$E,'Summarized Plan'!A130)) | Q130: =IF(A130="","",IF(ISNA(VLOOKUP(A130,'DISPATCHED (VT11)'!$E:$M,9,0)),"",VLOOKUP(A130,'DISPATCHED (VT11)'!$E:$M,9,0))) | R130: =IF(H130="","",IF(H130<#REF!,1,0)) -> #REF! | S130: =IF(H130="","",IF(H130>#REF!,1,0)) -> #REF! | T130: =IF(H130="","",IF(H130=#REF!,1,0)) -> #REF! | U130: =IF(I130="","",1)
A131: 31032032 | B131: DP GENERO ENTERPRISE | C131: 730 | D131: 1 | G131: =+N131 -> LP-PUP | H131: 46125 | M131: =VLOOKUP(B131,REFERENCE!$A$2:D344,4,0) -> ANDRE GORDONCILLO | N131: =VLOOKUP(B131,REFERENCE!A:C,3,FALSE) -> LP-PUP | O131: =COUNTIF($A:$A,A131) -> 1 | P131: =IF(COUNTIF('DISPATCHED (VT11)'!$E:$E,'Summarized Plan'!A131)=0,"",COUNTIF('DISPATCHED (VT11)'!$E:$E,'Summarized Plan'!A131)) | Q131: =IF(A131="","",IF(ISNA(VLOOKUP(A131,'DISPATCHED (VT11)'!$E:$M,9,0)),"",VLOOKUP(A131,'DISPATCHED (VT11)'!$E:$M,9,0))) | R131: =IF(H131="","",IF(H131<#REF!,1,0)) -> #REF! | S131: =IF(H131="","",IF(H131>#REF!,1,0)) -> #REF! | T131: =IF(H131="","",IF(H131=#REF!,1,0)) -> #REF! | U131: =IF(I131="","",1)
A132: 31032033 | B132: DP GENERO ENTERPRISE | C132: 952 | D132: 1 | G132: =+N132 -> LP-PUP | H132: 46125 | M132: =VLOOKUP(B132,REFERENCE!$A$2:D345,4,0) -> ANDRE GORDONCILLO | N132: =VLOOKUP(B132,REFERENCE!A:C,3,FALSE) -> LP-PUP | O132: =COUNTIF($A:$A,A132) -> 1 | P132: =IF(COUNTIF('DISPATCHED (VT11)'!$E:$E,'Summarized Plan'!A132)=0,"",COUNTIF('DISPATCHED (VT11)'!$E:$E,'Summarized Plan'!A132)) | Q132: =IF(A132="","",IF(ISNA(VLOOKUP(A132,'DISPATCHED (VT11)'!$E:$M,9,0)),"",VLOOKUP(A132,'DISPATCHED (VT11)'!$E:$M,9,0))) | R132: =IF(H132="","",IF(H132<#REF!,1,0)) -> #REF! | S132: =IF(H132="","",IF(H132>#REF!,1,0)) -> #REF! | T132: =IF(H132="","",IF(H132=#REF!,1,0)) -> #REF! | U132: =IF(I132="","",1)
A133: 31027662 | B133: GIRON STORE 2 | C133: 255 | D133: 1 | E133: 5.71 | G133: =+N133 -> TAG-PUP | H133: 46125 | M133: =VLOOKUP(B133,REFERENCE!$A$2:D346,4,0) -> FERDINAND ALVAREZ | N133: =VLOOKUP(B133,REFERENCE!A:C,3,FALSE) -> TAG-PUP | O133: =COUNTIF($A:$A,A133) -> 1 | P133: =IF(COUNTIF('DISPATCHED (VT11)'!$E:$E,'Summarized Plan'!A133)=0,"",COUNTIF('DISPATCHED (VT11)'!$E:$E,'Summarized Plan'!A133)) | Q133: =IF(A133="","",IF(ISNA(VLOOKUP(A133,'DISPATCHED (VT11)'!$E:$M,9,0)),"",VLOOKUP(A133,'DISPATCHED (VT11)'!$E:$M,9,0))) | R133: =IF(H133="","",IF(H133<#REF!,1,0)) -> #REF! | S133: =IF(H133="","",IF(H133>#REF!,1,0)) -> #REF! | T133: =IF(H133="","",IF(H133=#REF!,1,0)) -> #REF! | U133: =IF(I133="","",1)
A134: 31027664 | B134: JMP SARI-SARI STORE | C134: 366 | D134: 2 | E134: 6.57 | G134: =+N134 -> PAR-PUP | H134: 46125 | M134: =VLOOKUP(B134,REFERENCE!$A$2:D347,4,0) -> RONNIE ROMERO | N134: =VLOOKUP(B134,REFERENCE!A:C,3,FALSE) -> PAR-PUP | O134: =COUNTIF($A:$A,A134) -> 1 | P134: =IF(COUNTIF('DISPATCHED (VT11)'!$E:$E,'Summarized Plan'!A134)=0,"",COUNTIF('DISPATCHED (VT11)'!$E:$E,'Summarized Plan'!A134)) | Q134: =IF(A134="","",IF(ISNA(VLOOKUP(A134,'DISPATCHED (VT11)'!$E:$M,9,0)),"",VLOOKUP(A134,'DISPATCHED (VT11)'!$E:$M,9,0))) | R134: =IF(H134="","",IF(H134<#REF!,1,0)) -> #REF! | S134: =IF(H134="","",IF(H134>#REF!,1,0)) -> #REF! | T134: =IF(H134="","",IF(H134=#REF!,1,0)) -> #REF! | U134: =IF(I134="","",1)
A135: 31027666 | B135: PERRY AND DORY STORE | C135: 560 | D135: 1 | E135: 10 | G135: =+N135 -> PAR-PUP | H135: 46125 | M135: =VLOOKUP(B135,REFERENCE!$A$2:D348,4,0) -> RONNIE ROMERO | N135: =VLOOKUP(B135,REFERENCE!A:C,3,FALSE) -> PAR-PUP | O135: =COUNTIF($A:$A,A135) -> 1 | P135: =IF(COUNTIF('DISPATCHED (VT11)'!$E:$E,'Summarized Plan'!A135)=0,"",COUNTIF('DISPATCHED (VT11)'!$E:$E,'Summarized Plan'!A135)) | Q135: =IF(A135="","",IF(ISNA(VLOOKUP(A135,'DISPATCHED (VT11)'!$E:$M,9,0)),"",VLOOKUP(A135,'DISPATCHED (VT11)'!$E:$M,9,0))) | R135: =IF(H135="","",IF(H135<#REF!,1,0)) -> #REF! | S135: =IF(H135="","",IF(H135>#REF!,1,0)) -> #REF! | T135: =IF(H135="","",IF(H135=#REF!,1,0)) -> #REF! | U135: =IF(I135="","",1)
A136: 31027667 | B136: PERRY AND DORY STORE | C136: 560 | D136: 1 | E136: 10 | G136: =+N136 -> PAR-PUP | H136: 46125 | M136: =VLOOKUP(B136,REFERENCE!$A$2:D349,4,0) -> RONNIE ROMERO | N136: =VLOOKUP(B136,REFERENCE!A:C,3,FALSE) -> PAR-PUP | O136: =COUNTIF($A:$A,A136) -> 1 | P136: =IF(COUNTIF('DISPATCHED (VT11)'!$E:$E,'Summarized Plan'!A136)=0,"",COUNTIF('DISPATCHED (VT11)'!$E:$E,'Summarized Plan'!A136)) | Q136: =IF(A136="","",IF(ISNA(VLOOKUP(A136,'DISPATCHED (VT11)'!$E:$M,9,0)),"",VLOOKUP(A136,'DISPATCHED (VT11)'!$E:$M,9,0))) | R136: =IF(H136="","",IF(H136<#REF!,1,0)) -> #REF! | S136: =IF(H136="","",IF(H136>#REF!,1,0)) -> #REF! | T136: =IF(H136="","",IF(H136=#REF!,1,0)) -> #REF! | U136: =IF(I136="","",1)
A137: 31027668 | B137: PERRY AND DORY STORE | C137: 493 | D137: 1 | E137: 10.48 | G137: =+N137 -> PAR-PUP | H137: 46125 | M137: =VLOOKUP(B137,REFERENCE!$A$2:D350,4,0) -> RONNIE ROMERO | N137: =VLOOKUP(B137,REFERENCE!A:C,3,FALSE) -> PAR-PUP | O137: =COUNTIF($A:$A,A137) -> 1 | P137: =IF(COUNTIF('DISPATCHED (VT11)'!$E:$E,'Summarized Plan'!A137)=0,"",COUNTIF('DISPATCHED (VT11)'!$E:$E,'Summarized Plan'!A137)) | Q137: =IF(A137="","",IF(ISNA(VLOOKUP(A137,'DISPATCHED (VT11)'!$E:$M,9,0)),"",VLOOKUP(A137,'DISPATCHED (VT11)'!$E:$M,9,0))) | R137: =IF(H137="","",IF(H137<#REF!,1,0)) -> #REF! | S137: =IF(H137="","",IF(H137>#REF!,1,0)) -> #REF! | T137: =IF(H137="","",IF(H137=#REF!,1,0)) -> #REF! | U137: =IF(I137="","",1)
A138: 31027669 | B138: RETCHY STORE | C138: 344 | D138: 1 | E138: 8 | G138: =+N138 -> TAG-PUP | H138: 46125 | M138: =VLOOKUP(B138,REFERENCE!$A$2:D351,4,0) -> FERDINAND ALVAREZ | N138: =VLOOKUP(B138,REFERENCE!A:C,3,FALSE) -> TAG-PUP | O138: =COUNTIF($A:$A,A138) -> 1 | P138: =IF(COUNTIF('DISPATCHED (VT11)'!$E:$E,'Summarized Plan'!A138)=0,"",COUNTIF('DISPATCHED (VT11)'!$E:$E,'Summarized Plan'!A138)) | Q138: =IF(A138="","",IF(ISNA(VLOOKUP(A138,'DISPATCHED (VT11)'!$E:$M,9,0)),"",VLOOKUP(A138,'DISPATCHED (VT11)'!$E:$M,9,0))) | R138: =IF(H138="","",IF(H138<#REF!,1,0)) -> #REF! | S138: =IF(H138="","",IF(H138>#REF!,1,0)) -> #REF! | T138: =IF(H138="","",IF(H138=#REF!,1,0)) -> #REF! | U138: =IF(I138="","",1)
A139: 31027670 | B139: RETCHY STORE | C139: 344 | D139: 1 | E139: 8 | G139: =+N139 -> TAG-PUP | H139: 46125 | M139: =VLOOKUP(B139,REFERENCE!$A$2:D352,4,0) -> FERDINAND ALVAREZ | N139: =VLOOKUP(B139,REFERENCE!A:C,3,FALSE) -> TAG-PUP | O139: =COUNTIF($A:$A,A139) -> 1 | P139: =IF(COUNTIF('DISPATCHED (VT11)'!$E:$E,'Summarized Plan'!A139)=0,"",COUNTIF('DISPATCHED (VT11)'!$E:$E,'Summarized Plan'!A139)) | Q139: =IF(A139="","",IF(ISNA(VLOOKUP(A139,'DISPATCHED (VT11)'!$E:$M,9,0)),"",VLOOKUP(A139,'DISPATCHED (VT11)'!$E:$M,9,0))) | R139: =IF(H139="","",IF(H139<#REF!,1,0)) -> #REF! | S139: =IF(H139="","",IF(H139>#REF!,1,0)) -> #REF! | T139: =IF(H139="","",IF(H139=#REF!,1,0)) -> #REF! | U139: =IF(I139="","",1)
A140: 31027671 | B140: RETCHY STORE | C140: 344 | D140: 1 | E140: 8 | G140: =+N140 -> TAG-PUP | H140: 46125 | M140: =VLOOKUP(B140,REFERENCE!$A$2:D353,4,0) -> FERDINAND ALVAREZ | N140: =VLOOKUP(B140,REFERENCE!A:C,3,FALSE) -> TAG-PUP | O140: =COUNTIF($A:$A,A140) -> 1 | P140: =IF(COUNTIF('DISPATCHED (VT11)'!$E:$E,'Summarized Plan'!A140)=0,"",COUNTIF('DISPATCHED (VT11)'!$E:$E,'Summarized Plan'!A140)) | Q140: =IF(A140="","",IF(ISNA(VLOOKUP(A140,'DISPATCHED (VT11)'!$E:$M,9,0)),"",VLOOKUP(A140,'DISPATCHED (VT11)'!$E:$M,9,0))) | R140: =IF(H140="","",IF(H140<#REF!,1,0)) -> #REF! | S140: =IF(H140="","",IF(H140>#REF!,1,0)) -> #REF! | T140: =IF(H140="","",IF(H140=#REF!,1,0)) -> #REF! | U140: =IF(I140="","",1)
A141: 31027672 | B141: RETCHY STORE | C141: 448 | D141: 1 | E141: 8.01 | G141: =+N141 -> TAG-PUP | H141: 46125 | M141: =VLOOKUP(B141,REFERENCE!$A$2:D354,4,0) -> FERDINAND ALVAREZ | N141: =VLOOKUP(B141,REFERENCE!A:C,3,FALSE) -> TAG-PUP | O141: =COUNTIF($A:$A,A141) -> 1 | P141: =IF(COUNTIF('DISPATCHED (VT11)'!$E:$E,'Summarized Plan'!A141)=0,"",COUNTIF('DISPATCHED (VT11)'!$E:$E,'Summarized Plan'!A141)) -> 1 | Q141: =IF(A141="","",IF(ISNA(VLOOKUP(A141,'DISPATCHED (VT11)'!$E:$M,9,0)),"",VLOOKUP(A141,'DISPATCHED (VT11)'!$E:$M,9,0))) -> 448 | R141: =IF(H141="","",IF(H141<#REF!,1,0)) -> #REF! | S141: =IF(H141="","",IF(H141>#REF!,1,0)) -> #REF! | T141: =IF(H141="","",IF(H141=#REF!,1,0)) -> #REF! | U141: =IF(I141="","",1)
A142: 31027673 | B142: RETCHY STORE | C142: 176 | D142: 1 | E142: 3.37 | G142: =+N142 -> TAG-PUP | H142: 46125 | M142: =VLOOKUP(B142,REFERENCE!$A$2:D355,4,0) -> FERDINAND ALVAREZ | N142: =VLOOKUP(B142,REFERENCE!A:C,3,FALSE) -> TAG-PUP | O142: =COUNTIF($A:$A,A142) -> 1 | P142: =IF(COUNTIF('DISPATCHED (VT11)'!$E:$E,'Summarized Plan'!A142)=0,"",COUNTIF('DISPATCHED (VT11)'!$E:$E,'Summarized Plan'!A142)) | Q142: =IF(A142="","",IF(ISNA(VLOOKUP(A142,'DISPATCHED (VT11)'!$E:$M,9,0)),"",VLOOKUP(A142,'DISPATCHED (VT11)'!$E:$M,9,0))) | R142: =IF(H142="","",IF(H142<#REF!,1,0)) -> #REF! | S142: =IF(H142="","",IF(H142>#REF!,1,0)) -> #REF! | T142: =IF(H142="","",IF(H142=#REF!,1,0)) -> #REF! | U142: =IF(I142="","",1)
A143: 31028207 | B143: SOUTHSHOP SALES CORPORATION | C143: 181 | D143: 1 | E143: 3.23 | G143: =+N143 -> PAR-PUP | H143: 46125 | M143: =VLOOKUP(B143,REFERENCE!$A$2:D356,4,0) -> RONNIE ROMERO | N143: =VLOOKUP(B143,REFERENCE!A:C,3,FALSE) -> PAR-PUP | O143: =COUNTIF($A:$A,A143) -> 1 | P143: =IF(COUNTIF('DISPATCHED (VT11)'!$E:$E,'Summarized Plan'!A143)=0,"",COUNTIF('DISPATCHED (VT11)'!$E:$E,'Summarized Plan'!A143)) | Q143: =IF(A143="","",IF(ISNA(VLOOKUP(A143,'DISPATCHED (VT11)'!$E:$M,9,0)),"",VLOOKUP(A143,'DISPATCHED (VT11)'!$E:$M,9,0))) | R143: =IF(H143="","",IF(H143<#REF!,1,0)) -> #REF! | S143: =IF(H143="","",IF(H143>#REF!,1,0)) -> #REF! | T143: =IF(H143="","",IF(H143=#REF!,1,0)) -> #REF! | U143: =IF(I143="","",1)
A144: 31029582 | B144: PUREGOLD JR-TUBIGAN BIÑAN | C144: 113 | D144: 1 | E144: 2.64 | G144: KA | H144: 46125 | I144: INITIAL_VEGA | M144: =VLOOKUP(B144,REFERENCE!$A$2:D357,4,0) -> #N/A | N144: =VLOOKUP(B144,REFERENCE!A:C,3,FALSE) -> #N/A | O144: =COUNTIF($A:$A,A144) -> 1 | P144: =IF(COUNTIF('DISPATCHED (VT11)'!$E:$E,'Summarized Plan'!A144)=0,"",COUNTIF('DISPATCHED (VT11)'!$E:$E,'Summarized Plan'!A144)) | Q144: =IF(A144="","",IF(ISNA(VLOOKUP(A144,'DISPATCHED (VT11)'!$E:$M,9,0)),"",VLOOKUP(A144,'DISPATCHED (VT11)'!$E:$M,9,0))) | R144: =IF(H144="","",IF(H144<#REF!,1,0)) -> #REF! | S144: =IF(H144="","",IF(H144>#REF!,1,0)) -> #REF! | T144: =IF(H144="","",IF(H144=#REF!,1,0)) -> #REF! | U144: =IF(I144="","",1) -> 1
A145: 31029982 | B145: PANCAKE HOUSE-TAGUIG | C145: 381 | D145: 11 | E145: 3.15 | G145: KA | H145: 46125 | I145: INITIAL_CANDA | M145: =VLOOKUP(B145,REFERENCE!$A$2:D358,4,0) -> #N/A | N145: =VLOOKUP(B145,REFERENCE!A:C,3,FALSE) -> #N/A | O145: =COUNTIF($A:$A,A145) -> 1 | P145: =IF(COUNTIF('DISPATCHED (VT11)'!$E:$E,'Summarized Plan'!A145)=0,"",COUNTIF('DISPATCHED (VT11)'!$E:$E,'Summarized Plan'!A145)) -> 1 | Q145: =IF(A145="","",IF(ISNA(VLOOKUP(A145,'DISPATCHED (VT11)'!$E:$M,9,0)),"",VLOOKUP(A145,'DISPATCHED (VT11)'!$E:$M,9,0))) -> 381 | R145: =IF(H145="","",IF(H145<#REF!,1,0)) -> #REF! | S145: =IF(H145="","",IF(H145>#REF!,1,0)) -> #REF! | T145: =IF(H145="","",IF(H145=#REF!,1,0)) -> #REF! | U145: =IF(I145="","",1) -> 1
A146: 31029983 | B146: SHAKEYS PIZZA RESTAURANT | C146: 122 | D146: 7 | E146: 2.24 | G146: KA | H146: 46125 | I146: INITIAL_LAXAMANA | M146: =VLOOKUP(B146,REFERENCE!$A$2:D359,4,0) -> #N/A | N146: =VLOOKUP(B146,REFERENCE!A:C,3,FALSE) -> #N/A | O146: =COUNTIF($A:$A,A146) -> 1 | P146: =IF(COUNTIF('DISPATCHED (VT11)'!$E:$E,'Summarized Plan'!A146)=0,"",COUNTIF('DISPATCHED (VT11)'!$E:$E,'Summarized Plan'!A146)) -> 1 | Q146: =IF(A146="","",IF(ISNA(VLOOKUP(A146,'DISPATCHED (VT11)'!$E:$M,9,0)),"",VLOOKUP(A146,'DISPATCHED (VT11)'!$E:$M,9,0))) -> 122 | R146: =IF(H146="","",IF(H146<#REF!,1,0)) -> #REF! | S146: =IF(H146="","",IF(H146>#REF!,1,0)) -> #REF! | T146: =IF(H146="","",IF(H146=#REF!,1,0)) -> #REF! | U146: =IF(I146="","",1) -> 1
A147: 31030387 | B147: SHAKEY'S PILAR | C147: 160 | D147: 10 | E147: 3.27 | G147: KA | H147: 46125 | I147: INITIAL_PARANE | M147: =VLOOKUP(B147,REFERENCE!$A$2:D360,4,0) -> #N/A | N147: =VLOOKUP(B147,REFERENCE!A:C,3,FALSE) -> #N/A | O147: =COUNTIF($A:$A,A147) -> 1 | P147: =IF(COUNTIF('DISPATCHED (VT11)'!$E:$E,'Summarized Plan'!A147)=0,"",COUNTIF('DISPATCHED (VT11)'!$E:$E,'Summarized Plan'!A147)) | Q147: =IF(A147="","",IF(ISNA(VLOOKUP(A147,'DISPATCHED (VT11)'!$E:$M,9,0)),"",VLOOKUP(A147,'DISPATCHED (VT11)'!$E:$M,9,0))) | R147: =IF(H147="","",IF(H147<#REF!,1,0)) -> #REF! | S147: =IF(H147="","",IF(H147>#REF!,1,0)) -> #REF! | T147: =IF(H147="","",IF(H147=#REF!,1,0)) -> #REF! | U147: =IF(I147="","",1) -> 1
A148: 31029589 | B148: PUREGOLD PRICE CLUB-PUTATAN | C148: 313 | D148: 1 | E148: 5.85 | G148: KA | H148: 46125 | I148: 2ND LOAD_VEGA | M148: =VLOOKUP(B148,REFERENCE!$A$2:D361,4,0) -> #N/A | N148: =VLOOKUP(B148,REFERENCE!A:C,3,FALSE) -> #N/A | O148: =COUNTIF($A:$A,A148) -> 1 | P148: =IF(COUNTIF('DISPATCHED (VT11)'!$E:$E,'Summarized Plan'!A148)=0,"",COUNTIF('DISPATCHED (VT11)'!$E:$E,'Summarized Plan'!A148)) | Q148: =IF(A148="","",IF(ISNA(VLOOKUP(A148,'DISPATCHED (VT11)'!$E:$M,9,0)),"",VLOOKUP(A148,'DISPATCHED (VT11)'!$E:$M,9,0))) | R148: =IF(H148="","",IF(H148<#REF!,1,0)) -> #REF! | S148: =IF(H148="","",IF(H148>#REF!,1,0)) -> #REF! | T148: =IF(H148="","",IF(H148=#REF!,1,0)) -> #REF! | U148: =IF(I148="","",1) -> 1
A149: 31029580 | B149: PUREGOLD PRICE CLUB-88 SQUARE PARAN | C149: 296 | D149: 1 | E149: 4.12 | G149: KA | H149: 46125 | I149: INITIAL_MENDOZA | M149: =VLOOKUP(B149,REFERENCE!$A$2:D362,4,0) -> #N/A | N149: =VLOOKUP(B149,REFERENCE!A:C,3,FALSE) -> #N/A | O149: =COUNTIF($A:$A,A149) -> 1 | P149: =IF(COUNTIF('DISPATCHED (VT11)'!$E:$E,'Summarized Plan'!A149)=0,"",COUNTIF('DISPATCHED (VT11)'!$E:$E,'Summarized Plan'!A149)) -> 1 | Q149: =IF(A149="","",IF(ISNA(VLOOKUP(A149,'DISPATCHED (VT11)'!$E:$M,9,0)),"",VLOOKUP(A149,'DISPATCHED (VT11)'!$E:$M,9,0))) -> 296 | R149: =IF(H149="","",IF(H149<#REF!,1,0)) -> #REF! | S149: =IF(H149="","",IF(H149>#REF!,1,0)) -> #REF! | T149: =IF(H149="","",IF(H149=#REF!,1,0)) -> #REF! | U149: =IF(I149="","",1) -> 1
A150: 31030389 | B150: STAR PARKS CORP.-CCP CMPLX. | C150: 204 | D150: 10 | E150: 2.89 | G150: KA | H150: 46125 | I150: INITIAL_RAMIREZ | M150: =VLOOKUP(B150,REFERENCE!$A$2:D363,4,0) -> #N/A | N150: =VLOOKUP(B150,REFERENCE!A:C,3,FALSE) -> #N/A | O150: =COUNTIF($A:$A,A150) -> 1 | P150: =IF(COUNTIF('DISPATCHED (VT11)'!$E:$E,'Summarized Plan'!A150)=0,"",COUNTIF('DISPATCHED (VT11)'!$E:$E,'Summarized Plan'!A150)) | Q150: =IF(A150="","",IF(ISNA(VLOOKUP(A150,'DISPATCHED (VT11)'!$E:$M,9,0)),"",VLOOKUP(A150,'DISPATCHED (VT11)'!$E:$M,9,0))) | R150: =IF(H150="","",IF(H150<#REF!,1,0)) -> #REF! | S150: =IF(H150="","",IF(H150>#REF!,1,0)) -> #REF! | T150: =IF(H150="","",IF(H150=#REF!,1,0)) -> #REF! | U150: =IF(I150="","",1) -> 1
A151: 31030261 | B151: THE BELLEVUE MANILA-FILINVEST | C151: 286 | D151: 18 | E151: 3.71 | G151: KA | H151: 46125 | I151: INITIAL_GERVACIO | M151: =VLOOKUP(B151,REFERENCE!$A$2:D364,4,0) -> #N/A | N151: =VLOOKUP(B151,REFERENCE!A:C,3,FALSE) -> #N/A | O151: =COUNTIF($A:$A,A151) -> 1 | P151: =IF(COUNTIF('DISPATCHED (VT11)'!$E:$E,'Summarized Plan'!A151)=0,"",COUNTIF('DISPATCHED (VT11)'!$E:$E,'Summarized Plan'!A151)) -> 1 | Q151: =IF(A151="","",IF(ISNA(VLOOKUP(A151,'DISPATCHED (VT11)'!$E:$M,9,0)),"",VLOOKUP(A151,'DISPATCHED (VT11)'!$E:$M,9,0))) -> 286 | R151: =IF(H151="","",IF(H151<#REF!,1,0)) -> #REF! | S151: =IF(H151="","",IF(H151>#REF!,1,0)) -> #REF! | T151: =IF(H151="","",IF(H151=#REF!,1,0)) -> #REF! | U151: =IF(I151="","",1) -> 1
A152: 31029588 | B152: PUREGOLD PRICE CLUB-PUTATAN | C152: 519 | D152: 1 | E152: 5.29 | G152: KA | H152: 46125 | I152: INITIAL_MAHUSAY | M152: =VLOOKUP(B152,REFERENCE!$A$2:D365,4,0) -> #N/A | N152: =VLOOKUP(B152,REFERENCE!A:C,3,FALSE) -> #N/A | O152: =COUNTIF($A:$A,A152) -> 1 | P152: =IF(COUNTIF('DISPATCHED (VT11)'!$E:$E,'Summarized Plan'!A152)=0,"",COUNTIF('DISPATCHED (VT11)'!$E:$E,'Summarized Plan'!A152)) -> 1 | Q152: =IF(A152="","",IF(ISNA(VLOOKUP(A152,'DISPATCHED (VT11)'!$E:$M,9,0)),"",VLOOKUP(A152,'DISPATCHED (VT11)'!$E:$M,9,0))) -> 519 | R152: =IF(H152="","",IF(H152<#REF!,1,0)) -> #REF! | S152: =IF(H152="","",IF(H152>#REF!,1,0)) -> #REF! | T152: =IF(H152="","",IF(H152=#REF!,1,0)) -> #REF! | U152: =IF(I152="","",1) -> 1
A153: 31029981 | B153: CHOWKING UPTOWN MALL | C153: 253 | D153: 12 | E153: 3.69 | G153: KA | H153: 46125 | I153: INITIAL_LOBETE | M153: =VLOOKUP(B153,REFERENCE!$A$2:D366,4,0) -> #N/A | N153: =VLOOKUP(B153,REFERENCE!A:C,3,FALSE) -> #N/A | O153: =COUNTIF($A:$A,A153) -> 1 | P153: =IF(COUNTIF('DISPATCHED (VT11)'!$E:$E,'Summarized Plan'!A153)=0,"",COUNTIF('DISPATCHED (VT11)'!$E:$E,'Summarized Plan'!A153)) -> 1 | Q153: =IF(A153="","",IF(ISNA(VLOOKUP(A153,'DISPATCHED (VT11)'!$E:$M,9,0)),"",VLOOKUP(A153,'DISPATCHED (VT11)'!$E:$M,9,0))) -> 253 | R153: =IF(H153="","",IF(H153<#REF!,1,0)) -> #REF! | S153: =IF(H153="","",IF(H153>#REF!,1,0)) -> #REF! | T153: =IF(H153="","",IF(H153=#REF!,1,0)) -> #REF! | U153: =IF(I153="","",1) -> 1
A154: 31029706 | B154: W MALL SUPERMARKET | C154: 484 | D154: 1 | E154: 4.96 | G154: KA | H154: 46125 | I154: 2ND LOAD_AULISTIA | M154: =VLOOKUP(B154,REFERENCE!$A$2:D367,4,0) -> #N/A | N154: =VLOOKUP(B154,REFERENCE!A:C,3,FALSE) -> #N/A | O154: =COUNTIF($A:$A,A154) -> 1 | P154: =IF(COUNTIF('DISPATCHED (VT11)'!$E:$E,'Summarized Plan'!A154)=0,"",COUNTIF('DISPATCHED (VT11)'!$E:$E,'Summarized Plan'!A154)) | Q154: =IF(A154="","",IF(ISNA(VLOOKUP(A154,'DISPATCHED (VT11)'!$E:$M,9,0)),"",VLOOKUP(A154,'DISPATCHED (VT11)'!$E:$M,9,0))) | R154: =IF(H154="","",IF(H154<#REF!,1,0)) -> #REF! | S154: =IF(H154="","",IF(H154>#REF!,1,0)) -> #REF! | T154: =IF(H154="","",IF(H154=#REF!,1,0)) -> #REF! | U154: =IF(I154="","",1) -> 1
A155: 31029444 | B155: EVERWIN MART | C155: 120 | D155: 1 | E155: 5 | G155: KA | H155: 46125 | I155: INITIAL_MEJELLANO | M155: =VLOOKUP(B155,REFERENCE!$A$2:D368,4,0) -> #N/A | N155: =VLOOKUP(B155,REFERENCE!A:C,3,FALSE) -> #N/A | O155: =COUNTIF($A:$A,A155) -> 1 | P155: =IF(COUNTIF('DISPATCHED (VT11)'!$E:$E,'Summarized Plan'!A155)=0,"",COUNTIF('DISPATCHED (VT11)'!$E:$E,'Summarized Plan'!A155)) | Q155: =IF(A155="","",IF(ISNA(VLOOKUP(A155,'DISPATCHED (VT11)'!$E:$M,9,0)),"",VLOOKUP(A155,'DISPATCHED (VT11)'!$E:$M,9,0))) | R155: =IF(H155="","",IF(H155<#REF!,1,0)) -> #REF! | S155: =IF(H155="","",IF(H155>#REF!,1,0)) -> #REF! | T155: =IF(H155="","",IF(H155=#REF!,1,0)) -> #REF! | U155: =IF(I155="","",1) -> 1
... A170: 31030513 | B170: ALBA INTERNATIONAL INC. | C170: 257 | D170: 15 | E170: 4.18 | G170: KA | H170: 46125 | I170: INITIAL_CORTEZ | M170: =VLOOKUP(B170,REFERENCE!$A$2:D383,4,0) -> #N/A | N170: =VLOOKUP(B170,REFERENCE!A:C,3,FALSE) -> #N/A | O170: =COUNTIF($A:$A,A170) -> 1 | P170: =IF(COUNTIF('DISPATCHED (VT11)'!$E:$E,'Summarized Plan'!A170)=0,"",COUNTIF('DISPATCHED (VT11)'!$E:$E,'Summarized Plan'!A170)) -> 1 | Q170: =IF(A170="","",IF(ISNA(VLOOKUP(A170,'DISPATCHED (VT11)'!$E:$M,9,0)),"",VLOOKUP(A170,'DISPATCHED (VT11)'!$E:$M,9,0))) -> 257 | R170: =IF(H170="","",IF(H170<#REF!,1,0)) -> #REF! | S170: =IF(H170="","",IF(H170>#REF!,1,0)) -> #REF! | T170: =IF(H170="","",IF(H170=#REF!,1,0)) -> #REF! | U170: =IF(I170="","",1) -> 1
A171: 31027790 | B171: CCBPI_PARAÑAQUE DC | C171: 35 | D171: 1 | E171: 0.27 | G171: KA | H171: 46125 | I171: LSP_PICKUP | M171: =VLOOKUP(B171,REFERENCE!$A$2:D384,4,0) -> #N/A | N171: =VLOOKUP(B171,REFERENCE!A:C,3,FALSE) -> #N/A | O171: =COUNTIF($A:$A,A171) -> 1 | P171: =IF(COUNTIF('DISPATCHED (VT11)'!$E:$E,'Summarized Plan'!A171)=0,"",COUNTIF('DISPATCHED (VT11)'!$E:$E,'Summarized Plan'!A171)) | Q171: =IF(A171="","",IF(ISNA(VLOOKUP(A171,'DISPATCHED (VT11)'!$E:$M,9,0)),"",VLOOKUP(A171,'DISPATCHED (VT11)'!$E:$M,9,0))) | R171: =IF(H171="","",IF(H171<#REF!,1,0)) -> #REF! | S171: =IF(H171="","",IF(H171>#REF!,1,0)) -> #REF! | T171: =IF(H171="","",IF(H171=#REF!,1,0)) -> #REF! | U171: =IF(I171="","",1) -> 1 | Z171: A
A172: 31027791 | B172: CCBPI_PARAÑAQUE DC | C172: 32 | D172: 1 | E172: 0.8 | G172: KA | H172: 46125 | I172: LSP_PICKUP | M172: =VLOOKUP(B172,REFERENCE!$A$2:D385,4,0) -> #N/A | N172: =VLOOKUP(B172,REFERENCE!A:C,3,FALSE) -> #N/A | O172: =COUNTIF($A:$A,A172) -> 1 | P172: =IF(COUNTIF('DISPATCHED (VT11)'!$E:$E,'Summarized Plan'!A172)=0,"",COUNTIF('DISPATCHED (VT11)'!$E:$E,'Summarized Plan'!A172)) -> 1 | Q172: =IF(A172="","",IF(ISNA(VLOOKUP(A172,'DISPATCHED (VT11)'!$E:$M,9,0)),"",VLOOKUP(A172,'DISPATCHED (VT11)'!$E:$M,9,0))) -> 32 | R172: =IF(H172="","",IF(H172<#REF!,1,0)) -> #REF! | S172: =IF(H172="","",IF(H172>#REF!,1,0)) -> #REF! | T172: =IF(H172="","",IF(H172=#REF!,1,0)) -> #REF! | U172: =IF(I172="","",1) -> 1 | Z172: G
A173: 31027792 | B173: CCBPI_PARAÑAQUE DC | C173: 1024 | D173: 1 | E173: 5 | G173: KA | H173: 46125 | I173: LSP_PICKUP | M173: =VLOOKUP(B173,REFERENCE!$A$2:D386,4,0) -> #N/A | N173: =VLOOKUP(B173,REFERENCE!A:C,3,FALSE) -> #N/A | O173: =COUNTIF($A:$A,A173) -> 1 | P173: =IF(COUNTIF('DISPATCHED (VT11)'!$E:$E,'Summarized Plan'!A173)=0,"",COUNTIF('DISPATCHED (VT11)'!$E:$E,'Summarized Plan'!A173)) | Q173: =IF(A173="","",IF(ISNA(VLOOKUP(A173,'DISPATCHED (VT11)'!$E:$M,9,0)),"",VLOOKUP(A173,'DISPATCHED (VT11)'!$E:$M,9,0))) | R173: =IF(H173="","",IF(H173<#REF!,1,0)) -> #REF! | S173: =IF(H173="","",IF(H173>#REF!,1,0)) -> #REF! | T173: =IF(H173="","",IF(H173=#REF!,1,0)) -> #REF! | U173: =IF(I173="","",1) -> 1 | Z173: G
A174: 31027793 | B174: CCBPI_PARAÑAQUE DC | C174: 1104 | D174: 1 | E174: 5.39 | G174: KA | H174: 46125 | I174: LSP_PICKUP | M174: =VLOOKUP(B174,REFERENCE!$A$2:D387,4,0) -> #N/A | N174: =VLOOKUP(B174,REFERENCE!A:C,3,FALSE) -> #N/A | O174: =COUNTIF($A:$A,A174) -> 1 | P174: =IF(COUNTIF('DISPATCHED (VT11)'!$E:$E,'Summarized Plan'!A174)=0,"",COUNTIF('DISPATCHED (VT11)'!$E:$E,'Summarized Plan'!A174)) | Q174: =IF(A174="","",IF(ISNA(VLOOKUP(A174,'DISPATCHED (VT11)'!$E:$M,9,0)),"",VLOOKUP(A174,'DISPATCHED (VT11)'!$E:$M,9,0))) | R174: =IF(H174="","",IF(H174<#REF!,1,0)) -> #REF! | S174: =IF(H174="","",IF(H174>#REF!,1,0)) -> #REF! | T174: =IF(H174="","",IF(H174=#REF!,1,0)) -> #REF! | U174: =IF(I174="","",1) -> 1 | Z174: B
A175: 31027794 | B175: CCBPI_PARAÑAQUE DC | C175: 1024 | D175: 1 | E175: 5 | G175: KA | H175: 46125 | I175: LSP_PICKUP | M175: =VLOOKUP(B175,REFERENCE!$A$2:D388,4,0) -> #N/A | N175: =VLOOKUP(B175,REFERENCE!A:C,3,FALSE) -> #N/A | O175: =COUNTIF($A:$A,A175) -> 1 | P175: =IF(COUNTIF('DISPATCHED (VT11)'!$E:$E,'Summarized Plan'!A175)=0,"",COUNTIF('DISPATCHED (VT11)'!$E:$E,'Summarized Plan'!A175)) | Q175: =IF(A175="","",IF(ISNA(VLOOKUP(A175,'DISPATCHED (VT11)'!$E:$M,9,0)),"",VLOOKUP(A175,'DISPATCHED (VT11)'!$E:$M,9,0))) | R175: =IF(H175="","",IF(H175<#REF!,1,0)) -> #REF! | S175: =IF(H175="","",IF(H175>#REF!,1,0)) -> #REF! | T175: =IF(H175="","",IF(H175=#REF!,1,0)) -> #REF! | U175: =IF(I175="","",1) -> 1 | Z175: G
A176: 31027795 | B176: CCBPI_PARAÑAQUE DC | C176: 8 | D176: 1 | E176: 0.07 | G176: KA | H176: 46125 | I176: LSP_PICKUP | M176: =VLOOKUP(B176,REFERENCE!$A$2:D389,4,0) -> #N/A | N176: =VLOOKUP(B176,REFERENCE!A:C,3,FALSE) -> #N/A | O176: =COUNTIF($A:$A,A176) -> 1 | P176: =IF(COUNTIF('DISPATCHED (VT11)'!$E:$E,'Summarized Plan'!A176)=0,"",COUNTIF('DISPATCHED (VT11)'!$E:$E,'Summarized Plan'!A176)) | Q176: =IF(A176="","",IF(ISNA(VLOOKUP(A176,'DISPATCHED (VT11)'!$E:$M,9,0)),"",VLOOKUP(A176,'DISPATCHED (VT11)'!$E:$M,9,0))) | R176: =IF(H176="","",IF(H176<#REF!,1,0)) -> #REF! | S176: =IF(H176="","",IF(H176>#REF!,1,0)) -> #REF! | T176: =IF(H176="","",IF(H176=#REF!,1,0)) -> #REF! | U176: =IF(I176="","",1) -> 1
...

Sheet Report Summary
B2: Dispatch Date: | C2: =IF('DISPATCHED (VT11)'!C4="","Please encode date on Disp Sheet",'DISPATCHED (VT11)'!C4) -> 46125 | P2: Delivery Update: 7am, 9pm, 11pm, 3pm, 5pm, and Final
P3: Send DP Update: 12:30pm
A4: A. Load Out: | H4: A1. Load Out Breakdown: | O4: A2. Text Update:
B6: Summary | C6: Shipments | E6: Physical Cases | G6: Efficiency | I6: KA | J6: Shipments | L6: Physical Cases | N6: Efficiency | P6: Summary | R6: Trip dispatched | X6: Summary | Y6: TARGETS
C7: Planned | D7: Dispatched | E7: Planned | F7: Dispatched | J7: Planned | K7: Dispatched | L7: Planned | M7: Dispatched | R7: Planned | S7: Dispatched | T7: Variance | U7: Efficiency | Y7: 7AM Dispatched | Z7: Trippage | AA7: Dispatched | AB7: Truck Allocated | AC7: Trippage | AF7: Plan | AH7: Actual | AJ7: % | AL7: Balance | AN7: Remarks
B8: Current | C8: =R8+R11+R14+R17+R20+R23+R26 -> 186 | D8: =S8+S11+S14+S17+S20+S23+S26 -> 83 | E8: =R39+R42+R45+R48+R51+R54+R57 -> 58799 | F8: =S39+S42+S45+S48+S51+S54+S57 -> 21736 | G8: =IF(ISERROR(D8/C8),"-",D8/C8) -> 0.44623656 | I8: Current | J8: =COUNTIFS('Summarized Plan'!$G:$G,'Report Summary'!I6,'Summarized Plan'!$H:$H,'Report Summary'!$C$2) -> 89 | K8: =SUMIFS('Summarized Plan'!$P:$P,'Summarized Plan'!$G:$G,'Report Summary'!I6,'Summarized Plan'!$H:$H,'Report Summary'!C2) -> 57 | L8: =SUMIFS('Summarized Plan'!$C:$C,'Summarized Plan'!$G:$G,'Report Summary'!I6,'Summarized Plan'!$H:$H,'Report Summary'!$C$2) -> 25665 | M8: =SUMIFS('Summarized Plan'!$Q:$Q,'Summarized Plan'!$G:$G,'Report Summary'!I6,'Summarized Plan'!$H:$H,'Report Summary'!$C$2) -> 14252 | N8: =IF(ISERROR(K8/J8),"-",K8/J8) -> 0.64044944 | O8: =R8+R11+R14+R17+R20+R23+R9+R12+R15+R18+R21+R24 -> #REF! | P8: KA | Q8: CURRENT | R8: =+J8 -> 89 | S8: =K8 -> 57 | T8: =R8-S8 -> 32 | U8: =S8/R8 -> 0.64044944 | W8: =+AB8*Z8 -> 48.4 | X8: KA | Y8: =IF((R8+R9)<ROUNDDOWN((AB8*0.8),0),(R8+R9),ROUNDDOWN((AB8*0.8),0)) -> #REF! | Z8: 1.1 | AA8: =+S8+S9 -> 57 | AB8: =44 -> 44 | AC8: =+(S8+S9)/AB8 -> 1.2954545 | AF8: Shipments | AG8: cases | AH8: Shipments | AI8: cases | AJ8: Shipments | AK8: cases | AL8: Shipments | AM8: cases | AX8: =C2 -> 46125
B9: Backlogs | C9: =R9+R12+R15+R18+R21+R24+R27 -> #REF! | D9: =S9+S12+S15+S18+S21+S24+S27 -> 0 | E9: =R40+R43+R46+R49+R52+R55+R58 -> 0 | F9: =S40+S43+S46+S49+S52+S55+S58 -> 0 | G9: =IF(ISERROR(D9/C9),"-",D9/C9) -> - | I9: Backlogs | J9: =SUMIF('Summarized Plan'!$G:$G,'Report Summary'!I6,'Summarized Plan'!$R:$R) -> #REF! | K9: =SUMIFS('Summarized Plan'!$P:$P,'Summarized Plan'!$R:$R,"=1",'Summarized Plan'!$G:$G,'Report Summary'!I6) -> 0 | L9: =SUMIFS('Summarized Plan'!$C:$C,'Summarized Plan'!$R:$R,"=1",'Summarized Plan'!$G:$G,'Report Summary'!I6) -> 0 | M9: =SUMIFS('Summarized Plan'!$Q:$Q,'Summarized Plan'!$R:$R,"=1",'Summarized Plan'!$G:$G,'Report Summary'!I6) -> 0 | N9: =IF(ISERROR(K9/J9),"-",K9/J9) -> - | O9: =S8+S11+S14+S17+S20+S23+S9+S12+S15+S18+S21+S24 -> 80 | Q9: BACKLOG | R9: =J9 -> #REF! | S9: =K9 -> 0 | T9: =R9-S9 -> #REF! | U9: =S9/R9 -> #REF! | AE9: KA | AF9: =R8+R9 -> #REF! | AG9: =R39+R40 -> 25665 | AH9: =S8+S9 -> 57 | AI9: =S39+S40 -> 14252 | AJ9: =AH9/AF9 -> #REF! | AK9: =AI9/AG9 -> 0.55530879 | AL9: =AF9-AH9 -> #REF! | AM9: =AG9-AI9 -> 11413 | AX9: Dated | AY9: In Shipment | BB9: In PCS | BF9: In UCS
B10: Advanced | C10: =R10+R13+R16+R19+R22+R25+R28 -> #REF! | D10: =S10+S13+S16+S19+S22+S25+S28 -> 0 | E10: =R41+R44+R47+R50+R53+R56+R59 -> 0 | F10: =S41+S44+S47+S50+S53+S56+S59 -> 0 | G10: =IF(ISERROR(D10/C10),"-",D10/C10) -> - | I10: Advanced | J10: =SUMIF('Summarized Plan'!$G:$G,'Report Summary'!I6,'Summarized Plan'!$S:$S) -> #REF! | K10: =SUMIFS('Summarized Plan'!$P:$P,'Summarized Plan'!$S:$S,"=1",'Summarized Plan'!$G:$G,'Report Summary'!I6) -> 0 | L10: =SUMIFS('Summarized Plan'!$C:$C,'Summarized Plan'!$S:$S,"=1",'Summarized Plan'!$G:$G,'Report Summary'!I6) -> 0 | M10: =SUMIFS('Summarized Plan'!$Q:$Q,'Summarized Plan'!$S:$S,"=1",'Summarized Plan'!$G:$G,'Report Summary'!I6) -> 0 | N10: =IF(ISERROR(K10/J10),"-",K10/J10) -> - | Q10: ADVANCE | R10: =J10 -> #REF! | S10: =K10 -> 0 | T10: =R10-S10 -> #REF! | U10: =S10/R10 -> #REF! | W10: =+AB10*Z10 -> 1 | X10: DSD | Y10: =IF((R11+R12)<ROUNDDOWN((AB10*0.8),0),(R11+R12),ROUNDDOWN((AB10*0.8),0)) -> #REF! | Z10: 1 | AA10: =+S11+S12 -> 3 | AB10: 1 | AC10: =+(S11+S12)/AB10 -> 3 | AE10: DP | AF10: =R14+R15 -> #REF! | AG10: =R45+R46 -> 7184 | AH10: =S14+S15 -> 6 | AI10: =S45+S46 -> 1495 | AJ10: =AH10/AF10 -> #REF! | AK10: =AI10/AG10 -> 0.20810134 | AL10: =AF10-AH10 -> #REF! | AM10: =AG10-AI10 -> 5689 | AX10: Source | AY10: Plan | AZ10: Executed | BA10: Balance | BB10: Plan | BC10: Executed | BD10: Balance | BE10: Loadout | BF10: Plan | BG10: Executed | BH10: Balance | BI10: Loadout
B11: Total | C11: =SUM(C8:C10) -> #REF! | D11: =SUM(D8:D10) -> 83 | E11: =SUM(E8:E10) -> 58799 | F11: =S42+S45+S48+S51+S54+S57+S60 -> 7484 | G11: =IF(ISERROR(D11/C11),"-",D11/C11) -> - | I11: Total | J11: =SUM(J8:J10) -> #REF! | K11: =SUM(K8:K10) -> 57 | L11: =SUM(L8:L10) -> 25665 | M11: =SUM(M8:M10) -> 14252 | N11: =IF(ISERROR(K11/J11),"-",K11/J11) -> - | P11: HOD | Q11: CURRENT | R11: =J15 -> 11 | S11: =K15 -> 3 | T11: =R11-S11 -> 8 | U11: =S11/R11 -> 0.27272727 | AE11: DSD | AF11: =R11+R12 -> #REF! | AG11: =R42 -> 3504 | AH11: =S11 -> 3 | AI11: =S42 -> 921 | AJ11: =AH11/AF11 -> #REF! | AK11: =AI11/AG11 -> 0.26284247 | AL11: =AF11-AH11 -> #REF! | AM11: =AG11-AI11 -> 2583 | AX11: Manila | BI11: =IFERROR(BG11/BF11,"")
Q12: BACKLOG | R12: =J16 -> #REF! | S12: =K16 -> 0 | T12: =R12-S12 -> #REF! | U12: =S12/R12 -> #REF! | W12: =+AB12*Z12 -> 128 | X12: DP | Y12: =IF((R14+R15)<ROUNDDOWN((AB12*0.8),0),(R14+R15),ROUNDDOWN((AB12*0.8),0)) -> #REF! | Z12: 2 | AA12: =+S14+S15 -> 6 | AB12: =64 -> 64 | AC12: =+(S14+S15)/AB12 -> 0.09375 | AE12: KOFD | AF12: =R17+R18 -> #REF! | AG12: =R48+R49 -> 1900 | AH12: =S17+S18 -> 3 | AI12: =S48+S49 -> 777 | AJ12: =AH12/AF12 -> #REF! | AK12: =AI12/AG12 -> 0.40894737 | AL12: =AF12-AH12 -> #REF! | AM12: =AG12-AI12 -> 1123 | AX12: Parañaque | AY12: =+R8+R11+R14+R17+R20+R23+R29 -> 156 | AZ12: =+S8+S11+S14+S17+S20+S23+S29 -> 80 | BA12: =+AY12-AZ12 -> 76 | BI12: =IFERROR(BG12/BF12,"")
A13: B. DSR Attendance (CCBPI): | I13: HOD | J13: Shipments | L13: Physical Cases | N13: Efficiency | Q13: ADVANCE | R13: =J17 -> #REF! | S13: =K17 -> 0 | T13: =R13-S13 -> #REF! | U13: =S13/R13 -> #REF! | AE13: WS | AF13: =R20+R21 -> #REF! | AG13: =R51+R52 -> 5796 | AH13: =S20+S21 -> 11 | AI13: =S51+S52 -> 3003 | AJ13: =AH13/AF13 -> #REF! | AK13: =AI13/AG13 -> 0.51811594 | AL13: =AF13-AH13 -> #REF! | AY13: =SUM(AY11:AY12) -> 156 | AZ13: =SUM(AZ11:AZ12) -> 80 | BA13: =SUM(BA11:BA12) -> 76 | BB13: =SUM(BB11:BB12) -> 0 | BC13: =SUM(BC11:BC12) -> 0 | BD13: =SUM(BD11:BD12) -> 0 | BE13: =SUM(BE11:BE12) -> 0 | BF13: =SUM(BF11:BF12) -> 0 | ... BI13: =SUM(BI11:BI12) -> 0
J14: Planned | K14: Dispatched | L14: Planned | M14: Dispatched | P14: DP | Q14: CURRENT | R14: =J22+J29+J36+J43+J50+J183 -> 27 | S14: =K22+K29+K36+K43+K50+K183 -> 6 | T14: =R14-S14 -> 21 | U14: =S14/R14 -> 0.22222222 | W14: =+AB14*Z14 -> 2 | X14: KOF | Y14: =IF((R17+R18)<ROUNDDOWN((AB14*0.8),0),(R17+R18),ROUNDDOWN((AB14*0.8),0)) -> #REF! | Z14: 2 | AA14: =+S17+S18 -> 3 | AB14: 1 | AC14: =+(S17+S18)/AB14 -> 3 | AE14: Total | AF14: =SUM(AF9:AF13) -> #REF! | AG14: =SUM(AG9:AG13) -> 44049 | AH14: =SUM(AH9:AH13) -> 80 | AI14: =SUM(AI9:AI13) -> 20448 | AJ14: =AH14/AF14 -> #REF! | AK14: =AI14/AG14 -> 0.46421031 | AL14: =SUM(AL9:AL13) -> #REF! | AM14: =SUM(AM9:AM13) -> 20808
B15: Manning | C15: Number | F15: Absentism Rate | I15: Current | J15: =COUNTIFS('Summarized Plan'!$G:$G,'Report Summary'!I13,'Summarized Plan'!$H:$H,'Report Summary'!$C$2) -> 11 | K15: =SUMIFS('Summarized Plan'!$P:$P,'Summarized Plan'!$G:$G,'Report Summary'!I13,'Summarized Plan'!$H:$H,'Report Summary'!$C$2) -> 3 | L15: =SUMIFS('Summarized Plan'!$C:$C,'Summarized Plan'!$G:$G,'Report Summary'!I13,'Summarized Plan'!$H:$H,'Report Summary'!$C$2) -> 3504 | M15: =SUMIFS('Summarized Plan'!$Q:$Q,'Summarized Plan'!$G:$G,'Report Summary'!I13,'Summarized Plan'!$H:$H,'Report Summary'!$C$2) -> 921 | N15: =IF(ISERROR(K15/J15),"-",K15/J15) -> 0.27272727 | Q15: BACKLOG | R15: =J23+J30+J37+J44+J44+J51+J184 -> #REF! | S15: =K23+K30+K37+K44+K44+K51+K184 -> 0 | T15: =R15-S15 -> #REF! | U15: =S15/R15 -> #REF! | AI15: AGAG15:AI34
C16: Expected | D16: Reported | E16: Variance | I16: Backlogs | J16: =SUMIF('Summarized Plan'!$G:$G,'Report Summary'!I13,'Summarized Plan'!$R:$R) -> #REF! | K16: =SUMIFS('Summarized Plan'!$P:$P,'Summarized Plan'!$R:$R,"=1",'Summarized Plan'!$G:$G,'Report Summary'!I13) -> 0 | L16: =SUMIFS('Summarized Plan'!$C:$C,'Summarized Plan'!$R:$R,"=1",'Summarized Plan'!$G:$G,'Report Summary'!I13) -> 0 | M16: =SUMIFS('Summarized Plan'!$Q:$Q,'Summarized Plan'!$R:$R,"=1",'Summarized Plan'!$G:$G,'Report Summary'!I13) -> 0 | N16: =IF(ISERROR(K16/J16),"-",K16/J16) -> - | Q16: ADVANCE | R16: =J24+J31+J38+J45+J52+J185 -> #REF! | S16: =K24+K31+K38+K45+K52+K185 -> 0 | T16: =R16-S16 -> #REF! | U16: =S16/R16 -> #REF! | W16: =+AB16*Z16 -> 0 | X16: WS | Y16: =IF((R20+R21)<ROUNDDOWN((AB16*0.8),0),(R20+R21),ROUNDDOWN((AB16*0.8),0)) -> #REF! | Z16: 1.5 | AA16: =+S20+S21 -> 11 | AB16: 0 | AC16: =+(S20+S21)/AB16 -> #DIV/0! | AE16: Parañaque DC | AG16: Trip Dispatched | AJ16: Volume Loadout | AM16: PERCENT ACHIEVED | AN16: ASSIGNED DRIVER | AR16: Replacement DSR | AS16: SALES EXECUTIVE | AT16: REGION SALES MANAGER
B17: CCBPI | C17: =COUNTIF('DSR Attendance'!$B:$B,"=CCBPI") -> 109 | D17: =SUMIF('DSR Attendance'!$B:$B,"=CCBPI",'DSR Attendance'!$C:$C) -> 44 | E17: =+C17-D17 -> 65 | F17: =+D17/C17 -> 0.40366972 | I17: Advanced | J17: =SUMIF('Summarized Plan'!$G:$G,'Report Summary'!I13,'Summarized Plan'!$S:$S) -> #REF! | K17: =SUMIFS('Summarized Plan'!$P:$P,'Summarized Plan'!$S:$S,"=1",'Summarized Plan'!$G:$G,'Report Summary'!I13) -> 0 | L17: =SUMIFS('Summarized Plan'!$C:$C,'Summarized Plan'!$S:$S,"=1",'Summarized Plan'!$G:$G,'Report Summary'!I13) -> 0 | M17: =SUMIFS('Summarized Plan'!$Q:$Q,'Summarized Plan'!$S:$S,"=1",'Summarized Plan'!$G:$G,'Report Summary'!I13) -> 0 | N17: =IF(ISERROR(K17/J17),"-",K17/J17) -> - | P17: LWS | Q17: CURRENT | R17: =J57+J64+J71+J78+J85+J190 -> 8 | S17: =K57+K64+K71+K78+K85+K190 -> 3 | T17: =R17-S17 -> 5 | U17: =S17/R17 -> 0.375 | AG17: Planned | AH17: Dispatched | AI17: Balance | AJ17: Planned | AK17: Dispatched | AL17: Balance | AN17: DRIVER 1 | AO17: DRIVER 2 | AP17: DRIVER 3 | AQ17: DRIVER 4
B18: Casual | C18: =COUNTIF('DSR Attendance'!$B:$B,"=CCBPI - CASUAL") -> 0 | D18: =SUMIF('DSR Attendance'!$B:$B,"=TRCI -",'DSR Attendance'!$C:$C) -> 0 | E18: =+C18-D18 -> 0 | F18: =+D18/C18 -> #DIV/0! | I18: Total | J18: =SUM(J15:J17) -> #REF! | K18: =SUM(K15:K17) -> 3 | L18: =SUM(L15:L17) -> 3504 | M18: =SUM(M15:M17) -> 921 | N18: =IF(ISERROR(K18/J18),"-",K18/J18) -> - | Q18: BACKLOG | R18: =J58+J65+J72+J79+J86+J191 -> #REF! | S18: =K58+K65+K72+K79+K86 -> 0 | T18: =R18-S18 -> #REF! | U18: =S18/R18 -> #REF! | AG18: =SUMIF('Summarized Plan'!#REF!,$AE18,'Summarized Plan'!#REF!) -> #REF! | AH18: =SUMIF('Summarized Plan'!#REF!,$AE18,'Summarized Plan'!#REF!) -> #REF! | AI18: =AG18-AH18 -> #REF! | AJ18: =SUMIF('Summarized Plan'!#REF!,$AE18,'Summarized Plan'!#REF!) -> #REF! | AK18: =SUMIF('Summarized Plan'!#REF!,$AE18,'Summarized Plan'!#REF!) -> #REF! | AL18: =AJ18-AK18 -> #REF! | AM18: =AH18/AG18 -> #REF!
B19: Total | C19: =+SUM(C17:C18) -> 109 | D19: =+SUM(D17:D18) -> 44 | E19: =+SUM(E17:E18) -> 65 | F19: =+D19/C19 -> 0.40366972 | Q19: ADVANCE | R19: =J59+J66+J73+J80+J87+J192 -> #REF! | S19: =K59+K66+K73+K80+K87+K192 -> 0 | T19: =R19-S19 -> #REF! | U19: =S19/R19 -> #REF! | AG19: =SUM(AG18) -> #REF! | AH19: =SUM(AH18) -> #REF! | AI19: =AG19-AH19 -> #REF! | AJ19: =SUM(AJ18) -> #REF! | AK19: =SUM(AK18) -> #REF! | AL19: =AJ19-AK19 -> #REF! | AM19: =AH19/AG19 -> #REF!
I20: BAG-DP | J20: Shipments | L20: Physical Cases | N20: Efficiency | P20: WS | Q20: CURRENT | R20: =J92+J99+J106+J113+J120+J162+J197 -> 21 | S20: =K92+K99+K106+K113+K120+K162+K197 -> 11 | T20: =R20-S20 -> 10 | U20: =S20/R20 -> 0.52380952 | AE20: DP MAGNUM | AG20: =SUMIF('Summarized Plan'!#REF!,$AE20,'Summarized Plan'!#REF!) -> #REF! | AH20: =SUMIF('Summarized Plan'!#REF!,$AE20,'Summarized Plan'!#REF!) -> #REF! | AI20: =AG20-AH20 -> #REF! | AJ20: =SUMIF('Summarized Plan'!#REF!,$AE20,'Summarized Plan'!#REF!) -> #REF! | AK20: =SUMIF('Summarized Plan'!#REF!,$AE20,'Summarized Plan'!#REF!) -> #REF! | AL20: =AJ20-AK20 -> #REF! | AM20: =AH20/AG20 -> #REF!
A21: C. DSR Attendance (TPD): | J21: Planned | K21: Dispatched | L21: Planned | M21: Dispatched | Q21: BACKLOG | R21: =J93+J100+J107+J114+J121+J163+J198 -> #REF! | S21: =K93+K100+K107+K114+K121+K163+K198 -> 0 | T21: =R21-S21 -> #REF! | U21: =S21/R21 -> #REF! | AE21: DP ASH JACK TRADING | AG21: =SUMIF('Summarized Plan'!#REF!,$AE21,'Summarized Plan'!#REF!) -> #REF! | AH21: =SUMIF('Summarized Plan'!#REF!,$AE21,'Summarized Plan'!#REF!) -> #REF! | AI21: =AG21-AH21 -> #REF! | AJ21: =SUMIF('Summarized Plan'!#REF!,$AE21,'Summarized Plan'!#REF!) -> #REF! | AK21: =SUMIF('Summarized Plan'!#REF!,$AE21,'Summarized Plan'!#REF!) -> #REF! | AL21: =AJ21-AK21 -> #REF! | AM21: =AH21/AG21 -> #REF!
I22: Current | J22: =COUNTIFS('Summarized Plan'!$G:$G,'Report Summary'!I20,'Summarized Plan'!$H:$H,'Report Summary'!$C$2) -> 0 | K22: =SUMIFS('Summarized Plan'!$P:$P,'Summarized Plan'!$G:$G,'Report Summary'!I20,'Summarized Plan'!$H:$H,'Report Summary'!$C$2) -> 0 | L22: =SUMIFS('Summarized Plan'!$C:$C,'Summarized Plan'!$G:$G,'Report Summary'!I20,'Summarized Plan'!$H:$H,'Report Summary'!$C$2) -> 0 | M22: =SUMIFS('Summarized Plan'!$Q:$Q,'Summarized Plan'!$G:$G,'Report Summary'!I20,'Summarized Plan'!$H:$H,'Report Summary'!$C$2) -> 0 | N22: =IF(ISERROR(K22/J22),"-",K22/J22) -> - | Q22: ADVANCE | R22: =J94+J101+J108+J115+J122+J164+J199 -> #REF! | S22: =K94+K101+K108+K115+K122+K164+K199 -> 0 | T22: =R22-S22 -> #REF! | U22: =S22/R22 -> #REF! | AE22: DP L.A.V TRADING | AG22: =SUMIF('Summarized Plan'!#REF!,$AE22,'Summarized Plan'!#REF!) -> #REF! | AH22: =SUMIF('Summarized Plan'!#REF!,$AE22,'Summarized Plan'!#REF!) -> #REF! | AI22: =AG22-AH22 -> #REF! | AJ22: =SUMIF('Summarized Plan'!#REF!,$AE22,'Summarized Plan'!#REF!) -> #REF! | AK22: =SUMIF('Summarized Plan'!#REF!,$AE22,'Summarized Plan'!#REF!) -> #REF! | AL22: =AJ22-AK22 -> #REF! | AM22: =AH22/AG22 -> #REF!
B23: Manning | C23: Number | F23: Absentism Rate | I23: Backlogs | J23: =SUMIF('Summarized Plan'!$G:$G,'Report Summary'!I20,'Summarized Plan'!$R:$R) -> 0 | K23: =SUMIFS('Summarized Plan'!$P:$P,'Summarized Plan'!$R:$R,"=1",'Summarized Plan'!$G:$G,'Report Summary'!I20) -> 0 | L23: =SUMIFS('Summarized Plan'!$C:$C,'Summarized Plan'!$R:$R,"=1",'Summarized Plan'!$G:$G,'Report Summary'!I20) -> 0 | M23: =SUMIFS('Summarized Plan'!$Q:$Q,'Summarized Plan'!$R:$R,"=1",'Summarized Plan'!$G:$G,'Report Summary'!I20) -> 0 | N23: =IF(ISERROR(K23/J23),"-",K23/J23) -> - | P23: DIRECTSHIP | Q23: CURRENT | R23: =J169 -> 0 | S23: =K169 -> 0 | T23: =R23-S23 -> 0 | U23: =S23/R23 -> #DIV/0! | AE23: DP MAY SANTOS TRADING | AG23: =SUMIF('Summarized Plan'!#REF!,$AE23,'Summarized Plan'!#REF!) -> #REF! | AH23: =SUMIF('Summarized Plan'!#REF!,$AE23,'Summarized Plan'!#REF!) -> #REF! | AI23: =AG23-AH23 -> #REF! | AJ23: =SUMIF('Summarized Plan'!#REF!,$AE23,'Summarized Plan'!#REF!) -> #REF! | AK23: =SUMIF('Summarized Plan'!#REF!,$AE23,'Summarized Plan'!#REF!) -> #REF! | AL23: =AJ23-AK23 -> #REF! | AM23: =AH23/AG23 -> #REF!
C24: Expected | D24: Reported | E24: Variance | I24: Advanced | J24: =SUMIF('Summarized Plan'!$G:$G,'Report Summary'!I20,'Summarized Plan'!$S:$S) -> 0 | K24: =SUMIFS('Summarized Plan'!$P:$P,'Summarized Plan'!$S:$S,"=1",'Summarized Plan'!$G:$G,'Report Summary'!I20) -> 0 | L24: =SUMIFS('Summarized Plan'!$C:$C,'Summarized Plan'!$S:$S,"=1",'Summarized Plan'!$G:$G,'Report Summary'!I20) -> 0 | M24: =SUMIFS('Summarized Plan'!$Q:$Q,'Summarized Plan'!$S:$S,"=1",'Summarized Plan'!$G:$G,'Report Summary'!I20) -> 0 | N24: =IF(ISERROR(K24/J24),"-",K24/J24) -> - | Q24: BACKLOG | R24: =J170 -> 0 | S24: =K170 -> 0 | T24: =R24-S24 -> 0 | U24: =S24/R24 -> #DIV/0! | AE24: DP RICAFORTZ CONSUMER GOODS TRADING | AG24: =SUMIF('Summarized Plan'!#REF!,$AE24,'Summarized Plan'!#REF!) -> #REF! | AH24: =SUMIF('Summarized Plan'!#REF!,$AE24,'Summarized Plan'!#REF!) -> #REF! | AI24: =AG24-AH24 -> #REF! | AJ24: =SUMIF('Summarized Plan'!#REF!,$AE24,'Summarized Plan'!#REF!) -> #REF! | AK24: =SUMIF('Summarized Plan'!#REF!,$AE24,'Summarized Plan'!#REF!) -> #REF! | AL24: =AJ24-AK24 -> #REF! | AM24: =AH24/AG24 -> #REF!
B25: ONG | C25: =COUNTIF('DSR Attendance'!$B:$B,B25) -> 19 | D25: =SUMIF('DSR Attendance'!$B:$B,B25,'DSR Attendance'!$C:$C) -> 8 | E25: =+C25-D25 -> 11 | F25: =+D25/C25 -> 0.42105263 | I25: Total | J25: =SUM(J22:J24) -> 0 | K25: =SUM(K22:K24) -> 0 | L25: =SUM(L22:L24) -> 0 | M25: =SUM(M22:M24) -> 0 | N25: =IF(ISERROR(K25/J25),"-",K25/J25) -> - | Q25: ADVANCE | R25: =J171 -> 0 | S25: =K171 -> 0 | T25: =R25-S25 -> 0 | U25: =S25/R25 -> #DIV/0! | W25: =SUM(W8:W16) -> 179.4 | X25: Total | Y25: =IF((R32+R33)<SUM(Y8:Y19),R32+R33,SUM(Y8:Y19)) -> #REF! | Z25: =+W25/AB25 -> 1.6309091 | AA25: =SUM(AA16,AA12,AA14,AA8,AA10) -> 80 | AB25: =SUM(AB8:AB16) -> 110 | AC25: =+(S32+S33)/AB25 -> 0.75454545 | AG25: =SUMIF('Summarized Plan'!#REF!,$AE25,'Summarized Plan'!#REF!) -> #REF! | AH25: =SUMIF('Summarized Plan'!#REF!,$AE25,'Summarized Plan'!#REF!) -> #REF! | AI25: =AG25-AH25 -> #REF! | AJ25: =SUMIF('Summarized Plan'!#REF!,$AE25,'Summarized Plan'!#REF!) -> #REF! | AK25: =SUMIF('Summarized Plan'!#REF!,$AE25,'Summarized Plan'!#REF!) -> #REF! | AL25: =AJ25-AK25 -> #REF! | AM25: =AH25/AG25 -> #REF!
B26: RRAJ | C26: =COUNTIF('DSR Attendance'!$B:$B,B26) -> 22 | D26: =SUMIF('DSR Attendance'!$B:$B,B26,'DSR Attendance'!$C:$C) -> 9 | E26: =+C26-D26 -> 13 | F26: =+D26/C26 -> 0.40909091 | O26: =R26+R27 -> #REF! | P26: PICK UP | Q26: CURRENT | R26: =J127+J134+J141+J148+J155+J204 -> 30 | S26: =K127+K134+K141+K148+K155+K204 -> 3 | T26: =R26-S26 -> 27 | U26: =S26/R26 -> 0.1 | AG26: =SUMIF('Summarized Plan'!#REF!,$AE26,'Summarized Plan'!#REF!) -> #REF! | AH26: =SUMIF('Summarized Plan'!#REF!,$AE26,'Summarized Plan'!#REF!) -> #REF! | AI26: =AG26-AH26 -> #REF! | AJ26: =SUMIF('Summarized Plan'!#REF!,$AE26,'Summarized Plan'!#REF!) -> #REF! | AK26: =SUMIF('Summarized Plan'!#REF!,$AE26,'Summarized Plan'!#REF!) -> #REF! | AL26: =AJ26-AK26 -> #REF! | AM26: =AH26/AG26 -> #REF!
B27: 2GO | C27: =COUNTIF('DSR Attendance'!$B:$B,B27) -> 0 | D27: =SUMIF('DSR Attendance'!$B:$B,B27,'DSR Attendance'!$C:$C) -> 0 | E27: =+C27-D27 -> 0 | F27: =+D27/C27 -> #DIV/0! | I27: LP-DP | J27: Shipments | L27: Physical Cases | N27: Efficiency | O27: =S26+S27 -> 3 | Q27: BACKLOG | R27: =J128+J135+J142+J149+J156+J205 -> #REF! | S27: =K128+K135+K142+K149+K156+K205 -> 0 | T27: =R27-S27 -> #REF! | U27: =S27/R27 -> #REF! | AG27: =SUMIF('Summarized Plan'!#REF!,$AE27,'Summarized Plan'!#REF!) -> #REF! | AH27: =SUMIF('Summarized Plan'!#REF!,$AE27,'Summarized Plan'!#REF!) -> #REF! | AI27: =AG27-AH27 -> #REF! | AJ27: =SUMIF('Summarized Plan'!#REF!,$AE27,'Summarized Plan'!#REF!) -> #REF! | AK27: =SUMIF('Summarized Plan'!#REF!,$AE27,'Summarized Plan'!#REF!) -> #REF! | AL27: =AJ27-AK27 -> #REF! | AM27: =AH27/AG27 -> #REF!
B28: A-TRANS LOG | C28: =COUNTIF('DSR Attendance'!$B:$B,B28) -> 0 | D28: =SUMIF('DSR Attendance'!$B:$B,B28,'DSR Attendance'!$C:$C) -> 0 | E28: =+C28-D28 -> 0 | F28: =+D28/C28 -> #DIV/0! | J28: Planned | K28: Dispatched | L28: Planned | M28: Dispatched | Q28: ADVANCE | R28: =J129+J136+J143+J150+J157+J206 -> #REF! | S28: =K129+K136+K143+K150+K157+K206 -> 0 | T28: =R28-S28 -> #REF! | U28: =S28/R28 -> #REF! | AG28: =SUMIF('Summarized Plan'!#REF!,$AE28,'Summarized Plan'!#REF!) -> #REF! | AH28: =SUMIF('Summarized Plan'!#REF!,$AE28,'Summarized Plan'!#REF!) -> #REF! | AI28: =AG28-AH28 -> #REF! | AJ28: =SUMIF('Summarized Plan'!#REF!,$AE28,'Summarized Plan'!#REF!) -> #REF! | AK28: =SUMIF('Summarized Plan'!#REF!,$AE28,'Summarized Plan'!#REF!) -> #REF! | AL28: =AJ28-AK28 -> #REF! | AM28: =AH28/AG28 -> #REF!
B29: EMME | C29: =COUNTIF('DSR Attendance'!$B:$B,B29) -> 0 | D29: =SUMIF('DSR Attendance'!$B:$B,B29,'DSR Attendance'!$C:$C) -> 0 | E29: =+C29-D29 -> 0 | F29: =+D29/C29 -> #DIV/0! | I29: Current | J29: =COUNTIFS('Summarized Plan'!$G:$G,'Report Summary'!I27,'Summarized Plan'!$H:$H,'Report Summary'!$C$2) -> 20 | K29: =SUMIFS('Summarized Plan'!$P:$P,'Summarized Plan'!$G:$G,'Report Summary'!I27,'Summarized Plan'!$H:$H,'Report Summary'!$C$2) -> 3 | L29: =SUMIFS('Summarized Plan'!$C:$C,'Summarized Plan'!$G:$G,'Report Summary'!I27,'Summarized Plan'!$H:$H,'Report Summary'!$C$2) -> 5594 | M29: =SUMIFS('Summarized Plan'!$Q:$Q,'Summarized Plan'!$G:$G,'Report Summary'!I27,'Summarized Plan'!$H:$H,'Report Summary'!$C$2) -> 852 | N29: =IF(ISERROR(K29/J29),"-",K29/J29) -> 0.15 | P29: KOFD | Q29: CURRENT | R29: =J176 -> 0 | S29: =K176 -> 0 | T29: =R29-S29 -> 0 | U29: =S29/R29 -> #DIV/0! | AG29: =SUMIF('Summarized Plan'!#REF!,$AE29,'Summarized Plan'!#REF!) -> #REF! | AH29: =SUMIF('Summarized Plan'!#REF!,$AE29,'Summarized Plan'!#REF!) -> #REF! | AI29: =AG29-AH29 -> #REF! | AJ29: =SUMIF('Summarized Plan'!#REF!,$AE29,'Summarized Plan'!#REF!) -> #REF! | AK29: =SUMIF('Summarized Plan'!#REF!,$AE29,'Summarized Plan'!#REF!) -> #REF! | AL29: =AJ29-AK29 -> #REF! | AM29: =AH29/AG29 -> #REF!
B30: AMOURE | C30: =COUNTIF('DSR Attendance'!$B:$B,B30) -> 0 | D30: =SUMIF('DSR Attendance'!$B:$B,B30,'DSR Attendance'!$C:$C) -> 0 | E30: =+C30-D30 -> 0 | F30: =+D30/C30 -> #DIV/0! | I30: Backlogs | J30: =SUMIF('Summarized Plan'!$G:$G,'Report Summary'!I27,'Summarized Plan'!$R:$R) -> #REF! | K30: =SUMIFS('Summarized Plan'!$P:$P,'Summarized Plan'!$R:$R,"=1",'Summarized Plan'!$G:$G,'Report Summary'!I27) -> 0 | L30: =SUMIFS('Summarized Plan'!$C:$C,'Summarized Plan'!$R:$R,"=1",'Summarized Plan'!$G:$G,'Report Summary'!I27) -> 0 | M30: =SUMIFS('Summarized Plan'!$Q:$Q,'Summarized Plan'!$R:$R,"=1",'Summarized Plan'!$G:$G,'Report Summary'!I27) -> 0 | N30: =IF(ISERROR(K30/J30),"-",K30/J30) -> - | Q30: BACKLOG | R30: =J177 -> 0 | S30: =K177 -> 0 | T30: =R30-S30 -> 0 | U30: =S30/R30 -> #DIV/0! | AG30: =SUM(AG20:AG29) -> #REF! | AH30: =SUM(AH20:AH29) -> #REF! | AI30: =SUM(AI20:AI29) -> #REF! | AJ30: =SUM(AJ20:AJ29) -> #REF! | AK30: =SUM(AK20:AK29) -> #REF! | AL30: =SUM(AL20:AL29) -> #REF! | AM30: =AH30/AG30 -> #REF!
I31: Advanced | J31: =SUMIF('Summarized Plan'!$G:$G,'Report Summary'!I27,'Summarized Plan'!$S:$S) -> #REF! | K31: =SUMIFS('Summarized Plan'!$P:$P,'Summarized Plan'!$S:$S,"=1",'Summarized Plan'!$G:$G,'Report Summary'!I27) -> 0 | L31: =SUMIFS('Summarized Plan'!$C:$C,'Summarized Plan'!$S:$S,"=1",'Summarized Plan'!$G:$G,'Report Summary'!I27) -> 0 | M31: =SUMIFS('Summarized Plan'!$Q:$Q,'Summarized Plan'!$S:$S,"=1",'Summarized Plan'!$G:$G,'Report Summary'!I27) -> 0 | N31: =IF(ISERROR(K31/J31),"-",K31/J31) -> - | Q31: ADVANCE | R31: =J178 -> 0 | S31: =K178 -> 0 | T31: =R31-S31 -> 0 | U31: =S31/R31 -> #DIV/0! | AE31: DP COSMICLOAD INC. | AG31: =SUMIF('Summarized Plan'!#REF!,$AE31,'Summarized Plan'!#REF!) -> #REF! | AH31: =SUMIF('Summarized Plan'!#REF!,$AE31,'Summarized Plan'!#REF!) -> #REF! | AI31: =AG31-AH31 -> #REF! | AJ31: =SUMIF('Summarized Plan'!#REF!,$AE31,'Summarized Plan'!#REF!) -> #REF! | AK31: =SUMIF('Summarized Plan'!#REF!,$AE31,'Summarized Plan'!#REF!) -> #REF! | AL31: =AJ31-AK31 -> #REF! | AM31: =AH31/AG31 -> #REF!
I32: Total | J32: =SUM(J29:J31) -> #REF! | K32: =SUM(K29:K31) -> 3 | L32: =SUM(L29:L31) -> 5594 | M32: =SUM(M29:M31) -> 852 | N32: =IF(ISERROR(K32/J32),"-",K32/J32) -> - | P32: TOTAL | Q32: CURRENT | R32: =R8+R11+R14+R17+R20+R23+R26+R29 -> 186 | S32: =S8+S11+S14+S17+S20+S23+S26+S29 -> 83 | T32: =R32-S32 -> 103 | U32: =S32/R32 -> 0.44623656 | AE32: DP GENERO ENTERPRISE | AG32: =SUMIF('Summarized Plan'!#REF!,$AE32,'Summarized Plan'!#REF!) -> #REF! | AH32: =SUMIF('Summarized Plan'!#REF!,$AE32,'Summarized Plan'!#REF!) -> #REF! | AI32: =AG32-AH32 -> #REF! | AJ32: =SUMIF('Summarized Plan'!#REF!,$AE32,'Summarized Plan'!#REF!) -> #REF! | AK32: =SUMIF('Summarized Plan'!#REF!,$AE32,'Summarized Plan'!#REF!) -> #REF! | AL32: =AJ32-AK32 -> #REF! | AM32: =AH32/AG32 -> #REF!
Q33: BACKLOG | R33: =R9+R12+R15+R18+R21+R24+R27+R30 -> #REF! | S33: =S9+S12+S15+S18+S21+S24+S27+S30 -> 0 | T33: =R33-S33 -> #REF! | U33: =S33/R33 -> #REF! | AE33: CARRY ALL FOOD ENTERPRISES INC. | AG33: =SUMIF('Summarized Plan'!#REF!,$AE33,'Summarized Plan'!#REF!) -> #REF! | AH33: =SUMIF('Summarized Plan'!#REF!,$AE33,'Summarized Plan'!#REF!) -> #REF! | AI33: =AG33-AH33 -> #REF! | AJ33: =SUMIF('Summarized Plan'!#REF!,$AE33,'Summarized Plan'!#REF!) -> #REF! | AK33: =SUMIF('Summarized Plan'!#REF!,$AE33,'Summarized Plan'!#REF!) -> #REF! | AL33: =AJ33-AK33 -> #REF! | AM33: =AH33/AG33 -> #REF!
I34: MAN-DP | J34: Shipments | L34: Physical Cases | N34: Efficiency | Q34: ADVANCE | R34: =R10+R13+R16+R19+R22+R25+R28+R31 -> #REF! | S34: =S10+S13+S16+S19+S22+S25+S28+S31 -> 0 | T34: =R34-S34 -> #REF! | U34: =S34/R34 -> #REF! | AG34: =SUMIF('Summarized Plan'!#REF!,$AE34,'Summarized Plan'!#REF!) -> #REF! | AH34: =SUMIF('Summarized Plan'!#REF!,$AE34,'Summarized Plan'!#REF!) -> #REF! | AI34: =AG34-AH34 -> #REF! | AJ34: =SUMIF('Summarized Plan'!#REF!,$AE34,'Summarized Plan'!#REF!) -> #REF! | AK34: =SUMIF('Summarized Plan'!#REF!,$AE34,'Summarized Plan'!#REF!) -> #REF! | AL34: =AJ34-AK34 -> #REF! | AM34: =AH34/AG34 -> #REF!
J35: Planned | K35: Dispatched | L35: Planned | M35: Dispatched | P35: Grand Total | R35: =SUM(R32:R34) -> #REF! | S35: =SUM(S32:S34) -> 83 | T35: =R35-S35 -> #REF! | U35: =S35/R35 -> #REF! | AG35: =SUMIF('Summarized Plan'!#REF!,$AE35,'Summarized Plan'!#REF!) -> #REF! | AH35: =SUMIF('Summarized Plan'!#REF!,$AE35,'Summarized Plan'!#REF!) -> #REF! | AI35: =AG35-AH35 -> #REF! | AJ35: =SUMIF('Summarized Plan'!#REF!,$AE35,'Summarized Plan'!#REF!) -> #REF! | AK35: =SUMIF('Summarized Plan'!#REF!,$AE35,'Summarized Plan'!#REF!) -> #REF! | AL35: =AJ35-AK35 -> #REF! | AM35: =AH35/AG35 -> #REF!
I36: Current | J36: =COUNTIFS('Summarized Plan'!$G:$G,'Report Summary'!I34,'Summarized Plan'!$H:$H,'Report Summary'!$C$2) -> 0 | K36: =SUMIFS('Summarized Plan'!$P:$P,'Summarized Plan'!$G:$G,'Report Summary'!I34,'Summarized Plan'!$H:$H,'Report Summary'!$C$2) -> 0 | L36: =SUMIFS('Summarized Plan'!$C:$C,'Summarized Plan'!$G:$G,'Report Summary'!I34,'Summarized Plan'!$H:$H,'Report Summary'!$C$2) -> 0 | M36: =SUMIFS('Summarized Plan'!$Q:$Q,'Summarized Plan'!$G:$G,'Report Summary'!I34,'Summarized Plan'!$H:$H,'Report Summary'!$C$2) -> 0 | N36: =IF(ISERROR(K36/J36),"-",K36/J36) -> - | AG36: =SUMIF('Summarized Plan'!#REF!,$AE36,'Summarized Plan'!#REF!) -> #REF! | AH36: =SUMIF('Summarized Plan'!#REF!,$AE36,'Summarized Plan'!#REF!) -> #REF! | AI36: =AG36-AH36 -> #REF! | AJ36: =SUMIF('Summarized Plan'!#REF!,$AE36,'Summarized Plan'!#REF!) -> #REF! | AK36: =SUMIF('Summarized Plan'!#REF!,$AE36,'Summarized Plan'!#REF!) -> #REF! | AL36: =AJ36-AK36 -> #REF! | AM36: =AH36/AG36 -> #REF!
B37: Total | C37: =SUM(C25:C33) -> 41 | D37: =SUM(D25:D32) -> 17 | E37: =SUM(E25:E32) -> 24 | F37: =+D37/C37 -> 0.41463415 | I37: Backlogs | J37: =SUMIF('Summarized Plan'!$G:$G,'Report Summary'!I34,'Summarized Plan'!$R:$R) -> 0 | K37: =SUMIFS('Summarized Plan'!$P:$P,'Summarized Plan'!$R:$R,"=1",'Summarized Plan'!$G:$G,'Report Summary'!I34) -> 0 | L37: =SUMIFS('Summarized Plan'!$C:$C,'Summarized Plan'!$R:$R,"=1",'Summarized Plan'!$G:$G,'Report Summary'!I34) -> 0 | M37: =SUMIFS('Summarized Plan'!$Q:$Q,'Summarized Plan'!$R:$R,"=1",'Summarized Plan'!$G:$G,'Report Summary'!I34) -> 0 | N37: =IF(ISERROR(K37/J37),"-",K37/J37) -> - | P37: Summary | R37: Volume Loadout | AG37: =SUMIF('Summarized Plan'!#REF!,$AE37,'Summarized Plan'!#REF!) -> #REF! | AH37: =SUMIF('Summarized Plan'!#REF!,$AE37,'Summarized Plan'!#REF!) -> #REF! | AI37: =AG37-AH37 -> #REF! | AJ37: =SUMIF('Summarized Plan'!#REF!,$AE37,'Summarized Plan'!#REF!) -> #REF! | AK37: =SUMIF('Summarized Plan'!#REF!,$AE37,'Summarized Plan'!#REF!) -> #REF! | AL37: =AJ37-AK37 -> #REF! | AM37: =AH37/AG37 -> #REF!
I38: Advanced | J38: =SUMIF('Summarized Plan'!$G:$G,'Report Summary'!I34,'Summarized Plan'!$S:$S) -> 0 | K38: =SUMIFS('Summarized Plan'!$P:$P,'Summarized Plan'!$S:$S,"=1",'Summarized Plan'!$G:$G,'Report Summary'!I34) -> 0 | L38: =SUMIFS('Summarized Plan'!$C:$C,'Summarized Plan'!$S:$S,"=1",'Summarized Plan'!$G:$G,'Report Summary'!I34) -> 0 | M38: =SUMIFS('Summarized Plan'!$Q:$Q,'Summarized Plan'!$S:$S,"=1",'Summarized Plan'!$G:$G,'Report Summary'!I34) -> 0 | N38: =IF(ISERROR(K38/J38),"-",K38/J38) -> - | O38: =R39+R42+R45+R48+R51+R54 -> 44049 | R38: Planned | S38: Dispatched | T38: Variance | U38: Efficiency | AG38: =SUMIF('Summarized Plan'!#REF!,$AE38,'Summarized Plan'!#REF!) -> #REF! | AH38: =SUMIF('Summarized Plan'!#REF!,$AE38,'Summarized Plan'!#REF!) -> #REF! | AI38: =AG38-AH38 -> #REF! | AJ38: =SUMIF('Summarized Plan'!#REF!,$AE38,'Summarized Plan'!#REF!) -> #REF! | AK38: =SUMIF('Summarized Plan'!#REF!,$AE38,'Summarized Plan'!#REF!) -> #REF! | AL38: =AJ38-AK38 -> #REF! | AM38: =AH38/AG38 -> #REF!
B39: Total Attendance | C39: =+C19+C37 -> 150 | D39: =+D19+D37 -> 61 | E39: =+SUM(E37:E38) -> 24 | F39: =+D39/C39 -> 0.40666667 | I39: Total | J39: =SUM(J36:J38) -> 0 | K39: =SUM(K36:K38) -> 0 | L39: =SUM(L36:L38) -> 0 | M39: =SUM(M36:M38) -> 0 | N39: =IF(ISERROR(K39/J39),"-",K39/J39) -> - | O39: =S39+S42+S45+S48+S51+S54 -> 20448 | P39: KA | Q39: CURRENT | R39: =L8 -> 25665 | S39: =M8 -> 14252 | T39: =R39-S39 -> 11413 | U39: =S39/R39 -> 0.55530879 | AG39: =SUMIF('Summarized Plan'!#REF!,$AE39,'Summarized Plan'!#REF!) -> #REF! | AH39: =SUMIF('Summarized Plan'!#REF!,$AE39,'Summarized Plan'!#REF!) -> #REF! | AI39: =AG39-AH39 -> #REF! | AJ39: =SUMIF('Summarized Plan'!#REF!,$AE39,'Summarized Plan'!#REF!) -> #REF! | AK39: =SUMIF('Summarized Plan'!#REF!,$AE39,'Summarized Plan'!#REF!) -> #REF! | AL39: =AJ39-AK39 -> #REF! | AM39: =AH39/AG39 -> #REF!
Q40: BACKLOG | R40: =L9 -> 0 | S40: =M9 -> 0 | T40: =R40-S40 -> 0 | U40: =S40/R40 -> #DIV/0! | AG40: =SUMIF('Summarized Plan'!#REF!,$AE40,'Summarized Plan'!#REF!) -> #REF! | AH40: =SUMIF('Summarized Plan'!#REF!,$AE40,'Summarized Plan'!#REF!) -> #REF! | AI40: =AG40-AH40 -> #REF! | AJ40: =SUMIF('Summarized Plan'!#REF!,$AE40,'Summarized Plan'!#REF!) -> #REF! | AK40: =SUMIF('Summarized Plan'!#REF!,$AE40,'Summarized Plan'!#REF!) -> #REF! | AL40: =AJ40-AK40 -> #REF! | AM40: =AH40/AG40 -> #REF!
A41: D. Truck Utilization: | I41: PAC-DP | J41: Shipments | L41: Physical Cases | N41: Efficiency | Q41: ADVANCE | R41: =L10 -> 0 | S41: =M10 -> 0 | T41: =R41-S41 -> 0 | U41: =S41/R41 -> #DIV/0! | AG41: =SUMIF('Summarized Plan'!#REF!,$AE41,'Summarized Plan'!#REF!) -> #REF! | AH41: =SUMIF('Summarized Plan'!#REF!,$AE41,'Summarized Plan'!#REF!) -> #REF! | AI41: =AG41-AH41 -> #REF! | AJ41: =SUMIF('Summarized Plan'!#REF!,$AE41,'Summarized Plan'!#REF!) -> #REF! | AK41: =SUMIF('Summarized Plan'!#REF!,$AE41,'Summarized Plan'!#REF!) -> #REF! | AL41: =AJ41-AK41 -> #REF! | AM41: =AH41/AG41 -> #REF!
J42: Planned | K42: Dispatched | L42: Planned | M42: Dispatched | P42: HOD | Q42: CURRENT | R42: =L15 -> 3504 | S42: =M15 -> 921 | T42: =R42-S42 -> 2583 | U42: =S42/R42 -> 0.26284247 | AG42: =SUMIF('Summarized Plan'!#REF!,$AE42,'Summarized Plan'!#REF!) -> #REF! | AH42: =SUMIF('Summarized Plan'!#REF!,$AE42,'Summarized Plan'!#REF!) -> #REF! | AI42: =AG42-AH42 -> #REF! | AJ42: =SUMIF('Summarized Plan'!#REF!,$AE42,'Summarized Plan'!#REF!) -> #REF! | AK42: =SUMIF('Summarized Plan'!#REF!,$AE42,'Summarized Plan'!#REF!) -> #REF! | AL42: =AJ42-AK42 -> #REF! | AM42: =AH42/AG42 -> #REF!
C43: Fleet Inv. | D43: Fleet Utilized | E43: Un- utilized | F43: % Utilization | I43: Current | J43: =COUNTIFS('Summarized Plan'!$G:$G,'Report Summary'!I41,'Summarized Plan'!$H:$H,'Report Summary'!$C$2) -> 0 | K43: =SUMIFS('Summarized Plan'!$P:$P,'Summarized Plan'!$G:$G,'Report Summary'!I41,'Summarized Plan'!$H:$H,'Report Summary'!$C$2) -> 0 | L43: =SUMIFS('Summarized Plan'!$C:$C,'Summarized Plan'!$G:$G,'Report Summary'!I41,'Summarized Plan'!$H:$H,'Report Summary'!$C$2) -> 0 | M43: =SUMIFS('Summarized Plan'!$Q:$Q,'Summarized Plan'!$G:$G,'Report Summary'!I41,'Summarized Plan'!$H:$H,'Report Summary'!$C$2) -> 0 | N43: =IF(ISERROR(K43/J43),"-",K43/J43) -> - | Q43: BACKLOG | R43: =L16 -> 0 | S43: =M16 -> 0 | T43: =R43-S43 -> 0 | U43: =S43/R43 -> #DIV/0! | AG43: =SUMIF('Summarized Plan'!#REF!,$AE43,'Summarized Plan'!#REF!) -> #REF! | AH43: =SUMIF('Summarized Plan'!#REF!,$AE43,'Summarized Plan'!#REF!) -> #REF! | AI43: =AG43-AH43 -> #REF! | AJ43: =SUMIF('Summarized Plan'!#REF!,$AE43,'Summarized Plan'!#REF!) -> #REF! | AK43: =SUMIF('Summarized Plan'!#REF!,$AE43,'Summarized Plan'!#REF!) -> #REF! | AL43: =AJ43-AK43 -> #REF! | AM43: =AH43/AG43 -> #REF!
B44: Company | C44: =COUNTIF('Truck Utilization'!L:L,"CCBPI") -> 86 | D44: =SUMIF('Truck Utilization'!L:L,"CCBPI",'Truck Utilization'!E:E) -> 53 | E44: =C44-D44 -> 33 | F44: =D44/C44 -> 0.61627907 | I44: Backlogs | J44: =SUMIF('Summarized Plan'!$G:$G,'Report Summary'!I41,'Summarized Plan'!$R:$R) -> 0 | K44: =SUMIFS('Summarized Plan'!$P:$P,'Summarized Plan'!$R:$R,"=1",'Summarized Plan'!$G:$G,'Report Summary'!I41) -> 0 | L44: =SUMIFS('Summarized Plan'!$C:$C,'Summarized Plan'!$R:$R,"=1",'Summarized Plan'!$G:$G,'Report Summary'!I41) -> 0 | M44: =SUMIFS('Summarized Plan'!$Q:$Q,'Summarized Plan'!$R:$R,"=1",'Summarized Plan'!$G:$G,'Report Summary'!I41) -> 0 | N44: =IF(ISERROR(K44/J44),"-",K44/J44) -> - | Q44: ADVANCE | R44: =L17 -> 0 | S44: =M17 -> 0 | T44: =R44-S44 -> 0 | U44: =S44/R44 -> #DIV/0! | AG44: =SUM(AG31:AG43) -> #REF! | AH44: =SUM(AH31:AH43) -> #REF! | AI44: =SUM(AI31:AI43) -> #REF! | AJ44: =SUM(AJ31:AJ43) -> #REF! | AK44: =SUM(AK31:AK43) -> #REF! | AL44: =SUM(AL31:AL43) -> #REF! | AM44: =AH44/AG44 -> #REF!
B45: Third Party | C45: =COUNTIF('Truck Utilization'!L:L,"TPD") -> 51 | D45: =SUMIF('Truck Utilization'!L:L,"TPD",'Truck Utilization'!E:E) -> 26 | E45: =C45-D45 -> 25 | F45: =D45/C45 -> 0.50980392 | I45: Advanced | J45: =SUMIF('Summarized Plan'!$G:$G,'Report Summary'!I41,'Summarized Plan'!$S:$S) -> 0 | K45: =SUMIFS('Summarized Plan'!$P:$P,'Summarized Plan'!$S:$S,"=1",'Summarized Plan'!$G:$G,'Report Summary'!I41) -> 0 | L45: =SUMIFS('Summarized Plan'!$C:$C,'Summarized Plan'!$S:$S,"=1",'Summarized Plan'!$G:$G,'Report Summary'!I41) -> 0 | M45: =SUMIFS('Summarized Plan'!$Q:$Q,'Summarized Plan'!$S:$S,"=1",'Summarized Plan'!$G:$G,'Report Summary'!I41) -> 0 | N45: =IF(ISERROR(K45/J45),"-",K45/J45) -> - | P45: DP | Q45: CURRENT | R45: =L22+L29+L36+L43+L50+L183 -> 7184 | S45: =M22+M29+M36+M43+M50+M183 -> 1495 | T45: =R45-S45 -> 5689 | U45: =S45/R45 -> 0.20810134
B46: Total | C46: =SUM(C44:C45) -> 137 | D46: =SUM(D44:D45) -> 79 | E46: =C46-D46 -> 58 | F46: =D46/C46 -> 0.57664234 | I46: Total | J46: =SUM(J43:J45) -> 0 | K46: =SUM(K43:K45) -> 0 | L46: =SUM(L43:L45) -> 0 | M46: =SUM(M43:M45) -> 0 | N46: =IF(ISERROR(K46/J46),"-",K46/J46) -> - | Q46: BACKLOG | R46: =L23+L30+L37+L44+L44+L51+L184 -> 0 | S46: =M23+M30+M37+M44+M44+M51+M184 -> 0 | T46: =R46-S46 -> 0 | U46: =S46/R46 -> #DIV/0! | AF46: Grand Total | AG46: =SUM(AG44++AG30+AG19) -> #REF! | AH46: =SUM(AH44++AH30+AH19) -> #REF! | AI46: =SUM(AI44++AI30+AI19) -> #REF! | AJ46: =SUM(AJ44++AJ30+AJ19) -> #REF! | AK46: =SUM(AK44++AK30+AK19) -> #REF! | AL46: =SUM(AL44++AL30+AL19) -> #REF!
Q47: ADVANCE | R47: =L24+L31+L38+L45+L52+L185 -> 0 | S47: =M24+M31+M38+M45+M52+M185 -> 0 | T47: =R47-S47 -> 0 | U47: =S47/R47 -> #DIV/0!
A48: E. Trippage: | I48: PAR-DP | J48: Shipments | L48: Physical Cases | N48: Efficiency | P48: LWS | Q48: CURRENT | R48: =L57+L64+L71+L78+L85+L190 -> 1900 | S48: =M57+M64+M71+M78+M85+M190 -> 777 | T48: =R48-S48 -> 1123 | U48: =S48/R48 -> 0.40894737
J49: Planned | K49: Dispatched | L49: Planned | M49: Dispatched | Q49: BACKLOG | R49: =L58+L65+L72+L79+L86+L191 -> 0 | S49: =M58+M65+M72+M79+M86+M191 -> 0 | T49: =R49-S49 -> 0 | U49: =S49/R49 -> #DIV/0! | AF49: =C2 -> 46125 | AH49: KA LOADOUT REPORT AS OF 1200HRS
B50: TRUCK | C50: TRIPPAGE | I50: Current | J50: =COUNTIFS('Summarized Plan'!$G:$G,'Report Summary'!I48,'Summarized Plan'!$H:$H,'Report Summary'!$C$2) -> 3 | K50: =SUMIFS('Summarized Plan'!$P:$P,'Summarized Plan'!$G:$G,'Report Summary'!I48,'Summarized Plan'!$H:$H,'Report Summary'!$C$2) -> 2 | L50: =SUMIFS('Summarized Plan'!$C:$C,'Summarized Plan'!$G:$G,'Report Summary'!I48,'Summarized Plan'!$H:$H,'Report Summary'!$C$2) -> 540 | M50: =SUMIFS('Summarized Plan'!$Q:$Q,'Summarized Plan'!$G:$G,'Report Summary'!I48,'Summarized Plan'!$H:$H,'Report Summary'!$C$2) -> 360 | N50: =IF(ISERROR(K50/J50),"-",K50/J50) -> 0.66666667 | Q50: ADVANCE | R50: =L59+L66+L73+L80+L87+L192 -> 0 | S50: =M59+M66+M73+M80+M87+M192 -> 0 | T50: =R50-S50 -> 0 | U50: =S50/R50 -> #DIV/0!
B51: Company | C51: =+S70/S72 -> 1 | I51: Backlogs | J51: =SUMIF('Summarized Plan'!$G:$G,'Report Summary'!I48,'Summarized Plan'!$R:$R) -> #REF! | K51: =SUMIFS('Summarized Plan'!$P:$P,'Summarized Plan'!$R:$R,"=1",'Summarized Plan'!$G:$G,'Report Summary'!I48) -> 0 | L51: =SUMIFS('Summarized Plan'!$C:$C,'Summarized Plan'!$R:$R,"=1",'Summarized Plan'!$G:$G,'Report Summary'!I48) -> 0 | M51: =SUMIFS('Summarized Plan'!$Q:$Q,'Summarized Plan'!$R:$R,"=1",'Summarized Plan'!$G:$G,'Report Summary'!I48) -> 0 | N51: =IF(ISERROR(K51/J51),"-",K51/J51) -> - | P51: WS | Q51: CURRENT | R51: =L92+L99+L106+L113+L120+L162+L197 -> 5796 | S51: =M92+M99+M106+M113+M120+M162+M197 -> 3003 | T51: =R51-S51 -> 2793 | U51: =S51/R51 -> 0.51811594 | AF51: KA CLUSTER | AG51: PLAN | AH51: INITIAL | AI51: RELOAD | AJ51: DISPATCHED | AK51: PENDING
B52: Third Party | C52: =+S74/S76 -> 1 | I52: Advanced | J52: =SUMIF('Summarized Plan'!$G:$G,'Report Summary'!I48,'Summarized Plan'!$S:$S) -> #REF! | K52: =SUMIFS('Summarized Plan'!$P:$P,'Summarized Plan'!$S:$S,"=1",'Summarized Plan'!$G:$G,'Report Summary'!I48) -> 0 | L52: =SUMIFS('Summarized Plan'!$C:$C,'Summarized Plan'!$S:$S,"=1",'Summarized Plan'!$G:$G,'Report Summary'!I48) -> 0 | M52: =SUMIFS('Summarized Plan'!$Q:$Q,'Summarized Plan'!$S:$S,"=1",'Summarized Plan'!$G:$G,'Report Summary'!I48) -> 0 | N52: =IF(ISERROR(K52/J52),"-",K52/J52) -> - | Q52: BACKLOG | R52: =L93+L100+L107+L114+L121+L163+L198 -> 0 | S52: =M93+M100+M107+M114+M121+M163+M198 -> 0 | T52: =R52-S52 -> 0 | U52: =S52/R52 -> #DIV/0! | AF52: ONPREMISE | AG52: =COUNTIF('Summarized Plan'!K:K,AF52) -> 0 | AJ52: =COUNTIF('DISPATCHED (VT11)'!BC:BC,AF52) -> 0 | AK52: =+AG52-AJ52 -> 0
B53: Total Trippage | C53: =AVERAGE(C51:C52) -> 1 | I53: Total | J53: =SUM(J50:J52) -> #REF! | K53: =SUM(K50:K52) -> 2 | L53: =SUM(L50:L52) -> 540 | M53: =SUM(M50:M52) -> 360 | N53: =IF(ISERROR(K53/J53),"-",K53/J53) -> - | Q53: ADVANCE | R53: =L94+L101+L108+L115+L122+L164+L199 -> 0 | S53: =M94+M101+M108+M115+M122+M164+M199 -> 0 | T53: =R53-S53 -> 0 | U53: =S53/R53 -> #DIV/0! | AF53: SUPERMARKET | AG53: =COUNTIF('Summarized Plan'!K:K,AF53) -> 0 | AJ53: =COUNTIF('DISPATCHED (VT11)'!BC:BC,AF53) -> 0 | AK53: =+AG53-AJ53 -> 0
P54: DIRECTSHIP | Q54: CURRENT | R54: =L169 -> 0 | S54: =M169 -> 0 | T54: =R54-S54 -> 0 | U54: =S54/R54 -> #DIV/0! | AF54: MIXED | AG54: =COUNTIF('Summarized Plan'!K:K,AF54) -> 0 | AJ54: =COUNTIF('DISPATCHED (VT11)'!BC:BC,AF54) -> 0 | AK54: =+AG54-AJ54 -> 0
A55: F. Load Utilization | I55: BAG-LWS | J55: Shipments | L55: Physical Cases | N55: Efficiency | Q55: BACKLOG | R55: =L170 -> 0 | S55: =M170 -> 0 | T55: =R55-S55 -> 0 | U55: =S55/R55 -> #DIV/0! | AF55: PROXIMITY | AG55: =COUNTIF('Summarized Plan'!K:K,AF55) -> 0 | AJ55: =COUNTIF('DISPATCHED (VT11)'!BC:BC,AF55) -> 0 | AK55: =+AG55-AJ55 -> 0
J56: Planned | K56: Dispatched | L56: Planned | M56: Dispatched | O56: =R57+R58 -> 14750 | Q56: ADVANCE | R56: =L171 -> 0 | S56: =M171 -> 0 | T56: =R56-S56 -> 0 | U56: =S56/R56 -> #DIV/0! | AF56: TOTAL | AG56: =SUM(AG52:AG55) -> 0 | AH56: =SUM(AH52:AH55) -> 0 | AI56: =SUM(AI52:AI55) -> 0 | AJ56: =SUM(AJ52:AJ55) -> 0 | AK56: =SUM(AK52:AK55) -> 0
B57: Average LU | C57: ='DISPATCHED (VT11)'!W5 -> 0.88183036 | I57: Current | J57: =COUNTIFS('Summarized Plan'!$G:$G,'Report Summary'!I55,'Summarized Plan'!$H:$H,'Report Summary'!$C$2) -> 0 | K57: =SUMIFS('Summarized Plan'!$P:$P,'Summarized Plan'!$G:$G,'Report Summary'!I55,'Summarized Plan'!$H:$H,'Report Summary'!$C$2) -> 0 | L57: =SUMIFS('Summarized Plan'!$C:$C,'Summarized Plan'!$G:$G,'Report Summary'!I55,'Summarized Plan'!$H:$H,'Report Summary'!$C$2) -> 0 | M57: =SUMIFS('Summarized Plan'!$Q:$Q,'Summarized Plan'!$G:$G,'Report Summary'!I55,'Summarized Plan'!$H:$H,'Report Summary'!$C$2) -> 0 | N57: =IF(ISERROR(K57/J57),"-",K57/J57) -> - | O57: =S57+S58 -> 1288 | P57: PICK UP | Q57: CURRENT | R57: =L127+L134+L141+L148+L155+L204 -> 14750 | S57: =M127+M134+M141+M148+M155+M204 -> 1288 | T57: =R57-S57 -> 13462 | U57: =S57/R57 -> 0.087322034
I58: Backlogs | J58: =SUMIF('Summarized Plan'!$G:$G,'Report Summary'!I55,'Summarized Plan'!$R:$R) -> 0 | K58: =SUMIFS('Summarized Plan'!$P:$P,'Summarized Plan'!$R:$R,"=1",'Summarized Plan'!$G:$G,'Report Summary'!I55) -> 0 | L58: =SUMIFS('Summarized Plan'!$C:$C,'Summarized Plan'!$R:$R,"=1",'Summarized Plan'!$G:$G,'Report Summary'!I55) -> 0 | M58: =SUMIFS('Summarized Plan'!$Q:$Q,'Summarized Plan'!$R:$R,"=1",'Summarized Plan'!$G:$G,'Report Summary'!I55) -> 0 | N58: =IF(ISERROR(K58/J58),"-",K58/J58) -> - | Q58: BACKLOG | R58: =L128+L135+L142+L149+L156+L205 -> 0 | S58: =M128+M135+M142+M149+M156+M205 -> 0 | T58: =R58-S58 -> 0 | U58: =S58/R58 -> #DIV/0!
B59: MT | C59: ='DISPATCHED (VT11)'!W3 -> 0.87825472 | I59: Advanced | J59: =SUMIF('Summarized Plan'!$G:$G,'Report Summary'!I55,'Summarized Plan'!$S:$S) -> 0 | K59: =SUMIFS('Summarized Plan'!$P:$P,'Summarized Plan'!$S:$S,"=1",'Summarized Plan'!$G:$G,'Report Summary'!I55) -> 0 | L59: =SUMIFS('Summarized Plan'!$C:$C,'Summarized Plan'!$S:$S,"=1",'Summarized Plan'!$G:$G,'Report Summary'!I55) -> 0 | M59: =SUMIFS('Summarized Plan'!$Q:$Q,'Summarized Plan'!$S:$S,"=1",'Summarized Plan'!$G:$G,'Report Summary'!I55) -> 0 | N59: =IF(ISERROR(K59/J59),"-",K59/J59) -> - | Q59: ADVANCE | R59: =L129+L136+L143+L150+L157+L206 -> 0 | S59: =M129+M136+M143+M150+M157+M206 -> 0 | T59: =R59-S59 -> 0 | U59: =S59/R59 -> #DIV/0!
B60: GT | C60: ='DISPATCHED (VT11)'!W4 -> 0.945 | I60: Total | J60: =SUM(J57:J59) -> 0 | K60: =SUM(K57:K59) -> 0 | L60: =SUM(L57:L59) -> 0 | M60: =SUM(M57:M59) -> 0 | N60: =IF(ISERROR(K60/J60),"-",K60/J60) -> - | P60: KOFD | Q60: CURRENT | R60: =L176 -> 0 | S60: =M176 -> 0 | T60: =R60-S60 -> 0 | U60: =S60/R60 -> #DIV/0!
Q61: BACKLOG | R61: =L177 -> 0 | S61: =M177 -> 0 | T61: =R61-S61 -> 0 | U61: =S61/R61 -> #DIV/0!
I62: LP-LWS | J62: Shipments | L62: Physical Cases | N62: Efficiency | Q62: ADVANCE | R62: =L178 -> 0 | S62: =M178 -> 0 | T62: =R62-S62 -> 0 | U62: =S62/R62 -> #DIV/0!
J63: Planned | K63: Dispatched | L63: Planned | M63: Dispatched | P63: TOTAL | Q63: CURRENT | R63: =R39+R42+R45+R48+R51+R54+R57+R60 -> 58799 | S63: =S39+S42+S45+S48+S51+S54+S57+S60 -> 21736 | T63: =R63-S63 -> 37063 | U63: =S63/R63 -> 0.36966615
B64: KA UPDATE AS OF 1600HR | I64: Current | J64: =COUNTIFS('Summarized Plan'!$G:$G,'Report Summary'!I62,'Summarized Plan'!$H:$H,'Report Summary'!$C$2) -> 0 | K64: =SUMIFS('Summarized Plan'!$P:$P,'Summarized Plan'!$G:$G,'Report Summary'!I62,'Summarized Plan'!$H:$H,'Report Summary'!$C$2) -> 0 | L64: =SUMIFS('Summarized Plan'!$C:$C,'Summarized Plan'!$G:$G,'Report Summary'!I62,'Summarized Plan'!$H:$H,'Report Summary'!$C$2) -> 0 | M64: =SUMIFS('Summarized Plan'!$Q:$Q,'Summarized Plan'!$G:$G,'Report Summary'!I62,'Summarized Plan'!$H:$H,'Report Summary'!$C$2) -> 0 | N64: =IF(ISERROR(K64/J64),"-",K64/J64) -> - | Q64: BACKLOG | R64: =R40+R43+R46+R49+R52+R55+R58+R61 -> 0 | S64: =S40+S43+S46+S49+S52+S55+S58+S61 -> 0 | T64: =R64-S64 -> 0 | U64: =S64/R64 -> #DIV/0!
B65: KA UPDATE | I65: Backlogs | J65: =SUMIF('Summarized Plan'!$G:$G,'Report Summary'!I62,'Summarized Plan'!$R:$R) -> 0 | K65: =SUMIFS('Summarized Plan'!$P:$P,'Summarized Plan'!$R:$R,"=1",'Summarized Plan'!$G:$G,'Report Summary'!I62) -> 0 | L65: =SUMIFS('Summarized Plan'!$C:$C,'Summarized Plan'!$R:$R,"=1",'Summarized Plan'!$G:$G,'Report Summary'!I62) -> 0 | M65: =SUMIFS('Summarized Plan'!$Q:$Q,'Summarized Plan'!$R:$R,"=1",'Summarized Plan'!$G:$G,'Report Summary'!I62) -> 0 | N65: =IF(ISERROR(K65/J65),"-",K65/J65) -> - | Q65: ADVANCE | R65: =R41+R44+R47+R50+R53+R56+R59+R62 -> 0 | S65: =S41+S44+S47+S50+S53+S56+S59+S62 -> 0 | T65: =R65-S65 -> 0 | U65: =S65/R65 -> #DIV/0!
D66: LOADOUT | E66: BALANCE | I66: Advanced | J66: =SUMIF('Summarized Plan'!$G:$G,'Report Summary'!I62,'Summarized Plan'!$S:$S) -> 0 | K66: =SUMIFS('Summarized Plan'!$P:$P,'Summarized Plan'!$S:$S,"=1",'Summarized Plan'!$G:$G,'Report Summary'!I62) -> 0 | L66: =SUMIFS('Summarized Plan'!$C:$C,'Summarized Plan'!$S:$S,"=1",'Summarized Plan'!$G:$G,'Report Summary'!I62) -> 0 | M66: =SUMIFS('Summarized Plan'!$Q:$Q,'Summarized Plan'!$S:$S,"=1",'Summarized Plan'!$G:$G,'Report Summary'!I62) -> 0 | N66: =IF(ISERROR(K66/J66),"-",K66/J66) -> - | P66: Grand Total | R66: =SUM(R63:R65) -> 58799 | S66: =SUM(S63:S65) -> 21736 | T66: =R66-S66 -> 37063 | U66: =S66/R66 -> 0.36966615
B67: CURRENT | C67: =R8+R11 -> 100 | D67: =S8+S11 -> 60 | E67: =C67-D67 -> 40 | I67: Total | J67: =SUM(J64:J66) -> 0 | K67: =SUM(K64:K66) -> 0 | L67: =SUM(L64:L66) -> 0 | M67: =SUM(M64:M66) -> 0 | N67: =IF(ISERROR(K67/J67),"-",K67/J67) -> -
B68: BACKLOG | C68: =R9 -> #REF! | D68: =S9 -> 0 | E68: =C68-D68 -> #REF! | P68: Company Owned Truck Availability and Utilization
B69: ADVANCE | C69: =R10 -> #REF! | D69: =S10 -> 0 | E69: =C69-D69 -> #REF! | I69: MAN-LWS | J69: Shipments | L69: Physical Cases | N69: Efficiency
B70: TOTAL | C70: =SUM(C67:C69) -> #REF! | D70: =SUM(D67:D69) -> 60 | E70: =SUM(E67:E69) -> #REF! | J70: Planned | K70: Dispatched | L70: Planned | M70: Dispatched | P70: Total Dispatched trips Company Owned Units | S70: =+'Fleet Report'!D123 -> 57
C71: TRIPS | D71: COMMIT | E71: PRELOAD | F71: LOADOUT | G71: PROJECTION | I71: Current | J71: =COUNTIFS('Summarized Plan'!$G:$G,'Report Summary'!I69,'Summarized Plan'!$H:$H,'Report Summary'!$C$2) -> 0 | K71: =SUMIFS('Summarized Plan'!$P:$P,'Summarized Plan'!$G:$G,'Report Summary'!I69,'Summarized Plan'!$H:$H,'Report Summary'!$C$2) -> 0 | L71: =SUMIFS('Summarized Plan'!$C:$C,'Summarized Plan'!$G:$G,'Report Summary'!I69,'Summarized Plan'!$H:$H,'Report Summary'!$C$2) -> 0 | M71: =SUMIFS('Summarized Plan'!$Q:$Q,'Summarized Plan'!$G:$G,'Report Summary'!I69,'Summarized Plan'!$H:$H,'Report Summary'!$C$2) -> 0 | N71: =IF(ISERROR(K71/J71),"-",K71/J71) -> - | P71: Total Available Company Owned Units | S71: =+'Fleet Report'!E124 -> 93
B72: KO | C72: =COUNTIFS('Summarized Plan'!$G:$G,"=KA",'Summarized Plan'!$I:$I,"=Company")+COUNTIFS('Summarized Plan'!$G:$G,"=KA",'Summarized Plan'!$I:$I,"=Company Reload")+COUNTIFS('Summarized Plan'!$G:$G,"=KA",'Summarized Plan'!$I:$I,"=CCBPI")++COUNTIFS('Summarized Plan'!$G:$G,"=KA",'Summarized Plan'!$I:$I,"=CCBPI Reload") -> 0 | F72: =COUNTIFS('Summarized Plan'!$G:$G,"=KA",'Summarized Plan'!$I:$I,"=CCBPI",'Summarized Plan'!$P:$P,"=1")+COUNTIFS('Summarized Plan'!$G:$G,"=KA",'Summarized Plan'!$I:$I,"=CCBPI Reload",'Summarized Plan'!$P:$P,"=1") -> 0 | G72: =+E72*1.5 -> 0 | I72: Backlogs | J72: =SUMIF('Summarized Plan'!$G:$G,'Report Summary'!I69,'Summarized Plan'!$R:$R) -> 0 | K72: =SUMIFS('Summarized Plan'!$P:$P,'Summarized Plan'!$R:$R,"=1",'Summarized Plan'!$G:$G,'Report Summary'!I69) -> 0 | L72: =SUMIFS('Summarized Plan'!$C:$C,'Summarized Plan'!$R:$R,"=1",'Summarized Plan'!$G:$G,'Report Summary'!I69) -> 0 | M72: =SUMIFS('Summarized Plan'!$Q:$Q,'Summarized Plan'!$R:$R,"=1",'Summarized Plan'!$G:$G,'Report Summary'!I69) -> 0 | N72: =IF(ISERROR(K72/J72),"-",K72/J72) -> - | P72: Total Dispatched Company Owned Units | S72: =+'Fleet Report'!F125 -> 57
B73: ONG | C73: =COUNTIFS('Summarized Plan'!$G:$G,"=KA",'Summarized Plan'!$I:$I,"=Ong")+COUNTIFS('Summarized Plan'!$G:$G,"=KA",'Summarized Plan'!$I:$I,"=Ong Reload") -> 0 | F73: =COUNTIFS('Summarized Plan'!$G:$G,"=KA",'Summarized Plan'!$I:$I,"=Ong",'Summarized Plan'!$P:$P,"=1")+COUNTIFS('Summarized Plan'!$G:$G,"=KA",'Summarized Plan'!$I:$I,"=Ong Reload",'Summarized Plan'!$P:$P,"=1") -> 0 | G73: =+E73*1.5 -> 0 | I73: Advanced | J73: =SUMIF('Summarized Plan'!$G:$G,'Report Summary'!I69,'Summarized Plan'!$S:$S) -> 0 | K73: =SUMIFS('Summarized Plan'!$P:$P,'Summarized Plan'!$S:$S,"=1",'Summarized Plan'!$G:$G,'Report Summary'!I69) -> 0 | L73: =SUMIFS('Summarized Plan'!$C:$C,'Summarized Plan'!$S:$S,"=1",'Summarized Plan'!$G:$G,'Report Summary'!I69) -> 0 | M73: =SUMIFS('Summarized Plan'!$Q:$Q,'Summarized Plan'!$S:$S,"=1",'Summarized Plan'!$G:$G,'Report Summary'!I69) -> 0 | N73: =IF(ISERROR(K73/J73),"-",K73/J73) -> - | P73: Third Party Delivery Units
B74: RRAJ | C74: =COUNTIFS('Summarized Plan'!$G:$G,"=KA",'Summarized Plan'!$I:$I,"=RRAJ")+COUNTIFS('Summarized Plan'!$G:$G,"=KA",'Summarized Plan'!$I:$I,"=RRAJ Reload") -> 0 | F74: =COUNTIFS('Summarized Plan'!$G:$G,"=KA",'Summarized Plan'!$I:$I,"=RRAJ",'Summarized Plan'!$P:$P,"=1")+COUNTIFS('Summarized Plan'!$G:$G,"=KA",'Summarized Plan'!$I:$I,"=RRAJ Reload",'Summarized Plan'!$P:$P,"=1") -> 0 | G74: =+E74*1.5 -> 0 | I74: Total | J74: =SUM(J71:J73) -> 0 | K74: =SUM(K71:K73) -> 0 | L74: =SUM(L71:L73) -> 0 | M74: =SUM(M71:M73) -> 0 | N74: =IF(ISERROR(K74/J74),"-",K74/J74) -> - | P74: Total Dispatched trips TPD Units | S74: =+'Fleet Report'!T104 -> 30
B75: 2GO | C75: =COUNTIFS('Summarized Plan'!$G:$G,"=KA",'Summarized Plan'!$I:$I,"=2GO TRANSLOADING")+COUNTIFS('Summarized Plan'!$G:$G,"=KA",'Summarized Plan'!$I:$I,"=2GO TRANSLOADING Reload") -> 0 | F75: =COUNTIFS('Summarized Plan'!$G:$G,"=KA",'Summarized Plan'!$I:$I,"=2GO TRANSLOADING",'Summarized Plan'!$P:$P,"=1")+COUNTIFS('Summarized Plan'!$G:$G,"=KA",'Summarized Plan'!$I:$I,"=2GO TRANSLOADING Reload",'Summarized Plan'!$P:$P,"=1") -> 0 | G75: =+E75*1.5 -> 0 | P75: Total Available TPD Units | S75: =+'Fleet Report'!U105 -> 0
A76: x | B76: A-TRANS LOG | C76: =COUNTIFS('Summarized Plan'!$G:$G,"=KA",'Summarized Plan'!$I:$I,"=A TRANSLOADING")+COUNTIFS('Summarized Plan'!$G:$G,"=KA",'Summarized Plan'!$I:$I,"=A TRANSLOADING Reload") -> 0 | F76: =COUNTIFS('Summarized Plan'!$G:$G,"=KA",'Summarized Plan'!$I:$I,"=A TRANSLOADING",'Summarized Plan'!$P:$P,"=1")+COUNTIFS('Summarized Plan'!$G:$G,"=KA",'Summarized Plan'!$I:$I,"=A TRANSLOADING Reload",'Summarized Plan'!$P:$P,"=1") -> 0 | G76: =+E76*1.5 -> 0 | I76: PAC-LWS | J76: Shipments | L76: Physical Cases | N76: Efficiency | P76: Total Dispatched TPD Units | S76: =+'Fleet Report'!V106 -> 30
B77: EMME | C77: =COUNTIFS('Summarized Plan'!$G:$G,"=KA",'Summarized Plan'!$I:$I,"=EMME")+COUNTIFS('Summarized Plan'!$G:$G,"=KA",'Summarized Plan'!$I:$I,"=EMME Reload") -> 0 | F77: =COUNTIFS('Summarized Plan'!$G:$G,"=KA",'Summarized Plan'!$I:$I,"=EMME",'Summarized Plan'!$P:$P,"=1")+COUNTIFS('Summarized Plan'!$G:$G,"=KA",'Summarized Plan'!$I:$I,"=EMME Reload",'Summarized Plan'!$P:$P,"=1") -> 0 | G77: =+E77*1.5 -> 0 | J77: Planned | K77: Dispatched | L77: Planned | M77: Dispatched | P77: Total Trips Dispatched | S77: =+S70+S74 -> 87
A78: =C78+C77+C74+C73 -> 0 | B78: AMOURE | C78: =COUNTIFS('Summarized Plan'!$G:$G,"=KA",'Summarized Plan'!$I:$I,"=AMOURE")+COUNTIFS('Summarized Plan'!$G:$G,"=KA",'Summarized Plan'!$I:$I,"=AMOURE Reload") -> 0 | F78: =COUNTIFS('Summarized Plan'!$G:$G,"=KA",'Summarized Plan'!$I:$I,"=AMOURE",'Summarized Plan'!$P:$P,"=1")+COUNTIFS('Summarized Plan'!$G:$G,"=KA",'Summarized Plan'!$I:$I,"=AMOURE Reload",'Summarized Plan'!$P:$P,"=1") -> 0 | G78: =+E78*1.5 -> 0 | I78: Current | J78: =COUNTIFS('Summarized Plan'!$G:$G,'Report Summary'!I76,'Summarized Plan'!$H:$H,'Report Summary'!$C$2) -> 1 | K78: =SUMIFS('Summarized Plan'!$P:$P,'Summarized Plan'!$G:$G,'Report Summary'!I76,'Summarized Plan'!$H:$H,'Report Summary'!$C$2) -> 1 | L78: =SUMIFS('Summarized Plan'!$C:$C,'Summarized Plan'!$G:$G,'Report Summary'!I76,'Summarized Plan'!$H:$H,'Report Summary'!$C$2) -> 320 | M78: =SUMIFS('Summarized Plan'!$Q:$Q,'Summarized Plan'!$G:$G,'Report Summary'!I76,'Summarized Plan'!$H:$H,'Report Summary'!$C$2) -> 320 | N78: =IF(ISERROR(K78/J78),"-",K78/J78) -> 1
B79: PICKUP | C79: =COUNTIFS('Summarized Plan'!$G:$G,"=KA",'Summarized Plan'!$I:$I,"=PICKUP")+COUNTIFS('Summarized Plan'!$G:$G,"=KA",'Summarized Plan'!$I:$I,"=PICKUP Reload") -> 0 | F79: =COUNTIFS('Summarized Plan'!$G:$G,"=KA",'Summarized Plan'!$I:$I,"=PICKUP",'Summarized Plan'!$P:$P,"=1")+COUNTIFS('Summarized Plan'!$G:$G,"=KA",'Summarized Plan'!$I:$I,"=PICKUP Reload",'Summarized Plan'!$P:$P,"=1") -> 0 | G79: =+E79*1.5 -> 0 | I79: Backlogs | J79: =SUMIF('Summarized Plan'!$G:$G,'Report Summary'!I76,'Summarized Plan'!$R:$R) -> #REF! | K79: =SUMIFS('Summarized Plan'!$P:$P,'Summarized Plan'!$R:$R,"=1",'Summarized Plan'!$G:$G,'Report Summary'!I76) -> 0 | L79: =SUMIFS('Summarized Plan'!$C:$C,'Summarized Plan'!$R:$R,"=1",'Summarized Plan'!$G:$G,'Report Summary'!I76) -> 0 | M79: =SUMIFS('Summarized Plan'!$Q:$Q,'Summarized Plan'!$R:$R,"=1",'Summarized Plan'!$G:$G,'Report Summary'!I76) -> 0 | N79: =IF(ISERROR(K79/J79),"-",K79/J79) -> - | P79: Fleet Utilization
B80: DIRECTSHIP | C80: =COUNTIFS('Summarized Plan'!$G:$G,"=DSHIP",'Summarized Plan'!$I:$I,"=ROGERSON")+COUNTIFS('Summarized Plan'!$G:$G,"=DSHIP",'Summarized Plan'!$I:$I,"=ROGERSON Reload") -> 0 | F80: =COUNTIFS('Summarized Plan'!$G:$G,"=DSHIP",'Summarized Plan'!$I:$I,"=ROGERSON",'Summarized Plan'!$P:$P,"=1")+COUNTIFS('Summarized Plan'!$G:$G,"=DSHIP",'Summarized Plan'!$I:$I,"=ROGERSON Reload",'Summarized Plan'!$P:$P,"=1") -> 0 | G80: =+E80*1.5 -> 0 | I80: Advanced | J80: =SUMIF('Summarized Plan'!$G:$G,'Report Summary'!I76,'Summarized Plan'!$S:$S) -> #REF! | K80: =SUMIFS('Summarized Plan'!$P:$P,'Summarized Plan'!$S:$S,"=1",'Summarized Plan'!$G:$G,'Report Summary'!I76) -> 0 | L80: =SUMIFS('Summarized Plan'!$C:$C,'Summarized Plan'!$S:$S,"=1",'Summarized Plan'!$G:$G,'Report Summary'!I76) -> 0 | M80: =SUMIFS('Summarized Plan'!$Q:$Q,'Summarized Plan'!$S:$S,"=1",'Summarized Plan'!$G:$G,'Report Summary'!I76) -> 0 | N80: =IF(ISERROR(K80/J80),"-",K80/J80) -> - | R80: Inventory | S80: Available | T80: Utilized | U80: %
B81: KO DIRECTSHIP | C81: =COUNTIFS('Summarized Plan'!$G:$G,"=DSHIP",'Summarized Plan'!$I:$I,"=Company")+COUNTIFS('Summarized Plan'!$G:$G,"=DSHIP",'Summarized Plan'!$I:$I,"=Company Reload")+COUNTIFS('Summarized Plan'!$G:$G,"=DSHIP",'Summarized Plan'!$I:$I,"=CCBPI")++COUNTIFS('Summarized Plan'!$G:$G,"=DSHIP",'Summarized Plan'!$I:$I,"=CCBPI Reload") -> 0 | F81: =COUNTIFS('Summarized Plan'!$G:$G,"=DSHIP",'Summarized Plan'!$I:$I,"=CCBPI",'Summarized Plan'!$P:$P,"=1")+COUNTIFS('Summarized Plan'!$G:$G,"=DSHIP",'Summarized Plan'!$I:$I,"=CCBPI Reload",'Summarized Plan'!$P:$P,"=1") -> 0 | G81: =+E81*1.5 -> 0 | I81: Total | J81: =SUM(J78:J80) -> #REF! | K81: =SUM(K78:K80) -> 1 | L81: =SUM(L78:L80) -> 320 | M81: =SUM(M78:M80) -> 320 | N81: =IF(ISERROR(K81/J81),"-",K81/J81) -> - | R81: ='Fleet Report'!I128 -> 95 | S81: ='Fleet Report'!E124 -> 93 | T81: ='Fleet Report'!F125 -> 57 | U81: =+T81/S81 -> 0.61290323
B82: TOTAL | C82: =SUM(C73:C81) -> 0 | D82: =SUM(D74:D80) -> 0 | E82: =SUM(E74:E80) -> 0 | F82: =SUM(F74:F80) -> 0 | G82: =SUM(G74:G80) -> 0
I83: PAR-LWS | J83: Shipments | L83: Physical Cases | N83: Efficiency | P83: Standard Reasons | R83: ='Fleet Report'!M123 -> 2 | S83: Breakdown/PM
J84: Planned | K84: Dispatched | L84: Planned | M84: Dispatched
I85: Current | J85: =COUNTIFS('Summarized Plan'!$G:$G,'Report Summary'!I83,'Summarized Plan'!$H:$H,'Report Summary'!$C$2) -> 3 | K85: =SUMIFS('Summarized Plan'!$P:$P,'Summarized Plan'!$G:$G,'Report Summary'!I83,'Summarized Plan'!$H:$H,'Report Summary'!$C$2) -> 1 | L85: =SUMIFS('Summarized Plan'!$C:$C,'Summarized Plan'!$G:$G,'Report Summary'!I83,'Summarized Plan'!$H:$H,'Report Summary'!$C$2) -> 557 | M85: =SUMIFS('Summarized Plan'!$Q:$Q,'Summarized Plan'!$G:$G,'Report Summary'!I83,'Summarized Plan'!$H:$H,'Report Summary'!$C$2) -> 224 | N85: =IF(ISERROR(K85/J85),"-",K85/J85) -> 0.33333333 | P85: Utilized Units (Planned)
I86: Backlogs | J86: =SUMIF('Summarized Plan'!$G:$G,'Report Summary'!I83,'Summarized Plan'!$R:$R) -> #REF! | K86: =SUMIFS('Summarized Plan'!$P:$P,'Summarized Plan'!$R:$R,"=1",'Summarized Plan'!$G:$G,'Report Summary'!I83) -> 0 | L86: =SUMIFS('Summarized Plan'!$C:$C,'Summarized Plan'!$R:$R,"=1",'Summarized Plan'!$G:$G,'Report Summary'!I83) -> 0 | M86: =SUMIFS('Summarized Plan'!$Q:$Q,'Summarized Plan'!$R:$R,"=1",'Summarized Plan'!$G:$G,'Report Summary'!I83) -> 0 | N86: =IF(ISERROR(K86/J86),"-",K86/J86) -> -
I87: Advanced | J87: =SUMIF('Summarized Plan'!$G:$G,'Report Summary'!I83,'Summarized Plan'!$S:$S) -> #REF! | K87: =SUMIFS('Summarized Plan'!$P:$P,'Summarized Plan'!$S:$S,"=1",'Summarized Plan'!$G:$G,'Report Summary'!I83) -> 0 | L87: =SUMIFS('Summarized Plan'!$C:$C,'Summarized Plan'!$S:$S,"=1",'Summarized Plan'!$G:$G,'Report Summary'!I83) -> 0 | M87: =SUMIFS('Summarized Plan'!$Q:$Q,'Summarized Plan'!$S:$S,"=1",'Summarized Plan'!$G:$G,'Report Summary'!I83) -> 0 | N87: =IF(ISERROR(K87/J87),"-",K87/J87) -> -
I88: Total | J88: =SUM(J85:J87) -> #REF! | K88: =SUM(K85:K87) -> 1 | L88: =SUM(L85:L87) -> 557 | M88: =SUM(M85:M87) -> 224 | N88: =IF(ISERROR(K88/J88),"-",K88/J88) -> -
I90: BAG-WS | J90: Shipments | L90: Physical Cases | N90: Efficiency
J91: Planned | K91: Dispatched | L91: Planned | M91: Dispatched
I92: Current | J92: =COUNTIFS('Summarized Plan'!$G:$G,'Report Summary'!I90,'Summarized Plan'!$H:$H,'Report Summary'!$C$2) -> 2 | K92: =SUMIFS('Summarized Plan'!$P:$P,'Summarized Plan'!$G:$G,'Report Summary'!I90,'Summarized Plan'!$H:$H,'Report Summary'!$C$2) -> 1 | L92: =SUMIFS('Summarized Plan'!$C:$C,'Summarized Plan'!$G:$G,'Report Summary'!I90,'Summarized Plan'!$H:$H,'Report Summary'!$C$2) -> 519 | M92: =SUMIFS('Summarized Plan'!$Q:$Q,'Summarized Plan'!$G:$G,'Report Summary'!I90,'Summarized Plan'!$H:$H,'Report Summary'!$C$2) -> 182 | N92: =IF(ISERROR(K92/J92),"-",K92/J92) -> 0.5
I93: Backlogs | J93: =SUMIF('Summarized Plan'!$G:$G,'Report Summary'!I90,'Summarized Plan'!$R:$R) -> #REF! | K93: =SUMIFS('Summarized Plan'!$P:$P,'Summarized Plan'!$R:$R,"=1",'Summarized Plan'!$G:$G,'Report Summary'!I90) -> 0 | L93: =SUMIFS('Summarized Plan'!$C:$C,'Summarized Plan'!$R:$R,"=1",'Summarized Plan'!$G:$G,'Report Summary'!I90) -> 0 | M93: =SUMIFS('Summarized Plan'!$Q:$Q,'Summarized Plan'!$R:$R,"=1",'Summarized Plan'!$G:$G,'Report Summary'!I90) -> 0 | N93: =IF(ISERROR(K93/J93),"-",K93/J93) -> -
I94: Advanced | J94: =SUMIF('Summarized Plan'!$G:$G,'Report Summary'!I90,'Summarized Plan'!$S:$S) -> #REF! | K94: =SUMIFS('Summarized Plan'!$P:$P,'Summarized Plan'!$S:$S,"=1",'Summarized Plan'!$G:$G,'Report Summary'!I90) -> 0 | L94: =SUMIFS('Summarized Plan'!$C:$C,'Summarized Plan'!$S:$S,"=1",'Summarized Plan'!$G:$G,'Report Summary'!I90) -> 0 | M94: =SUMIFS('Summarized Plan'!$Q:$Q,'Summarized Plan'!$S:$S,"=1",'Summarized Plan'!$G:$G,'Report Summary'!I90) -> 0 | N94: =IF(ISERROR(K94/J94),"-",K94/J94) -> -
I95: Total | J95: =SUM(J92:J94) -> #REF! | K95: =SUM(K92:K94) -> 1 | L95: =SUM(L92:L94) -> 519 | M95: =SUM(M92:M94) -> 182 | N95: =IF(ISERROR(K95/J95),"-",K95/J95) -> -
I97: LP-WS | J97: Shipments | L97: Physical Cases | N97: Efficiency
J98: Planned | K98: Dispatched | L98: Planned | M98: Dispatched
I99: Current | J99: =COUNTIFS('Summarized Plan'!$G:$G,'Report Summary'!I97,'Summarized Plan'!$H:$H,'Report Summary'!$C$2) -> 8 | K99: =SUMIFS('Summarized Plan'!$P:$P,'Summarized Plan'!$G:$G,'Report Summary'!I97,'Summarized Plan'!$H:$H,'Report Summary'!$C$2) -> 4 | L99: =SUMIFS('Summarized Plan'!$C:$C,'Summarized Plan'!$G:$G,'Report Summary'!I97,'Summarized Plan'!$H:$H,'Report Summary'!$C$2) -> 2178 | M99: =SUMIFS('Summarized Plan'!$Q:$Q,'Summarized Plan'!$G:$G,'Report Summary'!I97,'Summarized Plan'!$H:$H,'Report Summary'!$C$2) -> 1037 | N99: =IF(ISERROR(K99/J99),"-",K99/J99) -> 0.5
I100: Backlogs | J100: =SUMIF('Summarized Plan'!$G:$G,'Report Summary'!I97,'Summarized Plan'!$R:$R) -> #REF! | K100: =SUMIFS('Summarized Plan'!$P:$P,'Summarized Plan'!$R:$R,"=1",'Summarized Plan'!$G:$G,'Report Summary'!I97) -> 0 | L100: =SUMIFS('Summarized Plan'!$C:$C,'Summarized Plan'!$R:$R,"=1",'Summarized Plan'!$G:$G,'Report Summary'!I97) -> 0 | M100: =SUMIFS('Summarized Plan'!$Q:$Q,'Summarized Plan'!$R:$R,"=1",'Summarized Plan'!$G:$G,'Report Summary'!I97) -> 0 | N100: =IF(ISERROR(K100/J100),"-",K100/J100) -> -
I101: Advanced | J101: =SUMIF('Summarized Plan'!$G:$G,'Report Summary'!I97,'Summarized Plan'!$S:$S) -> #REF! | K101: =SUMIFS('Summarized Plan'!$P:$P,'Summarized Plan'!$S:$S,"=1",'Summarized Plan'!$G:$G,'Report Summary'!I97) -> 0 | L101: =SUMIFS('Summarized Plan'!$C:$C,'Summarized Plan'!$S:$S,"=1",'Summarized Plan'!$G:$G,'Report Summary'!I97) -> 0 | M101: =SUMIFS('Summarized Plan'!$Q:$Q,'Summarized Plan'!$S:$S,"=1",'Summarized Plan'!$G:$G,'Report Summary'!I97) -> 0 | N101: =IF(ISERROR(K101/J101),"-",K101/J101) -> -
I102: Total | J102: =SUM(J99:J101) -> #REF! | K102: =SUM(K99:K101) -> 4 | L102: =SUM(L99:L101) -> 2178 | M102: =SUM(M99:M101) -> 1037 | N102: =IF(ISERROR(K102/J102),"-",K102/J102) -> -
I104: MAN-WS | J104: Shipments | L104: Physical Cases | N104: Efficiency
J105: Planned | K105: Dispatched | L105: Planned | M105: Dispatched
...

Sheet Fleet Report
A1: Company Owned Truck Availability | H1: Fleet Report on Availability of Company Owned Trucks | Q1: TPD Availability | X1: VENDOR | Y1: COMMITMENT | Z1: ACTUAL TRUCK | AA1: % | AD1: COMMITMENT TO KA | AE1: ASSIGNED KA | AF1: ACTUAL UNIT USED TO KA | AG1: Feb % | AH1: ACTUAL UNIT USED TO CORE | AI1: UTILIZED TRUCK | AK1: BREAKDOWN | AL1: NO DRIVER | AM1: CODING | AN1: NOT UTILIZED DUE TO LOW BOOKING | AO1: UNUTILIZED TRUCK
A2: Plate Number | B2: Driver | C2: Service Model | D2: Number of Trip per Truck | E2: Truck Available | F2: Truck Used | H2: Plate# | I2: Pallet 1x1 | J2: Pallet 1x1.2 | K2: Condition | L2: Uncondition | M2: Breakdown | Q2: Plate Number | R2: Driver | S2: Service Model | T2: Number of Trip per Truck | U2: Truck Available | V2: Truck Used
A3: NFI765 | B3: =IFERROR(VLOOKUP(A3,'DISPATCHED (VT11)'!T$7:V$781,2,FALSE),"") -> AULISTIA | C3: =IFERROR(VLOOKUP(A3,'DISPATCHED (VT11)'!T$7:V$781,3,FALSE),"") -> KA | D3: =+COUNTIF('DISPATCHED (VT11)'!L:L,'Fleet Report'!A3) -> 1 | E3: =_xlfn.XLOOKUP(A3,H:H,K:K) -> 1 | F3: =IF(E3="","B",IF(D3=0,0,1+D3-D3)) -> 1 | H3: NFI765 | I3: =_xlfn.XLOOKUP(H3,'Truck Utilization'!B:B,'Truck Utilization'!D:D) -> 4 | J3: 4P | K3: =IF(M3=1,"","1") -> 1 | P3: BENLINE | Q3: AAQ9458 | R3: =VLOOKUP(Q3,'DISPATCHED (VT11)'!T$7:V$789,2,FALSE) -> GARCIA | S3: =VLOOKUP(Q3,'DISPATCHED (VT11)'!T$15:V$789,3,FALSE) -> KA | T3: =+COUNTIF('DISPATCHED (VT11)'!L:L,'Fleet Report'!Q3) -> 1 | V3: =IF(T3=0,0,1+T3-T3) -> 1 | X3: BENLINE | Y3: =+COUNTIF(P:P,X3) -> 4 | Z3: =+COUNTIFS(P:P,X3,V:V,"=1") -> 3 | AA3: =+Z3/Y3 -> 0.75 | AE3: =+COUNTIFS([2]Dispatch!$F:$F,"=1",[2]Dispatch!$O:$O,"=KA",[2]Dispatch!$A:$A,X3) -> #VALUE! | AP3: =IFERROR(VLOOKUP(Q3,'Truck Utilization'!B$3:C$237,2,FALSE),"") -> ONG
A4: NFI767 | B4: =IFERROR(VLOOKUP(A4,'DISPATCHED (VT11)'!T$7:V$781,2,FALSE),"") -> CELZO | C4: =IFERROR(VLOOKUP(A4,'DISPATCHED (VT11)'!T$7:V$781,3,FALSE),"") -> KA | D4: =+COUNTIF('DISPATCHED (VT11)'!L:L,'Fleet Report'!A4) -> 1 | E4: =_xlfn.XLOOKUP(A4,H:H,K:K) -> 1 | F4: =IF(E4="","B",IF(D4=0,0,1+D4-D4)) -> 1 | H4: NFI767 | I4: =_xlfn.XLOOKUP(H4,'Truck Utilization'!B:B,'Truck Utilization'!D:D) -> 4 | J4: 4P | K4: =IF(M4=1,"","1") -> 1 | P4: BENLINE | Q4: CAA5968 | R4: =VLOOKUP(Q4,'DISPATCHED (VT11)'!T$7:V$789,2,FALSE) -> nebreja | S4: =VLOOKUP(Q4,'DISPATCHED (VT11)'!T$15:V$789,3,FALSE) -> KA | T4: =+COUNTIF('DISPATCHED (VT11)'!L:L,'Fleet Report'!Q4) -> 1 | V4: =IF(T4=0,0,1+T4-T4) -> 1 | X4: JEKESA | Y4: =+COUNTIF(P:P,X4) -> 15 | Z4: =+COUNTIFS(P:P,X4,V:V,"=1") -> 8 | AA4: =+Z4/Y4 -> 0.53333333 | AE4: =+COUNTIFS([2]Dispatch!$F:$F,"=1",[2]Dispatch!$O:$O,"=KA",[2]Dispatch!$A:$A,X4) -> #VALUE! | AP4: =IFERROR(VLOOKUP(Q4,'Truck Utilization'!B$3:C$237,2,FALSE),"") -> ONG
A5: NFI903 | B5: =IFERROR(VLOOKUP(A5,'DISPATCHED (VT11)'!T$7:V$781,2,FALSE),"") | C5: =IFERROR(VLOOKUP(A5,'DISPATCHED (VT11)'!T$7:V$781,3,FALSE),"") | D5: =+COUNTIF('DISPATCHED (VT11)'!L:L,'Fleet Report'!A5) -> 0 | E5: =_xlfn.XLOOKUP(A5,H:H,K:K) -> 1 | F5: =IF(E5="","B",IF(D5=0,0,1+D5-D5)) -> 0 | H5: NFI903 | I5: =_xlfn.XLOOKUP(H5,'Truck Utilization'!B:B,'Truck Utilization'!D:D) -> 4 | J5: 4P | K5: =IF(M5=1,"","1") -> 1 | P5: BENLINE | Q5: CAA7228 | R5: =VLOOKUP(Q5,'DISPATCHED (VT11)'!T$7:V$789,2,FALSE) -> #N/A | S5: =VLOOKUP(Q5,'DISPATCHED (VT11)'!T$15:V$789,3,FALSE) -> #N/A | T5: =+COUNTIF('DISPATCHED (VT11)'!L:L,'Fleet Report'!Q5) -> 0 | V5: =IF(T5=0,0,1+T5-T5) -> 0 | X5: ONG | Y5: =+COUNTIF(P:P,X5) -> 29 | Z5: =+COUNTIFS(P:P,X5,V:V,"=1") -> 14 | AA5: =+Z5/Y5 -> 0.48275862 | AE5: =+COUNTIFS([2]Dispatch!$F:$F,"=1",[2]Dispatch!$O:$O,"=KA",[2]Dispatch!$A:$A,X5) -> #VALUE! | AP5: =IFERROR(VLOOKUP(Q5,'Truck Utilization'!B$3:C$237,2,FALSE),"") -> ONG
A6: NFI923 | B6: =IFERROR(VLOOKUP(A6,'DISPATCHED (VT11)'!T$7:V$781,2,FALSE),"") -> DAWAL | C6: =IFERROR(VLOOKUP(A6,'DISPATCHED (VT11)'!T$7:V$781,3,FALSE),"") -> KA | D6: =+COUNTIF('DISPATCHED (VT11)'!L:L,'Fleet Report'!A6) -> 1 | E6: =_xlfn.XLOOKUP(A6,H:H,K:K) -> 1 | F6: =IF(E6="","B",IF(D6=0,0,1+D6-D6)) -> 1 | H6: NFI923 | I6: =_xlfn.XLOOKUP(H6,'Truck Utilization'!B:B,'Truck Utilization'!D:D) -> 4 | J6: 4P | K6: =IF(M6=1,"","1") -> 1 | P6: BENLINE | Q6: CAA9233 | R6: =VLOOKUP(Q6,'DISPATCHED (VT11)'!T$7:V$789,2,FALSE) -> CONTILLO | S6: =VLOOKUP(Q6,'DISPATCHED (VT11)'!T$15:V$789,3,FALSE) -> KA | T6: =+COUNTIF('DISPATCHED (VT11)'!L:L,'Fleet Report'!Q6) -> 1 | V6: =IF(T6=0,0,1+T6-T6) -> 1 | X6: RODMAC | Y6: =+COUNTIF(P:P,X6) -> 18 | Z6: =+COUNTIFS(P:P,X6,V:V,"=1") -> 4 | AA6: =+Z6/Y6 -> 0.22222222 | AE6: =+COUNTIFS([2]Dispatch!$F:$F,"=1",[2]Dispatch!$O:$O,"=KA",[2]Dispatch!$A:$A,X6) -> #VALUE! | AP6: =IFERROR(VLOOKUP(Q6,'Truck Utilization'!B$3:C$237,2,FALSE),"") -> ONG
A7: PCQ860 | B7: =IFERROR(VLOOKUP(A7,'DISPATCHED (VT11)'!T$7:V$781,2,FALSE),"") -> BARCELO | C7: =IFERROR(VLOOKUP(A7,'DISPATCHED (VT11)'!T$7:V$781,3,FALSE),"") -> KA | D7: =+COUNTIF('DISPATCHED (VT11)'!L:L,'Fleet Report'!A7) -> 1 | E7: =_xlfn.XLOOKUP(A7,H:H,K:K) -> 1 | F7: =IF(E7="","B",IF(D7=0,0,1+D7-D7)) -> 1 | H7: PCQ860 | I7: =_xlfn.XLOOKUP(H7,'Truck Utilization'!B:B,'Truck Utilization'!D:D) -> 4 | J7: 4P | K7: =IF(M7=1,"","1") -> 1 | Q7: CAB9121 | R7: =VLOOKUP(Q7,'DISPATCHED (VT11)'!T$7:V$789,2,FALSE) -> #N/A | S7: =VLOOKUP(Q7,'DISPATCHED (VT11)'!T$15:V$789,3,FALSE) -> #N/A | T7: =+COUNTIF('DISPATCHED (VT11)'!L:L,'Fleet Report'!Q7) -> 0 | V7: =IF(T7=0,0,1+T7-T7) -> 0 | X7: SERVPRO | Y7: =+COUNTIF(P:P,X7) -> 4 | Z7: =+COUNTIFS(P:P,X7,V:V,"=1") -> 0 | AA7: =+Z7/Y7 -> 0 | AE7: =+COUNTIFS([2]Dispatch!$F:$F,"=1",[2]Dispatch!$O:$O,"=KA",[2]Dispatch!$A:$A,X7) -> #VALUE! | AP7: =IFERROR(VLOOKUP(Q7,'Truck Utilization'!B$3:C$237,2,FALSE),"") -> ONG
A8: PKO172 | B8: =IFERROR(VLOOKUP(A8,'DISPATCHED (VT11)'!T$7:V$781,2,FALSE),"") -> CANDA | C8: =IFERROR(VLOOKUP(A8,'DISPATCHED (VT11)'!T$7:V$781,3,FALSE),"") -> KA | D8: =+COUNTIF('DISPATCHED (VT11)'!L:L,'Fleet Report'!A8) -> 1 | E8: =_xlfn.XLOOKUP(A8,H:H,K:K) -> 1 | F8: =IF(E8="","B",IF(D8=0,0,1+D8-D8)) -> 1 | H8: PKO172 | I8: =_xlfn.XLOOKUP(H8,'Truck Utilization'!B:B,'Truck Utilization'!D:D) -> 4 | J8: 4P | K8: =IF(M8=1,"","1") -> 1 | P8: JEKESA | Q8: CAC8384 | R8: =VLOOKUP(Q8,'DISPATCHED (VT11)'!T$7:V$789,2,FALSE) -> #N/A | S8: =VLOOKUP(Q8,'DISPATCHED (VT11)'!T$15:V$789,3,FALSE) -> #N/A | T8: =+COUNTIF('DISPATCHED (VT11)'!L:L,'Fleet Report'!Q8) -> 0 | V8: =IF(T8=0,0,1+T8-T8) -> 0 | AP8: =IFERROR(VLOOKUP(Q8,'Truck Utilization'!B$3:C$237,2,FALSE),"") -> ONG
A9: PKO339 | B9: =IFERROR(VLOOKUP(A9,'DISPATCHED (VT11)'!T$7:V$781,2,FALSE),"") -> SALEM | C9: =IFERROR(VLOOKUP(A9,'DISPATCHED (VT11)'!T$7:V$781,3,FALSE),"") -> KA | D9: =+COUNTIF('DISPATCHED (VT11)'!L:L,'Fleet Report'!A9) -> 1 | E9: =_xlfn.XLOOKUP(A9,H:H,K:K) -> 1 | F9: =IF(E9="","B",IF(D9=0,0,1+D9-D9)) -> 1 | H9: PKO339 | I9: =_xlfn.XLOOKUP(H9,'Truck Utilization'!B:B,'Truck Utilization'!D:D) -> 4 | J9: 4P | K9: =IF(M9=1,"","1") -> 1 | P9: JEKESA | Q9: CAL3050 | R9: =VLOOKUP(Q9,'DISPATCHED (VT11)'!T$7:V$789,2,FALSE) -> PATURAY | S9: =VLOOKUP(Q9,'DISPATCHED (VT11)'!T$15:V$789,3,FALSE) -> KA | T9: =+COUNTIF('DISPATCHED (VT11)'!L:L,'Fleet Report'!Q9) -> 1 | V9: =IF(T9=0,0,1+T9-T9) -> 1 | AP9: =IFERROR(VLOOKUP(Q9,'Truck Utilization'!B$3:C$237,2,FALSE),"") -> ONG
A10: PKO720 | B10: =IFERROR(VLOOKUP(A10,'DISPATCHED (VT11)'!T$7:V$781,2,FALSE),"") -> ALIPIO | C10: =IFERROR(VLOOKUP(A10,'DISPATCHED (VT11)'!T$7:V$781,3,FALSE),"") -> KA | D10: =+COUNTIF('DISPATCHED (VT11)'!L:L,'Fleet Report'!A10) -> 1 | E10: =_xlfn.XLOOKUP(A10,H:H,K:K) -> 1 | F10: =IF(E10="","B",IF(D10=0,0,1+D10-D10)) -> 1 | H10: PKO720 | I10: =_xlfn.XLOOKUP(H10,'Truck Utilization'!B:B,'Truck Utilization'!D:D) -> 4 | J10: 4P | K10: =IF(M10=1,"","1") -> 1 | P10: JEKESA | Q10: CAL3058 | R10: =VLOOKUP(Q10,'DISPATCHED (VT11)'!T$7:V$789,2,FALSE) -> po | S10: =VLOOKUP(Q10,'DISPATCHED (VT11)'!T$15:V$789,3,FALSE) -> KA | T10: =+COUNTIF('DISPATCHED (VT11)'!L:L,'Fleet Report'!Q10) -> 1 | V10: =IF(T10=0,0,1+T10-T10) -> 1 | AP10: =IFERROR(VLOOKUP(Q10,'Truck Utilization'!B$3:C$237,2,FALSE),"") -> ONG
A11: PSQ152 | B11: =IFERROR(VLOOKUP(A11,'DISPATCHED (VT11)'!T$7:V$781,2,FALSE),"") -> MAHINAY | C11: =IFERROR(VLOOKUP(A11,'DISPATCHED (VT11)'!T$7:V$781,3,FALSE),"") -> TAG-LWS | D11: =+COUNTIF('DISPATCHED (VT11)'!L:L,'Fleet Report'!A11) -> 1 | E11: =_xlfn.XLOOKUP(A11,H:H,K:K) -> 1 | F11: =IF(E11="","B",IF(D11=0,0,1+D11-D11)) -> 1 | H11: PSQ152 | I11: =_xlfn.XLOOKUP(H11,'Truck Utilization'!B:B,'Truck Utilization'!D:D) -> 4 | J11: 4P | K11: =IF(M11=1,"","1") -> 1 | P11: JEKESA | Q11: CAL8015 | R11: =VLOOKUP(Q11,'DISPATCHED (VT11)'!T$7:V$789,2,FALSE) -> TALOSA | S11: =VLOOKUP(Q11,'DISPATCHED (VT11)'!T$15:V$789,3,FALSE) -> KA | T11: =+COUNTIF('DISPATCHED (VT11)'!L:L,'Fleet Report'!Q11) -> 1 | V11: =IF(T11=0,0,1+T11-T11) -> 1 | X11: VALDOZ | Y11: =+COUNTIF(P:P,X11) -> 12 | Z11: =+COUNTIFS(P:P,X11,V:V,"=1") -> 0 | AA11: =+Z11/Y11 -> 0 | AE11: =+COUNTIFS([2]Dispatch!$F:$F,"=1",[2]Dispatch!$O:$O,"=KA",[2]Dispatch!$A:$A,X11) -> #VALUE! | AP11: =IFERROR(VLOOKUP(Q11,'Truck Utilization'!B$3:C$237,2,FALSE),"") -> ONG
A12: PSQ370 | B12: =IFERROR(VLOOKUP(A12,'DISPATCHED (VT11)'!T$7:V$781,2,FALSE),"") -> CORTEZ | C12: =IFERROR(VLOOKUP(A12,'DISPATCHED (VT11)'!T$7:V$781,3,FALSE),"") -> KA | D12: =+COUNTIF('DISPATCHED (VT11)'!L:L,'Fleet Report'!A12) -> 1 | E12: =_xlfn.XLOOKUP(A12,H:H,K:K) -> 1 | F12: =IF(E12="","B",IF(D12=0,0,1+D12-D12)) -> 1 | H12: PSQ370 | I12: =_xlfn.XLOOKUP(H12,'Truck Utilization'!B:B,'Truck Utilization'!D:D) -> 4 | J12: 4P | K12: =IF(M12=1,"","1") -> 1 | P12: JEKESA | Q12: CAL8160 | R12: =VLOOKUP(Q12,'DISPATCHED (VT11)'!T$7:V$789,2,FALSE) -> masulit | S12: =VLOOKUP(Q12,'DISPATCHED (VT11)'!T$15:V$789,3,FALSE) -> KA | T12: =+COUNTIF('DISPATCHED (VT11)'!L:L,'Fleet Report'!Q12) -> 1 | V12: =IF(T12=0,0,1+T12-T12) -> 1 | X12: RAPID | Y12: =+COUNTIF(P:P,X12) -> 0 | Z12: =+COUNTIFS(P:P,X12,V:V,"=1") -> 0 | AA12: =+Z12/Y12 -> #DIV/0! | AE12: =+COUNTIFS([2]Dispatch!$F:$F,"=1",[2]Dispatch!$O:$O,"=KA",[2]Dispatch!$A:$A,X12) -> #VALUE! | AP12: =IFERROR(VLOOKUP(Q12,'Truck Utilization'!B$3:C$237,2,FALSE),"") -> ONG
A13: PSQ390 | B13: =IFERROR(VLOOKUP(A13,'DISPATCHED (VT11)'!T$7:V$781,2,FALSE),"") -> LOBETE | C13: =IFERROR(VLOOKUP(A13,'DISPATCHED (VT11)'!T$7:V$781,3,FALSE),"") -> KA | D13: =+COUNTIF('DISPATCHED (VT11)'!L:L,'Fleet Report'!A13) -> 1 | E13: =_xlfn.XLOOKUP(A13,H:H,K:K) -> 1 | F13: =IF(E13="","B",IF(D13=0,0,1+D13-D13)) -> 1 | H13: PSQ390 | I13: =_xlfn.XLOOKUP(H13,'Truck Utilization'!B:B,'Truck Utilization'!D:D) -> 4 | J13: 4P | K13: =IF(M13=1,"","1") -> 1 | P13: JEKESA | Q13: CAL8472 | R13: =VLOOKUP(Q13,'DISPATCHED (VT11)'!T$7:V$789,2,FALSE) -> YAGONIA | S13: =VLOOKUP(Q13,'DISPATCHED (VT11)'!T$15:V$789,3,FALSE) -> KA | T13: =+COUNTIF('DISPATCHED (VT11)'!L:L,'Fleet Report'!Q13) -> 1 | V13: =IF(T13=0,0,1+T13-T13) -> 1 | X13: GML | Y13: =+COUNTIF(P:P,X13) -> 0 | Z13: =+COUNTIFS(P:P,X13,V:V,"=1") -> 0 | AA13: =+Z13/Y13 -> #DIV/0! | AE13: =+COUNTIFS([2]Dispatch!$F:$F,"=1",[2]Dispatch!$O:$O,"=KA",[2]Dispatch!$A:$A,X13) -> #VALUE! | AP13: =IFERROR(VLOOKUP(Q13,'Truck Utilization'!B$3:C$237,2,FALSE),"") -> ONG
A14: ZTC562 | B14: =IFERROR(VLOOKUP(A14,'DISPATCHED (VT11)'!T$7:V$781,2,FALSE),"") -> JARCIA | C14: =IFERROR(VLOOKUP(A14,'DISPATCHED (VT11)'!T$7:V$781,3,FALSE),"") -> PAR-LWS | D14: =+COUNTIF('DISPATCHED (VT11)'!L:L,'Fleet Report'!A14) -> 1 | E14: =_xlfn.XLOOKUP(A14,H:H,K:K) -> 1 | F14: =IF(E14="","B",IF(D14=0,0,1+D14-D14)) -> 1 | H14: ZTC562 | I14: =_xlfn.XLOOKUP(H14,'Truck Utilization'!B:B,'Truck Utilization'!D:D) -> 4 | J14: 4P | K14: =IF(M14=1,"","1") -> 1 | P14: JEKESA | Q14: CAY3279 | R14: =VLOOKUP(Q14,'DISPATCHED (VT11)'!T$7:V$789,2,FALSE) -> #N/A | S14: =VLOOKUP(Q14,'DISPATCHED (VT11)'!T$15:V$789,3,FALSE) -> #N/A | T14: =+COUNTIF('DISPATCHED (VT11)'!L:L,'Fleet Report'!Q14) -> 0 | V14: =IF(T14=0,0,1+T14-T14) -> 0 | X14: UNLIMTED | Y14: =+COUNTIF(P:P,X14) -> 0 | Z14: =+COUNTIFS(P:P,X14,V:V,"=1") -> 0 | AA14: =+Z14/Y14 -> #DIV/0! | AE14: =+COUNTIFS([2]Dispatch!$F:$F,"=1",[2]Dispatch!$O:$O,"=KA",[2]Dispatch!$A:$A,X14) -> #VALUE! | AP14: =IFERROR(VLOOKUP(Q14,'Truck Utilization'!B$3:C$237,2,FALSE),"") -> ONG
A15: ZTC662 | B15: =IFERROR(VLOOKUP(A15,'DISPATCHED (VT11)'!T$7:V$781,2,FALSE),"") -> OPIDER | C15: =IFERROR(VLOOKUP(A15,'DISPATCHED (VT11)'!T$7:V$781,3,FALSE),"") -> KA | D15: =+COUNTIF('DISPATCHED (VT11)'!L:L,'Fleet Report'!A15) -> 1 | E15: =_xlfn.XLOOKUP(A15,H:H,K:K) -> 1 | F15: =IF(E15="","B",IF(D15=0,0,1+D15-D15)) -> 1 | H15: ZTC662 | I15: =_xlfn.XLOOKUP(H15,'Truck Utilization'!B:B,'Truck Utilization'!D:D) -> 4 | J15: 4P | K15: =IF(M15=1,"","1") -> 1 | P15: JEKESA | Q15: CAY8822 | R15: =VLOOKUP(Q15,'DISPATCHED (VT11)'!T$7:V$789,2,FALSE) -> #N/A | S15: =VLOOKUP(Q15,'DISPATCHED (VT11)'!T$15:V$789,3,FALSE) -> #N/A | T15: =+COUNTIF('DISPATCHED (VT11)'!L:L,'Fleet Report'!Q15) -> 0 | V15: =IF(T15=0,0,1+T15-T15) -> 0 | X15: GRAND TOTAL | Y15: =+SUM(Y3:Y14) -> 82 | Z15: =+SUM(Z3:Z14) -> 29 | AA15: =+Z15/Y15 -> 0.35365854 | AE15: =+COUNTIFS([2]Dispatch!$F:$F,"=1",[2]Dispatch!$O:$O,"=KA",[2]Dispatch!$A:$A,X15) -> #VALUE! | AP15: =IFERROR(VLOOKUP(Q15,'Truck Utilization'!B$3:C$237,2,FALSE),"") -> ONG
A16: ZTC954 | B16: =IFERROR(VLOOKUP(A16,'DISPATCHED (VT11)'!T$7:V$781,2,FALSE),"") | C16: =IFERROR(VLOOKUP(A16,'DISPATCHED (VT11)'!T$7:V$781,3,FALSE),"") | D16: =+COUNTIF('DISPATCHED (VT11)'!L:L,'Fleet Report'!A16) -> 0 | E16: =_xlfn.XLOOKUP(A16,H:H,K:K) -> 1 | F16: =IF(E16="","B",IF(D16=0,0,1+D16-D16)) -> 0 | H16: ZTC954 | I16: =_xlfn.XLOOKUP(H16,'Truck Utilization'!B:B,'Truck Utilization'!D:D) -> 4 | J16: 4P | K16: =IF(M16=1,"","1") -> 1 | P16: JEKESA | Q16: CAY9299 | R16: =VLOOKUP(Q16,'DISPATCHED (VT11)'!T$7:V$789,2,FALSE) -> #N/A | S16: =VLOOKUP(Q16,'DISPATCHED (VT11)'!T$15:V$789,3,FALSE) -> #N/A | T16: =+COUNTIF('DISPATCHED (VT11)'!L:L,'Fleet Report'!Q16) -> 0 | V16: =IF(T16=0,0,1+T16-T16) -> 0 | AP16: =IFERROR(VLOOKUP(Q16,'Truck Utilization'!B$3:C$237,2,FALSE),"") -> ONG
A17: ZTC974 | B17: =IFERROR(VLOOKUP(A17,'DISPATCHED (VT11)'!T$7:V$781,2,FALSE),"") -> ROXAS | C17: =IFERROR(VLOOKUP(A17,'DISPATCHED (VT11)'!T$7:V$781,3,FALSE),"") -> KA | D17: =+COUNTIF('DISPATCHED (VT11)'!L:L,'Fleet Report'!A17) -> 1 | E17: =_xlfn.XLOOKUP(A17,H:H,K:K) -> 1 | F17: =IF(E17="","B",IF(D17=0,0,1+D17-D17)) -> 1 | H17: ZTC974 | I17: =_xlfn.XLOOKUP(H17,'Truck Utilization'!B:B,'Truck Utilization'!D:D) -> 4 | J17: 4P | K17: =IF(M17=1,"","1") -> 1 | P17: JEKESA | Q17: CCN6054 | R17: =VLOOKUP(Q17,'DISPATCHED (VT11)'!T$7:V$789,2,FALSE) -> #N/A | S17: =VLOOKUP(Q17,'DISPATCHED (VT11)'!T$15:V$789,3,FALSE) -> #N/A | T17: =+COUNTIF('DISPATCHED (VT11)'!L:L,'Fleet Report'!Q17) -> 0 | V17: =IF(T17=0,0,1+T17-T17) -> 0 | AP17: =IFERROR(VLOOKUP(Q17,'Truck Utilization'!B$3:C$237,2,FALSE),"") -> ONG
A18: ZTC512 | B18: =IFERROR(VLOOKUP(A18,'DISPATCHED (VT11)'!T$7:V$781,2,FALSE),"") | C18: =IFERROR(VLOOKUP(A18,'DISPATCHED (VT11)'!T$7:V$781,3,FALSE),"") | D18: =+COUNTIF('DISPATCHED (VT11)'!L:L,'Fleet Report'!A18) -> 0 | E18: =_xlfn.XLOOKUP(A18,H:H,K:K) -> 1 | F18: =IF(E18="","B",IF(D18=0,0,1+D18-D18)) -> 0 | H18: ZTC512 | I18: =_xlfn.XLOOKUP(H18,'Truck Utilization'!B:B,'Truck Utilization'!D:D) -> 4 | J18: 4P | K18: =IF(M18=1,"","1") -> 1 | P18: JEKESA | Q18: CDJ4426 | R18: =VLOOKUP(Q18,'DISPATCHED (VT11)'!T$7:V$789,2,FALSE) -> #N/A | S18: =VLOOKUP(Q18,'DISPATCHED (VT11)'!T$15:V$789,3,FALSE) -> #N/A | T18: =+COUNTIF('DISPATCHED (VT11)'!L:L,'Fleet Report'!Q18) -> 0 | V18: =IF(T18=0,0,1+T18-T18) -> 0 | AP18: =IFERROR(VLOOKUP(Q18,'Truck Utilization'!B$3:C$237,2,FALSE),"") -> ONG
A19: ZSA902 | B19: =IFERROR(VLOOKUP(A19,'DISPATCHED (VT11)'!T$7:V$781,2,FALSE),"") | C19: =IFERROR(VLOOKUP(A19,'DISPATCHED (VT11)'!T$7:V$781,3,FALSE),"") | D19: =+COUNTIF('DISPATCHED (VT11)'!L:L,'Fleet Report'!A19) -> 0 | E19: =_xlfn.XLOOKUP(A19,H:H,K:K) -> 1 | F19: =IF(E19="","B",IF(D19=0,0,1+D19-D19)) -> 0 | H19: ZSA902 | I19: =_xlfn.XLOOKUP(H19,'Truck Utilization'!B:B,'Truck Utilization'!D:D) -> 4 | J19: 4P | K19: =IF(M19=1,"","1") -> 1 | P19: JEKESA | Q19: CDJ4725 | R19: =VLOOKUP(Q19,'DISPATCHED (VT11)'!T$7:V$789,2,FALSE) -> #N/A | S19: =VLOOKUP(Q19,'DISPATCHED (VT11)'!T$15:V$789,3,FALSE) -> #N/A | T19: =+COUNTIF('DISPATCHED (VT11)'!L:L,'Fleet Report'!Q19) -> 0 | V19: =IF(T19=0,0,1+T19-T19) -> 0 | AP19: =IFERROR(VLOOKUP(Q19,'Truck Utilization'!B$3:C$237,2,FALSE),"") -> ONG
A20: NFI863 | B20: =IFERROR(VLOOKUP(A20,'DISPATCHED (VT11)'!T$7:V$781,2,FALSE),"") | C20: =IFERROR(VLOOKUP(A20,'DISPATCHED (VT11)'!T$7:V$781,3,FALSE),"") | D20: =+COUNTIF('DISPATCHED (VT11)'!L:L,'Fleet Report'!A20) -> 0 | E20: =_xlfn.XLOOKUP(A20,H:H,K:K) -> 1 | F20: =IF(E20="","B",IF(D20=0,0,1+D20-D20)) -> 0 | H20: NFI863 | I20: =_xlfn.XLOOKUP(H20,'Truck Utilization'!B:B,'Truck Utilization'!D:D) -> 4 | J20: 4P | K20: =IF(M20=1,"","1") -> 1 | P20: JEKESA | Q20: CDJ5671 | R20: =VLOOKUP(Q20,'DISPATCHED (VT11)'!T$7:V$789,2,FALSE) -> ULEP | S20: =VLOOKUP(Q20,'DISPATCHED (VT11)'!T$15:V$789,3,FALSE) -> KA | T20: =+COUNTIF('DISPATCHED (VT11)'!L:L,'Fleet Report'!Q20) -> 1 | V20: =IF(T20=0,0,1+T20-T20) -> 1 | AP20: =IFERROR(VLOOKUP(Q20,'Truck Utilization'!B$3:C$237,2,FALSE),"") -> ONG
A21: PCQ522 | B21: =IFERROR(VLOOKUP(A21,'DISPATCHED (VT11)'!T$7:V$781,2,FALSE),"") -> LAXAMANA | C21: =IFERROR(VLOOKUP(A21,'DISPATCHED (VT11)'!T$7:V$781,3,FALSE),"") -> KA | D21: =+COUNTIF('DISPATCHED (VT11)'!L:L,'Fleet Report'!A21) -> 1 | E21: =_xlfn.XLOOKUP(A21,H:H,K:K) -> 1 | F21: =IF(E21="","B",IF(D21=0,0,1+D21-D21)) -> 1 | H21: PCQ522 | I21: =_xlfn.XLOOKUP(H21,'Truck Utilization'!B:B,'Truck Utilization'!D:D) -> 4 | J21: 4P | K21: =IF(M21=1,"","1") -> 1 | Q21: NAQ3267 | R21: =VLOOKUP(Q21,'DISPATCHED (VT11)'!T$7:V$789,2,FALSE) -> d talosa | S21: =VLOOKUP(Q21,'DISPATCHED (VT11)'!T$15:V$789,3,FALSE) -> KA | T21: =+COUNTIF('DISPATCHED (VT11)'!L:L,'Fleet Report'!Q21) -> 1 | V21: =IF(T21=0,0,1+T21-T21) -> 1 | AP21: =IFERROR(VLOOKUP(Q21,'Truck Utilization'!B$3:C$237,2,FALSE),"") -> ONG
A22: ZTC804 | B22: =IFERROR(VLOOKUP(A22,'DISPATCHED (VT11)'!T$7:V$781,2,FALSE),"") -> SANTOS | C22: =IFERROR(VLOOKUP(A22,'DISPATCHED (VT11)'!T$7:V$781,3,FALSE),"") -> KA | D22: =+COUNTIF('DISPATCHED (VT11)'!L:L,'Fleet Report'!A22) -> 1 | E22: =_xlfn.XLOOKUP(A22,H:H,K:K) -> 1 | F22: =IF(E22="","B",IF(D22=0,0,1+D22-D22)) -> 1 | H22: ZTC804 | I22: =_xlfn.XLOOKUP(H22,'Truck Utilization'!B:B,'Truck Utilization'!D:D) -> 4 | J22: 4P | K22: =IF(M22=1,"","1") -> 1 | P22: ONG | Q22: NCK7880 | R22: =VLOOKUP(Q22,'DISPATCHED (VT11)'!T$7:V$789,2,FALSE) -> #N/A | S22: =VLOOKUP(Q22,'DISPATCHED (VT11)'!T$15:V$789,3,FALSE) -> #N/A | T22: =+COUNTIF('DISPATCHED (VT11)'!L:L,'Fleet Report'!Q22) -> 0 | V22: =IF(T22=0,0,1+T22-T22) -> 0 | AP22: =IFERROR(VLOOKUP(Q22,'Truck Utilization'!B$3:C$237,2,FALSE),"") -> ONG
A23: PSQ480 | B23: =IFERROR(VLOOKUP(A23,'DISPATCHED (VT11)'!T$7:V$781,2,FALSE),"") -> PARE | C23: =IFERROR(VLOOKUP(A23,'DISPATCHED (VT11)'!T$7:V$781,3,FALSE),"") -> KA | D23: =+COUNTIF('DISPATCHED (VT11)'!L:L,'Fleet Report'!A23) -> 1 | E23: =_xlfn.XLOOKUP(A23,H:H,K:K) -> 1 | F23: =IF(E23="","B",IF(D23=0,0,1+D23-D23)) -> 1 | H23: PSQ480 | I23: =_xlfn.XLOOKUP(H23,'Truck Utilization'!B:B,'Truck Utilization'!D:D) -> 4 | J23: 4P | K23: =IF(M23=1,"","1") -> 1 | P23: ONG | Q23: NIJ7918 | R23: =VLOOKUP(Q23,'DISPATCHED (VT11)'!T$7:V$789,2,FALSE) -> estrella | S23: =VLOOKUP(Q23,'DISPATCHED (VT11)'!T$15:V$789,3,FALSE) -> KA | T23: =+COUNTIF('DISPATCHED (VT11)'!L:L,'Fleet Report'!Q23) -> 1 | V23: =IF(T23=0,0,1+T23-T23) -> 1 | AP23: =IFERROR(VLOOKUP(Q23,'Truck Utilization'!B$3:C$237,2,FALSE),"") -> ONG
A24: ZTC824 | B24: =IFERROR(VLOOKUP(A24,'DISPATCHED (VT11)'!T$7:V$781,2,FALSE),"") -> CABACABA | C24: =IFERROR(VLOOKUP(A24,'DISPATCHED (VT11)'!T$7:V$781,3,FALSE),"") -> KA | D24: =+COUNTIF('DISPATCHED (VT11)'!L:L,'Fleet Report'!A24) -> 1 | E24: =_xlfn.XLOOKUP(A24,H:H,K:K) -> 1 | F24: =IF(E24="","B",IF(D24=0,0,1+D24-D24)) -> 1 | H24: ZTC824 | I24: =_xlfn.XLOOKUP(H24,'Truck Utilization'!B:B,'Truck Utilization'!D:D) -> 4 | J24: 4P | K24: =IF(M24=1,"","1") -> 1 | P24: ONG | Q24: CAL8470 | R24: =VLOOKUP(Q24,'DISPATCHED (VT11)'!T$7:V$789,2,FALSE) -> #N/A | S24: =VLOOKUP(Q24,'DISPATCHED (VT11)'!T$15:V$789,3,FALSE) -> #N/A | T24: =+COUNTIF('DISPATCHED (VT11)'!L:L,'Fleet Report'!Q24) -> 0 | V24: =IF(T24=0,0,1+T24-T24) -> 0 | AP24: =IFERROR(VLOOKUP(Q24,'Truck Utilization'!B$3:C$237,2,FALSE),"") -> ONG
A25: NFI785 | B25: =IFERROR(VLOOKUP(A25,'DISPATCHED (VT11)'!T$7:V$781,2,FALSE),"") | C25: =IFERROR(VLOOKUP(A25,'DISPATCHED (VT11)'!T$7:V$781,3,FALSE),"") | D25: =+COUNTIF('DISPATCHED (VT11)'!L:L,'Fleet Report'!A25) -> 0 | E25: =_xlfn.XLOOKUP(A25,H:H,K:K) -> 1 | F25: =IF(E25="","B",IF(D25=0,0,1+D25-D25)) -> 0 | H25: NFI785 | I25: =_xlfn.XLOOKUP(H25,'Truck Utilization'!B:B,'Truck Utilization'!D:D) -> 4 | J25: 4P | K25: =IF(M25=1,"","1") -> 1 | P25: ONG | Q25: ABB1344 | R25: =VLOOKUP(Q25,'DISPATCHED (VT11)'!T$7:V$789,2,FALSE) -> HERRERA | S25: =VLOOKUP(Q25,'DISPATCHED (VT11)'!T$15:V$789,3,FALSE) -> KA | T25: =+COUNTIF('DISPATCHED (VT11)'!L:L,'Fleet Report'!Q25) -> 1 | V25: =IF(T25=0,0,1+T25-T25) -> 1 | AP25: =IFERROR(VLOOKUP(Q25,'Truck Utilization'!B$3:C$237,2,FALSE),"") -> RRAJ
A26: NFI795 | B26: =IFERROR(VLOOKUP(A26,'DISPATCHED (VT11)'!T$7:V$781,2,FALSE),"") | C26: =IFERROR(VLOOKUP(A26,'DISPATCHED (VT11)'!T$7:V$781,3,FALSE),"") | D26: =+COUNTIF('DISPATCHED (VT11)'!L:L,'Fleet Report'!A26) -> 0 | E26: =_xlfn.XLOOKUP(A26,H:H,K:K) -> 1 | F26: =IF(E26="","B",IF(D26=0,0,1+D26-D26)) -> 0 | H26: NFI795 | I26: =_xlfn.XLOOKUP(H26,'Truck Utilization'!B:B,'Truck Utilization'!D:D) -> 4 | J26: 4P | K26: =IF(M26=1,"","1") -> 1 | P26: ONG | Q26: ABB1427 | R26: =VLOOKUP(Q26,'DISPATCHED (VT11)'!T$7:V$789,2,FALSE) -> SARAGA | S26: =VLOOKUP(Q26,'DISPATCHED (VT11)'!T$15:V$789,3,FALSE) -> KA | T26: =+COUNTIF('DISPATCHED (VT11)'!L:L,'Fleet Report'!Q26) -> 1 | V26: =IF(T26=0,0,1+T26-T26) -> 1 | AP26: =IFERROR(VLOOKUP(Q26,'Truck Utilization'!B$3:C$237,2,FALSE),"") -> RRAJ
A27: NFI853 | B27: =IFERROR(VLOOKUP(A27,'DISPATCHED (VT11)'!T$7:V$781,2,FALSE),"") -> ALVARADO | C27: =IFERROR(VLOOKUP(A27,'DISPATCHED (VT11)'!T$7:V$781,3,FALSE),"") -> PAR-WS | D27: =+COUNTIF('DISPATCHED (VT11)'!L:L,'Fleet Report'!A27) -> 1 | E27: =_xlfn.XLOOKUP(A27,H:H,K:K) -> 1 | F27: =IF(E27="","B",IF(D27=0,0,1+D27-D27)) -> 1 | H27: NFI853 | I27: =_xlfn.XLOOKUP(H27,'Truck Utilization'!B:B,'Truck Utilization'!D:D) -> 4 | J27: 4P | K27: =IF(M27=1,"","1") -> 1 | P27: ONG | Q27: ABB1428 | R27: =VLOOKUP(Q27,'DISPATCHED (VT11)'!T$7:V$789,2,FALSE) -> LORETO | S27: =VLOOKUP(Q27,'DISPATCHED (VT11)'!T$15:V$789,3,FALSE) -> KA | T27: =+COUNTIF('DISPATCHED (VT11)'!L:L,'Fleet Report'!Q27) -> 1 | V27: =IF(T27=0,0,1+T27-T27) -> 1 | AP27: =IFERROR(VLOOKUP(Q27,'Truck Utilization'!B$3:C$237,2,FALSE),"") -> RRAJ
A28: ZTC502 | B28: =IFERROR(VLOOKUP(A28,'DISPATCHED (VT11)'!T$7:V$781,2,FALSE),"") -> AGUSTIN | C28: =IFERROR(VLOOKUP(A28,'DISPATCHED (VT11)'!T$7:V$781,3,FALSE),"") -> TAG-WS | D28: =+COUNTIF('DISPATCHED (VT11)'!L:L,'Fleet Report'!A28) -> 1 | E28: =_xlfn.XLOOKUP(A28,H:H,K:K) -> 1 | F28: =IF(E28="","B",IF(D28=0,0,1+D28-D28)) -> 1 | H28: ZTC502 | I28: =_xlfn.XLOOKUP(H28,'Truck Utilization'!B:B,'Truck Utilization'!D:D) -> 4 | J28: 4P | K28: =IF(M28=1,"","1") -> 1 | P28: ONG | Q28: ABB1430 | R28: =VLOOKUP(Q28,'DISPATCHED (VT11)'!T$7:V$789,2,FALSE) -> H.BANGGABANGGA | S28: =VLOOKUP(Q28,'DISPATCHED (VT11)'!T$15:V$789,3,FALSE) -> KA | T28: =+COUNTIF('DISPATCHED (VT11)'!L:L,'Fleet Report'!Q28) -> 1 | V28: =IF(T28=0,0,1+T28-T28) -> 1 | AP28: =IFERROR(VLOOKUP(Q28,'Truck Utilization'!B$3:C$237,2,FALSE),"") -> RRAJ
A29: DAD9136 | B29: =IFERROR(VLOOKUP(A29,'DISPATCHED (VT11)'!T$7:V$781,2,FALSE),"") -> BANTEL | C29: =IFERROR(VLOOKUP(A29,'DISPATCHED (VT11)'!T$7:V$781,3,FALSE),"") -> TAG-DP | D29: =+COUNTIF('DISPATCHED (VT11)'!L:L,'Fleet Report'!A29) -> 1 | E29: =_xlfn.XLOOKUP(A29,H:H,K:K) -> 1 | F29: =IF(E29="","B",IF(D29=0,0,1+D29-D29)) -> 1 | H29: DAD9136 | I29: =_xlfn.XLOOKUP(H29,'Truck Utilization'!B:B,'Truck Utilization'!D:D) -> 6 | J29: 4P | K29: =IF(M29=1,"","1") -> 1 | P29: ONG | Q29: ACK4539 | R29: =VLOOKUP(Q29,'DISPATCHED (VT11)'!T$7:V$789,2,FALSE) -> #N/A | S29: =VLOOKUP(Q29,'DISPATCHED (VT11)'!T$15:V$789,3,FALSE) -> #N/A | T29: =+COUNTIF('DISPATCHED (VT11)'!L:L,'Fleet Report'!Q29) -> 0 | V29: =IF(T29=0,0,1+T29-T29) -> 0 | AP29: =IFERROR(VLOOKUP(Q29,'Truck Utilization'!B$3:C$237,2,FALSE),"") -> RRAJ
A30: NFZ6891 | B30: =IFERROR(VLOOKUP(A30,'DISPATCHED (VT11)'!T$7:V$781,2,FALSE),"") -> 0 | C30: =IFERROR(VLOOKUP(A30,'DISPATCHED (VT11)'!T$7:V$781,3,FALSE),"") | D30: =+COUNTIF('DISPATCHED (VT11)'!L:L,'Fleet Report'!A30) -> 1 | E30: =_xlfn.XLOOKUP(A30,H:H,K:K) -> 1 | F30: =IF(E30="","B",IF(D30=0,0,1+D30-D30)) -> 1 | H30: NFZ6891 | I30: =_xlfn.XLOOKUP(H30,'Truck Utilization'!B:B,'Truck Utilization'!D:D) -> 6 | J30: 4P | K30: =IF(M30=1,"","1") -> 1 | P30: ONG | Q30: AVA4604 | R30: =VLOOKUP(Q30,'DISPATCHED (VT11)'!T$7:V$789,2,FALSE) -> #N/A | S30: =VLOOKUP(Q30,'DISPATCHED (VT11)'!T$15:V$789,3,FALSE) -> #N/A | T30: =+COUNTIF('DISPATCHED (VT11)'!L:L,'Fleet Report'!Q30) -> 0 | V30: =IF(T30=0,0,1+T30-T30) -> 0 | AP30: =IFERROR(VLOOKUP(Q30,'Truck Utilization'!B$3:C$237,2,FALSE),"") -> RRAJ
A31: NFZ6740 | B31: =IFERROR(VLOOKUP(A31,'DISPATCHED (VT11)'!T$7:V$781,2,FALSE),"") | C31: =IFERROR(VLOOKUP(A31,'DISPATCHED (VT11)'!T$7:V$781,3,FALSE),"") | D31: =+COUNTIF('DISPATCHED (VT11)'!L:L,'Fleet Report'!A31) -> 0 | E31: =_xlfn.XLOOKUP(A31,H:H,K:K) -> 1 | F31: =IF(E31="","B",IF(D31=0,0,1+D31-D31)) -> 0 | H31: NFZ6740 | I31: =_xlfn.XLOOKUP(H31,'Truck Utilization'!B:B,'Truck Utilization'!D:D) -> 6 | J31: 4P | K31: =IF(M31=1,"","1") -> 1 | P31: ONG | Q31: CAQ6545 | R31: =VLOOKUP(Q31,'DISPATCHED (VT11)'!T$7:V$789,2,FALSE) -> #N/A | S31: =VLOOKUP(Q31,'DISPATCHED (VT11)'!T$15:V$789,3,FALSE) -> #N/A | T31: =+COUNTIF('DISPATCHED (VT11)'!L:L,'Fleet Report'!Q31) -> 0 | V31: =IF(T31=0,0,1+T31-T31) -> 0 | AP31: =IFERROR(VLOOKUP(Q31,'Truck Utilization'!B$3:C$237,2,FALSE),"") -> RRAJ
A32: DAE4388 | B32: =IFERROR(VLOOKUP(A32,'DISPATCHED (VT11)'!T$7:V$781,2,FALSE),"") -> MOIT | C32: =IFERROR(VLOOKUP(A32,'DISPATCHED (VT11)'!T$7:V$781,3,FALSE),"") -> PAR-LWS | D32: =+COUNTIF('DISPATCHED (VT11)'!L:L,'Fleet Report'!A32) -> 1 | E32: =_xlfn.XLOOKUP(A32,H:H,K:K) -> 1 | F32: =IF(E32="","B",IF(D32=0,0,1+D32-D32)) -> 1 | H32: DAE4388 | I32: =_xlfn.XLOOKUP(H32,'Truck Utilization'!B:B,'Truck Utilization'!D:D) -> 6 | J32: 4P | K32: =IF(M32=1,"","1") -> 1 | P32: ONG | Q32: CAR9975 | R32: =VLOOKUP(Q32,'DISPATCHED (VT11)'!T$7:V$789,2,FALSE) -> #N/A | S32: =VLOOKUP(Q32,'DISPATCHED (VT11)'!T$15:V$789,3,FALSE) -> #N/A | T32: =+COUNTIF('DISPATCHED (VT11)'!L:L,'Fleet Report'!Q32) -> 0 | V32: =IF(T32=0,0,1+T32-T32) -> 0 | AP32: =IFERROR(VLOOKUP(Q32,'Truck Utilization'!B$3:C$237,2,FALSE),"") -> RRAJ
A33: DAE4390 | B33: =IFERROR(VLOOKUP(A33,'DISPATCHED (VT11)'!T$7:V$781,2,FALSE),"") -> 0 | C33: =IFERROR(VLOOKUP(A33,'DISPATCHED (VT11)'!T$7:V$781,3,FALSE),"") | D33: =+COUNTIF('DISPATCHED (VT11)'!L:L,'Fleet Report'!A33) -> 1 | E33: =_xlfn.XLOOKUP(A33,H:H,K:K) -> 1 | F33: =IF(E33="","B",IF(D33=0,0,1+D33-D33)) -> 1 | H33: DAE4390 | I33: =_xlfn.XLOOKUP(H33,'Truck Utilization'!B:B,'Truck Utilization'!D:D) -> 6 | J33: 4P | K33: =IF(M33=1,"","1") -> 1 | P33: ONG | Q33: CBP9768 | R33: =VLOOKUP(Q33,'DISPATCHED (VT11)'!T$7:V$789,2,FALSE) -> #N/A | S33: =VLOOKUP(Q33,'DISPATCHED (VT11)'!T$15:V$789,3,FALSE) -> #N/A | T33: =+COUNTIF('DISPATCHED (VT11)'!L:L,'Fleet Report'!Q33) -> 0 | V33: =IF(T33=0,0,1+T33-T33) -> 0 | AP33: =IFERROR(VLOOKUP(Q33,'Truck Utilization'!B$3:C$237,2,FALSE),"") -> RRAJ
... A41: DAD9139 | B41: =IFERROR(VLOOKUP(A41,'DISPATCHED (VT11)'!T$7:V$781,2,FALSE),"") -> 0 | C41: =IFERROR(VLOOKUP(A41,'DISPATCHED (VT11)'!T$7:V$781,3,FALSE),"") | D41: =+COUNTIF('DISPATCHED (VT11)'!L:L,'Fleet Report'!A41) -> 1 | E41: =_xlfn.XLOOKUP(A41,H:H,K:K) -> 1 | F41: =IF(E41="","B",IF(D41=0,0,1+D41-D41)) -> 1 | H41: DAD9139 | I41: =_xlfn.XLOOKUP(H41,'Truck Utilization'!B:B,'Truck Utilization'!D:D) -> 6 | J41: 4P | K41: =IF(M41=1,"","1") -> 1 | P41: ONG | Q41: NBP2827 | R41: =VLOOKUP(Q41,'DISPATCHED (VT11)'!T$7:V$789,2,FALSE) -> #N/A | S41: =VLOOKUP(Q41,'DISPATCHED (VT11)'!T$15:V$789,3,FALSE) -> #N/A | T41: =+COUNTIF('DISPATCHED (VT11)'!L:L,'Fleet Report'!Q41) -> 0 | V41: =IF(T41=0,0,1+T41-T41) -> 0 | AP41: =IFERROR(VLOOKUP(Q41,'Truck Utilization'!B$3:C$237,2,FALSE),"") -> RRAJ
A42: DAD9138 | B42: =IFERROR(VLOOKUP(A42,'DISPATCHED (VT11)'!T$7:V$781,2,FALSE),"") | C42: =IFERROR(VLOOKUP(A42,'DISPATCHED (VT11)'!T$7:V$781,3,FALSE),"") | D42: =+COUNTIF('DISPATCHED (VT11)'!L:L,'Fleet Report'!A42) -> 0 | E42: =_xlfn.XLOOKUP(A42,H:H,K:K) | F42: =IF(E42="","B",IF(D42=0,0,1+D42-D42)) -> B | H42: DAD9138 | I42: =_xlfn.XLOOKUP(H42,'Truck Utilization'!B:B,'Truck Utilization'!D:D) -> 6 | J42: 4P | K42: =IF(M42=1,"","1") | M42: 1 | P42: ONG | Q42: NBP2828 | R42: =VLOOKUP(Q42,'DISPATCHED (VT11)'!T$7:V$789,2,FALSE) -> #N/A | S42: =VLOOKUP(Q42,'DISPATCHED (VT11)'!T$15:V$789,3,FALSE) -> #N/A | T42: =+COUNTIF('DISPATCHED (VT11)'!L:L,'Fleet Report'!Q42) -> 0 | V42: =IF(T42=0,0,1+T42-T42) -> 0 | AP42: =IFERROR(VLOOKUP(Q42,'Truck Utilization'!B$3:C$237,2,FALSE),"") -> RRAJ
A43: DAG5520 | B43: =IFERROR(VLOOKUP(A43,'DISPATCHED (VT11)'!T$7:V$781,2,FALSE),"") | C43: =IFERROR(VLOOKUP(A43,'DISPATCHED (VT11)'!T$7:V$781,3,FALSE),"") | D43: =+COUNTIF('DISPATCHED (VT11)'!L:L,'Fleet Report'!A43) -> 0 | E43: =_xlfn.XLOOKUP(A43,H:H,K:K) -> 1 | F43: =IF(E43="","B",IF(D43=0,0,1+D43-D43)) -> 0 | H43: DAG5520 | I43: =_xlfn.XLOOKUP(H43,'Truck Utilization'!B:B,'Truck Utilization'!D:D) -> 6 | J43: 4P | K43: =IF(M43=1,"","1") -> 1 | P43: ONG | Q43: NBP2837 | R43: =VLOOKUP(Q43,'DISPATCHED (VT11)'!T$7:V$789,2,FALSE) -> #N/A | S43: =VLOOKUP(Q43,'DISPATCHED (VT11)'!T$15:V$789,3,FALSE) -> #N/A | T43: =+COUNTIF('DISPATCHED (VT11)'!L:L,'Fleet Report'!Q43) -> 0 | V43: =IF(T43=0,0,1+T43-T43) -> 0 | AP43: =IFERROR(VLOOKUP(Q43,'Truck Utilization'!B$3:C$237,2,FALSE),"") -> RRAJ
A44: DAG5519 | B44: =IFERROR(VLOOKUP(A44,'DISPATCHED (VT11)'!T$7:V$781,2,FALSE),"") | C44: =IFERROR(VLOOKUP(A44,'DISPATCHED (VT11)'!T$7:V$781,3,FALSE),"") | D44: =+COUNTIF('DISPATCHED (VT11)'!L:L,'Fleet Report'!A44) -> 0 | E44: =_xlfn.XLOOKUP(A44,H:H,K:K) -> 1 | F44: =IF(E44="","B",IF(D44=0,0,1+D44-D44)) -> 0 | H44: DAG5519 | I44: =_xlfn.XLOOKUP(H44,'Truck Utilization'!B:B,'Truck Utilization'!D:D) -> 6 | J44: 4P | K44: =IF(M44=1,"","1") -> 1 | P44: ONG | Q44: NCK3264 | R44: =VLOOKUP(Q44,'DISPATCHED (VT11)'!T$7:V$789,2,FALSE) -> bien | S44: =VLOOKUP(Q44,'DISPATCHED (VT11)'!T$15:V$789,3,FALSE) -> KA | T44: =+COUNTIF('DISPATCHED (VT11)'!L:L,'Fleet Report'!Q44) -> 1 | V44: =IF(T44=0,0,1+T44-T44) -> 1 | AP44: =IFERROR(VLOOKUP(Q44,'Truck Utilization'!B$3:C$237,2,FALSE),"") -> RRAJ
A45: DAD9134 | B45: =IFERROR(VLOOKUP(A45,'DISPATCHED (VT11)'!T$7:V$781,2,FALSE),"") -> MULA | C45: =IFERROR(VLOOKUP(A45,'DISPATCHED (VT11)'!T$7:V$781,3,FALSE),"") -> LP-DP | D45: =+COUNTIF('DISPATCHED (VT11)'!L:L,'Fleet Report'!A45) -> 1 | E45: =_xlfn.XLOOKUP(A45,H:H,K:K) -> 1 | F45: =IF(E45="","B",IF(D45=0,0,1+D45-D45)) -> 1 | H45: DAD9134 | I45: =_xlfn.XLOOKUP(H45,'Truck Utilization'!B:B,'Truck Utilization'!D:D) -> 6 | J45: 4P | K45: =IF(M45=1,"","1") -> 1 | P45: ONG | Q45: NCK4036 | R45: =VLOOKUP(Q45,'DISPATCHED (VT11)'!T$7:V$789,2,FALSE) -> AQUINDE | S45: =VLOOKUP(Q45,'DISPATCHED (VT11)'!T$15:V$789,3,FALSE) -> KA | T45: =+COUNTIF('DISPATCHED (VT11)'!L:L,'Fleet Report'!Q45) -> 1 | V45: =IF(T45=0,0,1+T45-T45) -> 1 | AP45: =IFERROR(VLOOKUP(Q45,'Truck Utilization'!B$3:C$237,2,FALSE),"") -> RRAJ
A46: DAD9133 | B46: =IFERROR(VLOOKUP(A46,'DISPATCHED (VT11)'!T$7:V$781,2,FALSE),"") -> BASBAS | C46: =IFERROR(VLOOKUP(A46,'DISPATCHED (VT11)'!T$7:V$781,3,FALSE),"") -> LP-WS | D46: =+COUNTIF('DISPATCHED (VT11)'!L:L,'Fleet Report'!A46) -> 1 | E46: =_xlfn.XLOOKUP(A46,H:H,K:K) -> 1 | F46: =IF(E46="","B",IF(D46=0,0,1+D46-D46)) -> 1 | H46: DAD9133 | I46: =_xlfn.XLOOKUP(H46,'Truck Utilization'!B:B,'Truck Utilization'!D:D) -> 6 | J46: 4P | K46: =IF(M46=1,"","1") -> 1 | P46: ONG | Q46: NDH1740 | R46: =VLOOKUP(Q46,'DISPATCHED (VT11)'!T$7:V$789,2,FALSE) -> R.MANAYON | S46: =VLOOKUP(Q46,'DISPATCHED (VT11)'!T$15:V$789,3,FALSE) -> KA | T46: =+COUNTIF('DISPATCHED (VT11)'!L:L,'Fleet Report'!Q46) -> 1 | V46: =IF(T46=0,0,1+T46-T46) -> 1 | AP46: =IFERROR(VLOOKUP(Q46,'Truck Utilization'!B$3:C$237,2,FALSE),"") -> RRAJ
A47: DAD9130 | B47: =IFERROR(VLOOKUP(A47,'DISPATCHED (VT11)'!T$7:V$781,2,FALSE),"") -> BERSABE | C47: =IFERROR(VLOOKUP(A47,'DISPATCHED (VT11)'!T$7:V$781,3,FALSE),"") -> PAR-LWS | D47: =+COUNTIF('DISPATCHED (VT11)'!L:L,'Fleet Report'!A47) -> 1 | E47: =_xlfn.XLOOKUP(A47,H:H,K:K) -> 1 | F47: =IF(E47="","B",IF(D47=0,0,1+D47-D47)) -> 1 | H47: DAD9130 | I47: =_xlfn.XLOOKUP(H47,'Truck Utilization'!B:B,'Truck Utilization'!D:D) -> 6 | J47: 4P | K47: =IF(M47=1,"","1") -> 1 | P47: ONG | Q47: WIW311 | R47: =VLOOKUP(Q47,'DISPATCHED (VT11)'!T$7:V$789,2,FALSE) -> CASTILLO | S47: =VLOOKUP(Q47,'DISPATCHED (VT11)'!T$15:V$789,3,FALSE) -> KA | T47: =+COUNTIF('DISPATCHED (VT11)'!L:L,'Fleet Report'!Q47) -> 1 | V47: =IF(T47=0,0,1+T47-T47) -> 1 | AP47: =IFERROR(VLOOKUP(Q47,'Truck Utilization'!B$3:C$237,2,FALSE),"") -> RRAJ
A48: NAQ8939 | B48: =IFERROR(VLOOKUP(A48,'DISPATCHED (VT11)'!T$7:V$781,2,FALSE),"") | C48: =IFERROR(VLOOKUP(A48,'DISPATCHED (VT11)'!T$7:V$781,3,FALSE),"") | D48: =+COUNTIF('DISPATCHED (VT11)'!L:L,'Fleet Report'!A48) -> 0 | E48: =_xlfn.XLOOKUP(A48,H:H,K:K) -> 1 | F48: =IF(E48="","B",IF(D48=0,0,1+D48-D48)) -> 0 | H48: NAQ8939 | I48: =_xlfn.XLOOKUP(H48,'Truck Utilization'!B:B,'Truck Utilization'!D:D) -> 6 | J48: 4P | K48: =IF(M48=1,"","1") -> 1 | P48: ONG | Q48: CBQ9738 | R48: =VLOOKUP(Q48,'DISPATCHED (VT11)'!T$7:V$789,2,FALSE) -> #N/A | S48: =VLOOKUP(Q48,'DISPATCHED (VT11)'!T$15:V$789,3,FALSE) -> #N/A | T48: =+COUNTIF('DISPATCHED (VT11)'!L:L,'Fleet Report'!Q48) -> 0 | V48: =IF(T48=0,0,1+T48-T48) -> 0 | AP48: =IFERROR(VLOOKUP(Q48,'Truck Utilization'!B$3:C$237,2,FALSE),"") -> ROGERSON
A49: NAQ8940 | B49: =IFERROR(VLOOKUP(A49,'DISPATCHED (VT11)'!T$7:V$781,2,FALSE),"") -> ACEBRON | C49: =IFERROR(VLOOKUP(A49,'DISPATCHED (VT11)'!T$7:V$781,3,FALSE),"") -> TAG-DP | D49: =+COUNTIF('DISPATCHED (VT11)'!L:L,'Fleet Report'!A49) -> 1 | E49: =_xlfn.XLOOKUP(A49,H:H,K:K) -> 1 | F49: =IF(E49="","B",IF(D49=0,0,1+D49-D49)) -> 1 | H49: NAQ8940 | I49: =_xlfn.XLOOKUP(H49,'Truck Utilization'!B:B,'Truck Utilization'!D:D) -> 6 | J49: 4P | K49: =IF(M49=1,"","1") -> 1 | P49: ONG | Q49: CBF3215 | R49: =VLOOKUP(Q49,'DISPATCHED (VT11)'!T$7:V$789,2,FALSE) -> #N/A | S49: =VLOOKUP(Q49,'DISPATCHED (VT11)'!T$15:V$789,3,FALSE) -> #N/A | T49: =+COUNTIF('DISPATCHED (VT11)'!L:L,'Fleet Report'!Q49) -> 0 | V49: =IF(T49=0,0,1+T49-T49) -> 0 | AP49: =IFERROR(VLOOKUP(Q49,'Truck Utilization'!B$3:C$237,2,FALSE),"") -> ROGERSON
A50: NAQ8941 | B50: =IFERROR(VLOOKUP(A50,'DISPATCHED (VT11)'!T$7:V$781,2,FALSE),"") -> MORALES | C50: =IFERROR(VLOOKUP(A50,'DISPATCHED (VT11)'!T$7:V$781,3,FALSE),"") -> PAR-WS | D50: =+COUNTIF('DISPATCHED (VT11)'!L:L,'Fleet Report'!A50) -> 1 | E50: =_xlfn.XLOOKUP(A50,H:H,K:K) -> 1 | F50: =IF(E50="","B",IF(D50=0,0,1+D50-D50)) -> 1 | H50: NAQ8941 | I50: =_xlfn.XLOOKUP(H50,'Truck Utilization'!B:B,'Truck Utilization'!D:D) -> 6 | J50: 4P | K50: =IF(M50=1,"","1") -> 1 | P50: ONG | Q50: NHA4790 | R50: =VLOOKUP(Q50,'DISPATCHED (VT11)'!T$7:V$789,2,FALSE) -> #N/A | S50: =VLOOKUP(Q50,'DISPATCHED (VT11)'!T$15:V$789,3,FALSE) -> #N/A | T50: =+COUNTIF('DISPATCHED (VT11)'!L:L,'Fleet Report'!Q50) -> 0 | V50: =IF(T50=0,0,1+T50-T50) -> 0 | AP50: =IFERROR(VLOOKUP(Q50,'Truck Utilization'!B$3:C$237,2,FALSE),"") -> FAST
A51: NAQ8946 | B51: =IFERROR(VLOOKUP(A51,'DISPATCHED (VT11)'!T$7:V$781,2,FALSE),"") -> SALVIO | C51: =IFERROR(VLOOKUP(A51,'DISPATCHED (VT11)'!T$7:V$781,3,FALSE),"") -> WS-SRC | D51: =+COUNTIF('DISPATCHED (VT11)'!L:L,'Fleet Report'!A51) -> 1 | E51: =_xlfn.XLOOKUP(A51,H:H,K:K) -> 1 | F51: =IF(E51="","B",IF(D51=0,0,1+D51-D51)) -> 1 | H51: NAQ8946 | I51: =_xlfn.XLOOKUP(H51,'Truck Utilization'!B:B,'Truck Utilization'!D:D) -> 6 | J51: 4P | K51: =IF(M51=1,"","1") -> 1 | Q51: CCE1705 | R51: =VLOOKUP(Q51,'DISPATCHED (VT11)'!T$7:V$789,2,FALSE) -> #N/A | S51: =VLOOKUP(Q51,'DISPATCHED (VT11)'!T$15:V$789,3,FALSE) -> #N/A | T51: =+COUNTIF('DISPATCHED (VT11)'!L:L,'Fleet Report'!Q51) -> 0 | V51: =IF(T51=0,0,1+T51-T51) -> 0 | AP51: =IFERROR(VLOOKUP(Q51,'Truck Utilization'!B$3:C$237,2,FALSE),"") -> FAST
A52: NAQ8948 | B52: =IFERROR(VLOOKUP(A52,'DISPATCHED (VT11)'!T$7:V$781,2,FALSE),"") | C52: =IFERROR(VLOOKUP(A52,'DISPATCHED (VT11)'!T$7:V$781,3,FALSE),"") | D52: =+COUNTIF('DISPATCHED (VT11)'!L:L,'Fleet Report'!A52) -> 0 | E52: =_xlfn.XLOOKUP(A52,H:H,K:K) -> 1 | F52: =IF(E52="","B",IF(D52=0,0,1+D52-D52)) -> 0 | H52: NAQ8948 | I52: =_xlfn.XLOOKUP(H52,'Truck Utilization'!B:B,'Truck Utilization'!D:D) -> 6 | J52: 4P | K52: =IF(M52=1,"","1") -> 1 | P52: RODMAC | Q52: CBQ3421 | R52: =VLOOKUP(Q52,'DISPATCHED (VT11)'!T$7:V$789,2,FALSE) -> #N/A | S52: =VLOOKUP(Q52,'DISPATCHED (VT11)'!T$15:V$789,3,FALSE) -> #N/A | T52: =+COUNTIF('DISPATCHED (VT11)'!L:L,'Fleet Report'!Q52) -> 0 | V52: =IF(T52=0,0,1+T52-T52) -> 0 | AP52: =IFERROR(VLOOKUP(Q52,'Truck Utilization'!B$3:C$237,2,FALSE),"") -> FAST
A53: NAQ8949 | B53: =IFERROR(VLOOKUP(A53,'DISPATCHED (VT11)'!T$7:V$781,2,FALSE),"") -> SOLLANO | C53: =IFERROR(VLOOKUP(A53,'DISPATCHED (VT11)'!T$7:V$781,3,FALSE),"") -> LP-WS | D53: =+COUNTIF('DISPATCHED (VT11)'!L:L,'Fleet Report'!A53) -> 1 | E53: =_xlfn.XLOOKUP(A53,H:H,K:K) -> 1 | F53: =IF(E53="","B",IF(D53=0,0,1+D53-D53)) -> 1 | H53: NAQ8949 | I53: =_xlfn.XLOOKUP(H53,'Truck Utilization'!B:B,'Truck Utilization'!D:D) -> 6 | J53: 4P | K53: =IF(M53=1,"","1") -> 1 | P53: RODMAC | Q53: CCE3817 | R53: =VLOOKUP(Q53,'DISPATCHED (VT11)'!T$7:V$789,2,FALSE) -> #N/A | S53: =VLOOKUP(Q53,'DISPATCHED (VT11)'!T$15:V$789,3,FALSE) -> #N/A | T53: =+COUNTIF('DISPATCHED (VT11)'!L:L,'Fleet Report'!Q53) -> 0 | V53: =IF(T53=0,0,1+T53-T53) -> 0 | AP53: =IFERROR(VLOOKUP(Q53,'Truck Utilization'!B$3:C$237,2,FALSE),"") -> FAST
A54: NAQ8960 | B54: =IFERROR(VLOOKUP(A54,'DISPATCHED (VT11)'!T$7:V$781,2,FALSE),"") -> FRESCO | C54: =IFERROR(VLOOKUP(A54,'DISPATCHED (VT11)'!T$7:V$781,3,FALSE),"") -> WS-SRC | D54: =+COUNTIF('DISPATCHED (VT11)'!L:L,'Fleet Report'!A54) -> 1 | E54: =_xlfn.XLOOKUP(A54,H:H,K:K) -> 1 | F54: =IF(E54="","B",IF(D54=0,0,1+D54-D54)) -> 1 | H54: NAQ8960 | I54: =_xlfn.XLOOKUP(H54,'Truck Utilization'!B:B,'Truck Utilization'!D:D) -> 6 | J54: 4P | K54: =IF(M54=1,"","1") -> 1 | P54: RODMAC | Q54: WQB639 | R54: =VLOOKUP(Q54,'DISPATCHED (VT11)'!T$7:V$789,2,FALSE) -> #N/A | S54: =VLOOKUP(Q54,'DISPATCHED (VT11)'!T$15:V$789,3,FALSE) -> #N/A | T54: =+COUNTIF('DISPATCHED (VT11)'!L:L,'Fleet Report'!Q54) -> 0 | V54: =IF(T54=0,0,1+T54-T54) -> 0 | AP54: =IFERROR(VLOOKUP(Q54,'Truck Utilization'!B$3:C$237,2,FALSE),"") -> FAST
A55: NAQ8961 | B55: =IFERROR(VLOOKUP(A55,'DISPATCHED (VT11)'!T$7:V$781,2,FALSE),"") -> ANZANO | C55: =IFERROR(VLOOKUP(A55,'DISPATCHED (VT11)'!T$7:V$781,3,FALSE),"") -> LP-DP | D55: =+COUNTIF('DISPATCHED (VT11)'!L:L,'Fleet Report'!A55) -> 1 | E55: =_xlfn.XLOOKUP(A55,H:H,K:K) -> 1 | F55: =IF(E55="","B",IF(D55=0,0,1+D55-D55)) -> 1 | H55: NAQ8961 | I55: =_xlfn.XLOOKUP(H55,'Truck Utilization'!B:B,'Truck Utilization'!D:D) -> 6 | J55: 4P | K55: =IF(M55=1,"","1") -> 1 | P55: RODMAC | Q55: UDO494 | R55: =VLOOKUP(Q55,'DISPATCHED (VT11)'!T$7:V$789,2,FALSE) -> BUSTARGA | S55: =VLOOKUP(Q55,'DISPATCHED (VT11)'!T$15:V$789,3,FALSE) -> KA | T55: =+COUNTIF('DISPATCHED (VT11)'!L:L,'Fleet Report'!Q55) -> 1 | V55: =IF(T55=0,0,1+T55-T55) -> 1 | AP55: =IFERROR(VLOOKUP(Q55,'Truck Utilization'!B$3:C$237,2,FALSE),"") -> RRAJ
A56: NAQ8962 | B56: =IFERROR(VLOOKUP(A56,'DISPATCHED (VT11)'!T$7:V$781,2,FALSE),"") | C56: =IFERROR(VLOOKUP(A56,'DISPATCHED (VT11)'!T$7:V$781,3,FALSE),"") | D56: =+COUNTIF('DISPATCHED (VT11)'!L:L,'Fleet Report'!A56) -> 0 | E56: =_xlfn.XLOOKUP(A56,H:H,K:K) -> 1 | F56: =IF(E56="","B",IF(D56=0,0,1+D56-D56)) -> 0 | H56: NAQ8962 | I56: =_xlfn.XLOOKUP(H56,'Truck Utilization'!B:B,'Truck Utilization'!D:D) -> 6 | J56: 4P | K56: =IF(M56=1,"","1") -> 1 | P56: RODMAC | Q56: NBP2818 | R56: =VLOOKUP(Q56,'DISPATCHED (VT11)'!T$7:V$789,2,FALSE) -> GARCIA | S56: =VLOOKUP(Q56,'DISPATCHED (VT11)'!T$15:V$789,3,FALSE) -> KA | T56: =+COUNTIF('DISPATCHED (VT11)'!L:L,'Fleet Report'!Q56) -> 1 | V56: =IF(T56=0,0,1+T56-T56) -> 1 | AP56: =IFERROR(VLOOKUP(Q56,'Truck Utilization'!B$3:C$237,2,FALSE),"") -> RRAJ
A57: NAQ8972 | B57: =IFERROR(VLOOKUP(A57,'DISPATCHED (VT11)'!T$7:V$781,2,FALSE),"") -> DAMAYO | C57: =IFERROR(VLOOKUP(A57,'DISPATCHED (VT11)'!T$7:V$781,3,FALSE),"") -> PAR-WS | D57: =+COUNTIF('DISPATCHED (VT11)'!L:L,'Fleet Report'!A57) -> 1 | E57: =_xlfn.XLOOKUP(A57,H:H,K:K) -> 1 | F57: =IF(E57="","B",IF(D57=0,0,1+D57-D57)) -> 1 | H57: NAQ8972 | I57: =_xlfn.XLOOKUP(H57,'Truck Utilization'!B:B,'Truck Utilization'!D:D) -> 6 | J57: 4P | K57: =IF(M57=1,"","1") -> 1 | P57: JEKESA | Q57: CCK5975 | R57: =VLOOKUP(Q57,'DISPATCHED (VT11)'!T$7:V$789,2,FALSE) -> J.BANGGABANGGA | S57: =VLOOKUP(Q57,'DISPATCHED (VT11)'!T$15:V$789,3,FALSE) -> KA | T57: =+COUNTIF('DISPATCHED (VT11)'!L:L,'Fleet Report'!Q57) -> 1 | V57: =IF(T57=0,0,1+T57-T57) -> 1 | AP57: =IFERROR(VLOOKUP(Q57,'Truck Utilization'!B$3:C$237,2,FALSE),"") -> RRAJ
A58: NAQ8973 | B58: =IFERROR(VLOOKUP(A58,'DISPATCHED (VT11)'!T$7:V$781,2,FALSE),"") -> RAVELO | C58: =IFERROR(VLOOKUP(A58,'DISPATCHED (VT11)'!T$7:V$781,3,FALSE),"") -> LP-WS | D58: =+COUNTIF('DISPATCHED (VT11)'!L:L,'Fleet Report'!A58) -> 1 | E58: =_xlfn.XLOOKUP(A58,H:H,K:K) -> 1 | F58: =IF(E58="","B",IF(D58=0,0,1+D58-D58)) -> 1 | H58: NAQ8973 | I58: =_xlfn.XLOOKUP(H58,'Truck Utilization'!B:B,'Truck Utilization'!D:D) -> 6 | J58: 4P | K58: =IF(M58=1,"","1") -> 1 | P58: RODMAC | Q58: CCB9370 | R58: =VLOOKUP(Q58,'DISPATCHED (VT11)'!T$7:V$789,2,FALSE) -> #N/A | S58: =VLOOKUP(Q58,'DISPATCHED (VT11)'!T$15:V$789,3,FALSE) -> #N/A | T58: =+COUNTIF('DISPATCHED (VT11)'!L:L,'Fleet Report'!Q58) -> 0 | V58: =IF(T58=0,0,1+T58-T58) -> 0 | AP58: =IFERROR(VLOOKUP(Q58,'Truck Utilization'!B$3:C$237,2,FALSE),"") -> RRAJ
A59: NAQ8974 | B59: =IFERROR(VLOOKUP(A59,'DISPATCHED (VT11)'!T$7:V$781,2,FALSE),"") | C59: =IFERROR(VLOOKUP(A59,'DISPATCHED (VT11)'!T$7:V$781,3,FALSE),"") | D59: =+COUNTIF('DISPATCHED (VT11)'!L:L,'Fleet Report'!A59) -> 0 | E59: =_xlfn.XLOOKUP(A59,H:H,K:K) -> 1 | F59: =IF(E59="","B",IF(D59=0,0,1+D59-D59)) -> 0 | H59: NAQ8974 | I59: =_xlfn.XLOOKUP(H59,'Truck Utilization'!B:B,'Truck Utilization'!D:D) -> 6 | J59: 4P | K59: =IF(M59=1,"","1") -> 1 | P59: RODMAC | Q59: CCE5597 | R59: =VLOOKUP(Q59,'DISPATCHED (VT11)'!T$7:V$789,2,FALSE) -> vibar | S59: =VLOOKUP(Q59,'DISPATCHED (VT11)'!T$15:V$789,3,FALSE) -> KA | T59: =+COUNTIF('DISPATCHED (VT11)'!L:L,'Fleet Report'!Q59) -> 1 | V59: =IF(T59=0,0,1+T59-T59) -> 1 | AP59: =IFERROR(VLOOKUP(Q59,'Truck Utilization'!B$3:C$237,2,FALSE),"") -> RRAJ
A60: NAQ8977 | B60: =IFERROR(VLOOKUP(A60,'DISPATCHED (VT11)'!T$7:V$781,2,FALSE),"") -> MANALUSAN | C60: =IFERROR(VLOOKUP(A60,'DISPATCHED (VT11)'!T$7:V$781,3,FALSE),"") -> PAC-WS | D60: =+COUNTIF('DISPATCHED (VT11)'!L:L,'Fleet Report'!A60) -> 1 | E60: =_xlfn.XLOOKUP(A60,H:H,K:K) -> 1 | F60: =IF(E60="","B",IF(D60=0,0,1+D60-D60)) -> 1 | H60: NAQ8977 | I60: =_xlfn.XLOOKUP(H60,'Truck Utilization'!B:B,'Truck Utilization'!D:D) -> 6 | J60: 4P | K60: =IF(M60=1,"","1") -> 1 | P60: RODMAC | Q60: NBC4915 | R60: =VLOOKUP(Q60,'DISPATCHED (VT11)'!T$7:V$789,2,FALSE) -> marquez | S60: =VLOOKUP(Q60,'DISPATCHED (VT11)'!T$15:V$789,3,FALSE) -> KA | T60: =+COUNTIF('DISPATCHED (VT11)'!L:L,'Fleet Report'!Q60) -> 1 | V60: =IF(T60=0,0,1+T60-T60) -> 1 | AP60: =IFERROR(VLOOKUP(Q60,'Truck Utilization'!B$3:C$237,2,FALSE),"") -> EMME
A61: NAQ9062 | B61: =IFERROR(VLOOKUP(A61,'DISPATCHED (VT11)'!T$7:V$781,2,FALSE),"") | C61: =IFERROR(VLOOKUP(A61,'DISPATCHED (VT11)'!T$7:V$781,3,FALSE),"") | D61: =+COUNTIF('DISPATCHED (VT11)'!L:L,'Fleet Report'!A61) -> 0 | E61: =_xlfn.XLOOKUP(A61,H:H,K:K) -> 1 | F61: =IF(E61="","B",IF(D61=0,0,1+D61-D61)) -> 0 | H61: NAQ9062 | I61: =_xlfn.XLOOKUP(H61,'Truck Utilization'!B:B,'Truck Utilization'!D:D) -> 6 | J61: 4P | K61: =IF(M61=1,"","1") -> 1 | P61: RODMAC | Q61: NBC4914 | R61: =VLOOKUP(Q61,'DISPATCHED (VT11)'!T$7:V$789,2,FALSE) -> #N/A | S61: =VLOOKUP(Q61,'DISPATCHED (VT11)'!T$15:V$789,3,FALSE) -> #N/A | T61: =+COUNTIF('DISPATCHED (VT11)'!L:L,'Fleet Report'!Q61) -> 0 | V61: =IF(T61=0,0,1+T61-T61) -> 0 | AP61: =IFERROR(VLOOKUP(Q61,'Truck Utilization'!B$3:C$237,2,FALSE),"") -> EMME
A62: NAQ9063 | B62: =IFERROR(VLOOKUP(A62,'DISPATCHED (VT11)'!T$7:V$781,2,FALSE),"") -> FERGUSON | C62: =IFERROR(VLOOKUP(A62,'DISPATCHED (VT11)'!T$7:V$781,3,FALSE),"") -> TAG-DP | D62: =+COUNTIF('DISPATCHED (VT11)'!L:L,'Fleet Report'!A62) -> 1 | E62: =_xlfn.XLOOKUP(A62,H:H,K:K) -> 1 | F62: =IF(E62="","B",IF(D62=0,0,1+D62-D62)) -> 1 | H62: NAQ9063 | I62: =_xlfn.XLOOKUP(H62,'Truck Utilization'!B:B,'Truck Utilization'!D:D) -> 6 | J62: 4P | K62: =IF(M62=1,"","1") -> 1 | P62: JEKESA | Q62: NBC4916 | R62: =VLOOKUP(Q62,'DISPATCHED (VT11)'!T$7:V$789,2,FALSE) -> danque | S62: =VLOOKUP(Q62,'DISPATCHED (VT11)'!T$15:V$789,3,FALSE) -> KA | T62: =+COUNTIF('DISPATCHED (VT11)'!L:L,'Fleet Report'!Q62) -> 1 | V62: =IF(T62=0,0,1+T62-T62) -> 1 | AP62: =IFERROR(VLOOKUP(Q62,'Truck Utilization'!B$3:C$237,2,FALSE),"") -> EMME
A63: NAQ9068 | B63: =IFERROR(VLOOKUP(A63,'DISPATCHED (VT11)'!T$7:V$781,2,FALSE),"") -> MENDOZA | C63: =IFERROR(VLOOKUP(A63,'DISPATCHED (VT11)'!T$7:V$781,3,FALSE),"") -> KA | D63: =+COUNTIF('DISPATCHED (VT11)'!L:L,'Fleet Report'!A63) -> 1 | E63: =_xlfn.XLOOKUP(A63,H:H,K:K) -> 1 | F63: =IF(E63="","B",IF(D63=0,0,1+D63-D63)) -> 1 | H63: NAQ9068 | I63: =_xlfn.XLOOKUP(H63,'Truck Utilization'!B:B,'Truck Utilization'!D:D) -> 6 | J63: 4P | K63: =IF(M63=1,"","1") -> 1 | P63: RODMAC | Q63: CCE6479 | R63: =VLOOKUP(Q63,'DISPATCHED (VT11)'!T$7:V$789,2,FALSE) -> #N/A | S63: =VLOOKUP(Q63,'DISPATCHED (VT11)'!T$15:V$789,3,FALSE) -> #N/A | T63: =+COUNTIF('DISPATCHED (VT11)'!L:L,'Fleet Report'!Q63) -> 0 | V63: =IF(T63=0,0,1+T63-T63) -> 0 | AP63: =IFERROR(VLOOKUP(Q63,'Truck Utilization'!B$3:C$237,2,FALSE),"") -> ROGERSON
... A71: NFZ6701 | B71: =IFERROR(VLOOKUP(A71,'DISPATCHED (VT11)'!T$7:V$781,2,FALSE),"") | C71: =IFERROR(VLOOKUP(A71,'DISPATCHED (VT11)'!T$7:V$781,3,FALSE),"") | D71: =+COUNTIF('DISPATCHED (VT11)'!L:L,'Fleet Report'!A71) -> 0 | E71: =_xlfn.XLOOKUP(A71,H:H,K:K) -> 1 | F71: =IF(E71="","B",IF(D71=0,0,1+D71-D71)) -> 0 | H71: NFZ6701 | I71: =_xlfn.XLOOKUP(H71,'Truck Utilization'!B:B,'Truck Utilization'!D:D) -> 6 | J71: 4P | K71: =IF(M71=1,"","1") -> 1 | P71: RODMAC | Q71: CAF2646 | R71: =VLOOKUP(Q71,'DISPATCHED (VT11)'!T$7:V$789,2,FALSE) -> #N/A | S71: =VLOOKUP(Q71,'DISPATCHED (VT11)'!T$15:V$789,3,FALSE) -> #N/A | T71: =+COUNTIF('DISPATCHED (VT11)'!L:L,'Fleet Report'!Q71) -> 0 | V71: =IF(T71=0,0,1+T71-T71) -> 0 | AP71: =IFERROR(VLOOKUP(Q71,'Truck Utilization'!B$3:C$237,2,FALSE),"") -> AMOURE
A72: NFZ6886 | B72: =IFERROR(VLOOKUP(A72,'DISPATCHED (VT11)'!T$7:V$781,2,FALSE),"") | C72: =IFERROR(VLOOKUP(A72,'DISPATCHED (VT11)'!T$7:V$781,3,FALSE),"") | D72: =+COUNTIF('DISPATCHED (VT11)'!L:L,'Fleet Report'!A72) -> 0 | E72: =_xlfn.XLOOKUP(A72,H:H,K:K) -> 1 | F72: =IF(E72="","B",IF(D72=0,0,1+D72-D72)) -> 0 | H72: NFZ6886 | I72: =_xlfn.XLOOKUP(H72,'Truck Utilization'!B:B,'Truck Utilization'!D:D) -> 6 | J72: 4P | K72: =IF(M72=1,"","1") -> 1 | Q72: WJQ559 | R72: =VLOOKUP(Q72,'DISPATCHED (VT11)'!T$7:V$789,2,FALSE) -> #N/A | S72: =VLOOKUP(Q72,'DISPATCHED (VT11)'!T$15:V$789,3,FALSE) -> #N/A | T72: =+COUNTIF('DISPATCHED (VT11)'!L:L,'Fleet Report'!Q72) -> 0 | V72: =IF(T72=0,0,1+T72-T72) -> 0 | AP72: =IFERROR(VLOOKUP(Q72,'Truck Utilization'!B$3:C$237,2,FALSE),"") -> AMOURE
A73: NFZ6894 | B73: =IFERROR(VLOOKUP(A73,'DISPATCHED (VT11)'!T$7:V$781,2,FALSE),"") -> SEVILLA | C73: =IFERROR(VLOOKUP(A73,'DISPATCHED (VT11)'!T$7:V$781,3,FALSE),"") -> PAR-DP | D73: =+COUNTIF('DISPATCHED (VT11)'!L:L,'Fleet Report'!A73) -> 1 | E73: =_xlfn.XLOOKUP(A73,H:H,K:K) -> 1 | F73: =IF(E73="","B",IF(D73=0,0,1+D73-D73)) -> 1 | H73: NFZ6894 | I73: =_xlfn.XLOOKUP(H73,'Truck Utilization'!B:B,'Truck Utilization'!D:D) -> 6 | J73: 4P | K73: =IF(M73=1,"","1") -> 1 | P73: SERVPRO | Q73: TKI133 | R73: =VLOOKUP(Q73,'DISPATCHED (VT11)'!T$7:V$789,2,FALSE) -> #N/A | S73: =VLOOKUP(Q73,'DISPATCHED (VT11)'!T$15:V$789,3,FALSE) -> #N/A | T73: =+COUNTIF('DISPATCHED (VT11)'!L:L,'Fleet Report'!Q73) -> 0 | V73: =IF(T73=0,0,1+T73-T73) -> 0 | AP73: =IFERROR(VLOOKUP(Q73,'Truck Utilization'!B$3:C$237,2,FALSE),"") -> A TRANSLOADING
A74: NFZ6895 | B74: =IFERROR(VLOOKUP(A74,'DISPATCHED (VT11)'!T$7:V$781,2,FALSE),"") | C74: =IFERROR(VLOOKUP(A74,'DISPATCHED (VT11)'!T$7:V$781,3,FALSE),"") | D74: =+COUNTIF('DISPATCHED (VT11)'!L:L,'Fleet Report'!A74) -> 0 | E74: =_xlfn.XLOOKUP(A74,H:H,K:K) -> 1 | F74: =IF(E74="","B",IF(D74=0,0,1+D74-D74)) -> 0 | H74: NFZ6895 | I74: =_xlfn.XLOOKUP(H74,'Truck Utilization'!B:B,'Truck Utilization'!D:D) -> 6 | J74: 4P | K74: =IF(M74=1,"","1") -> 1 | P74: SERVPRO | Q74: NDZ8343 | R74: =VLOOKUP(Q74,'DISPATCHED (VT11)'!T$7:V$789,2,FALSE) -> #N/A | S74: =VLOOKUP(Q74,'DISPATCHED (VT11)'!T$15:V$789,3,FALSE) -> #N/A | T74: =+COUNTIF('DISPATCHED (VT11)'!L:L,'Fleet Report'!Q74) -> 0 | V74: =IF(T74=0,0,1+T74-T74) -> 0 | AP74: =IFERROR(VLOOKUP(Q74,'Truck Utilization'!B$3:C$237,2,FALSE),"") -> A TRANSLOADING
A75: NFZ6904 | B75: =IFERROR(VLOOKUP(A75,'DISPATCHED (VT11)'!T$7:V$781,2,FALSE),"") | C75: =IFERROR(VLOOKUP(A75,'DISPATCHED (VT11)'!T$7:V$781,3,FALSE),"") | D75: =+COUNTIF('DISPATCHED (VT11)'!L:L,'Fleet Report'!A75) -> 0 | E75: =_xlfn.XLOOKUP(A75,H:H,K:K) -> 1 | F75: =IF(E75="","B",IF(D75=0,0,1+D75-D75)) -> 0 | H75: NFZ6904 | I75: =_xlfn.XLOOKUP(H75,'Truck Utilization'!B:B,'Truck Utilization'!D:D) -> 6 | J75: 4P | K75: =IF(M75=1,"","1") -> 1 | P75: SERVPRO | Q75: RKN853 | R75: =VLOOKUP(Q75,'DISPATCHED (VT11)'!T$7:V$789,2,FALSE) -> #N/A | S75: =VLOOKUP(Q75,'DISPATCHED (VT11)'!T$15:V$789,3,FALSE) -> #N/A | T75: =+COUNTIF('DISPATCHED (VT11)'!L:L,'Fleet Report'!Q75) -> 0 | V75: =IF(T75=0,0,1+T75-T75) -> 0 | AP75: =IFERROR(VLOOKUP(Q75,'Truck Utilization'!B$3:C$237,2,FALSE),"") -> AMOURE
A76: NAQ8945 | B76: =IFERROR(VLOOKUP(A76,'DISPATCHED (VT11)'!T$7:V$781,2,FALSE),"") | C76: =IFERROR(VLOOKUP(A76,'DISPATCHED (VT11)'!T$7:V$781,3,FALSE),"") | D76: =+COUNTIF('DISPATCHED (VT11)'!L:L,'Fleet Report'!A76) -> 0 | E76: =_xlfn.XLOOKUP(A76,H:H,K:K) -> 1 | F76: =IF(E76="","B",IF(D76=0,0,1+D76-D76)) -> 0 | H76: NAQ8945 | I76: =_xlfn.XLOOKUP(H76,'Truck Utilization'!B:B,'Truck Utilization'!D:D) -> 6 | J76: 4P | K76: =IF(M76=1,"","1") -> 1 | P76: SERVPRO | Q76: RKG714 | R76: =VLOOKUP(Q76,'DISPATCHED (VT11)'!T$7:V$789,2,FALSE) -> #N/A | S76: =VLOOKUP(Q76,'DISPATCHED (VT11)'!T$15:V$789,3,FALSE) -> #N/A | T76: =+COUNTIF('DISPATCHED (VT11)'!L:L,'Fleet Report'!Q76) -> 0 | V76: =IF(T76=0,0,1+T76-T76) -> 0 | AP76: =IFERROR(VLOOKUP(Q76,'Truck Utilization'!B$3:C$237,2,FALSE),"") -> AMOURE
A77: NAQ9064 | B77: =IFERROR(VLOOKUP(A77,'DISPATCHED (VT11)'!T$7:V$781,2,FALSE),"") | C77: =IFERROR(VLOOKUP(A77,'DISPATCHED (VT11)'!T$7:V$781,3,FALSE),"") | D77: =+COUNTIF('DISPATCHED (VT11)'!L:L,'Fleet Report'!A77) -> 0 | E77: =_xlfn.XLOOKUP(A77,H:H,K:K) -> 1 | F77: =IF(E77="","B",IF(D77=0,0,1+D77-D77)) -> 0 | H77: NAQ9064 | I77: =_xlfn.XLOOKUP(H77,'Truck Utilization'!B:B,'Truck Utilization'!D:D) -> 6 | J77: 4P | K77: =IF(M77=1,"","1") -> 1 | Q77: NEL6574 | R77: =VLOOKUP(Q77,'DISPATCHED (VT11)'!T$7:V$789,2,FALSE) -> #N/A | S77: =VLOOKUP(Q77,'DISPATCHED (VT11)'!T$15:V$789,3,FALSE) -> #N/A | T77: =+COUNTIF('DISPATCHED (VT11)'!L:L,'Fleet Report'!Q77) -> 0 | V77: =IF(T77=0,0,1+T77-T77) -> 0 | AP77: =IFERROR(VLOOKUP(Q77,'Truck Utilization'!B$3:C$237,2,FALSE),"")
A78: NAQ8944 | B78: =IFERROR(VLOOKUP(A78,'DISPATCHED (VT11)'!T$7:V$781,2,FALSE),"") -> MAHUSAY | C78: =IFERROR(VLOOKUP(A78,'DISPATCHED (VT11)'!T$7:V$781,3,FALSE),"") -> KA | D78: =+COUNTIF('DISPATCHED (VT11)'!L:L,'Fleet Report'!A78) -> 1 | E78: =_xlfn.XLOOKUP(A78,H:H,K:K) -> 1 | F78: =IF(E78="","B",IF(D78=0,0,1+D78-D78)) -> 1 | H78: NAQ8944 | I78: =_xlfn.XLOOKUP(H78,'Truck Utilization'!B:B,'Truck Utilization'!D:D) -> 6 | J78: 4P | K78: =IF(M78=1,"","1") -> 1 | P78: VALDOZ | Q78: CCE6461 | R78: =VLOOKUP(Q78,'DISPATCHED (VT11)'!T$7:V$789,2,FALSE) -> #N/A | S78: =VLOOKUP(Q78,'DISPATCHED (VT11)'!T$15:V$789,3,FALSE) -> #N/A | T78: =+COUNTIF('DISPATCHED (VT11)'!L:L,'Fleet Report'!Q78) -> 0 | V78: =IF(T78=0,0,1+T78-T78) -> 0 | AP78: =IFERROR(VLOOKUP(Q78,'Truck Utilization'!B$3:C$237,2,FALSE),"") -> ROGERSON
A79: DAD9131 | B79: =IFERROR(VLOOKUP(A79,'DISPATCHED (VT11)'!T$7:V$781,2,FALSE),"") | C79: =IFERROR(VLOOKUP(A79,'DISPATCHED (VT11)'!T$7:V$781,3,FALSE),"") | D79: =+COUNTIF('DISPATCHED (VT11)'!L:L,'Fleet Report'!A79) -> 0 | E79: =_xlfn.XLOOKUP(A79,H:H,K:K) -> 1 | F79: =IF(E79="","B",IF(D79=0,0,1+D79-D79)) -> 0 | H79: DAD9131 | I79: =_xlfn.XLOOKUP(H79,'Truck Utilization'!B:B,'Truck Utilization'!D:D) -> 6 | J79: 4P | K79: =IF(M79=1,"","1") -> 1 | P79: VALDOZ | Q79: NGB3918 | R79: =VLOOKUP(Q79,'DISPATCHED (VT11)'!T$7:V$789,2,FALSE) -> #N/A | S79: =VLOOKUP(Q79,'DISPATCHED (VT11)'!T$15:V$789,3,FALSE) -> #N/A | T79: =+COUNTIF('DISPATCHED (VT11)'!L:L,'Fleet Report'!Q79) -> 0 | V79: =IF(T79=0,0,1+T79-T79) -> 0 | AP79: =IFERROR(VLOOKUP(Q79,'Truck Utilization'!B$3:C$237,2,FALSE),"") -> ROGERSON
A80: NRI646 | B80: =IFERROR(VLOOKUP(A80,'DISPATCHED (VT11)'!T$7:V$781,2,FALSE),"") | C80: =IFERROR(VLOOKUP(A80,'DISPATCHED (VT11)'!T$7:V$781,3,FALSE),"") | D80: =+COUNTIF('DISPATCHED (VT11)'!L:L,'Fleet Report'!A80) -> 0 | E80: =_xlfn.XLOOKUP(A80,H:H,K:K) -> 1 | F80: =IF(E80="","B",IF(D80=0,0,1+D80-D80)) -> 0 | H80: NRI646 | I80: =_xlfn.XLOOKUP(H80,'Truck Utilization'!B:B,'Truck Utilization'!D:D) -> 10 | J80: 8P | K80: =IF(M80=1,"","1") -> 1 | P80: VALDOZ | Q80: NGL8198 | R80: =VLOOKUP(Q80,'DISPATCHED (VT11)'!T$7:V$789,2,FALSE) -> #N/A | S80: =VLOOKUP(Q80,'DISPATCHED (VT11)'!T$15:V$789,3,FALSE) -> #N/A | T80: =+COUNTIF('DISPATCHED (VT11)'!L:L,'Fleet Report'!Q80) -> 0 | V80: =IF(T80=0,0,1+T80-T80) -> 0 | AP80: =IFERROR(VLOOKUP(Q80,'Truck Utilization'!B$3:C$237,2,FALSE),"") -> ROGERSON
A81: NRI689 | B81: =IFERROR(VLOOKUP(A81,'DISPATCHED (VT11)'!T$7:V$781,2,FALSE),"") | C81: =IFERROR(VLOOKUP(A81,'DISPATCHED (VT11)'!T$7:V$781,3,FALSE),"") | D81: =+COUNTIF('DISPATCHED (VT11)'!L:L,'Fleet Report'!A81) -> 0 | E81: =_xlfn.XLOOKUP(A81,H:H,K:K) -> 1 | F81: =IF(E81="","B",IF(D81=0,0,1+D81-D81)) -> 0 | H81: NRI689 | I81: =_xlfn.XLOOKUP(H81,'Truck Utilization'!B:B,'Truck Utilization'!D:D) -> 10 | J81: 8P | K81: =IF(M81=1,"","1") -> 1 | P81: VALDOZ | Q81: CAB2044 | R81: =VLOOKUP(Q81,'DISPATCHED (VT11)'!T$7:V$789,2,FALSE) -> #N/A | S81: =VLOOKUP(Q81,'DISPATCHED (VT11)'!T$15:V$789,3,FALSE) -> #N/A | T81: =+COUNTIF('DISPATCHED (VT11)'!L:L,'Fleet Report'!Q81) -> 0 | V81: =IF(T81=0,0,1+T81-T81) -> 0 | AP81: =IFERROR(VLOOKUP(Q81,'Truck Utilization'!B$3:C$237,2,FALSE),"") -> ROGERSON
A82: PCQ621 | B82: =IFERROR(VLOOKUP(A82,'DISPATCHED (VT11)'!T$7:V$781,2,FALSE),"") | C82: =IFERROR(VLOOKUP(A82,'DISPATCHED (VT11)'!T$7:V$781,3,FALSE),"") | D82: =+COUNTIF('DISPATCHED (VT11)'!L:L,'Fleet Report'!A82) -> 0 | E82: =_xlfn.XLOOKUP(A82,H:H,K:K) -> 1 | F82: =IF(E82="","B",IF(D82=0,0,1+D82-D82)) -> 0 | H82: PCQ621 | I82: =_xlfn.XLOOKUP(H82,'Truck Utilization'!B:B,'Truck Utilization'!D:D) -> 10 | J82: 8P | K82: =IF(M82=1,"","1") -> 1 | P82: VALDOZ | Q82: CBQ9459 | R82: =VLOOKUP(Q82,'DISPATCHED (VT11)'!T$7:V$789,2,FALSE) -> #N/A | S82: =VLOOKUP(Q82,'DISPATCHED (VT11)'!T$15:V$789,3,FALSE) -> #N/A | T82: =+COUNTIF('DISPATCHED (VT11)'!L:L,'Fleet Report'!Q82) -> 0 | V82: =IF(T82=0,0,1+T82-T82) -> 0 | AP82: =IFERROR(VLOOKUP(Q82,'Truck Utilization'!B$3:C$237,2,FALSE),"") -> ROGERSON
A83: PCQ671 | B83: =IFERROR(VLOOKUP(A83,'DISPATCHED (VT11)'!T$7:V$781,2,FALSE),"") | C83: =IFERROR(VLOOKUP(A83,'DISPATCHED (VT11)'!T$7:V$781,3,FALSE),"") | D83: =+COUNTIF('DISPATCHED (VT11)'!L:L,'Fleet Report'!A83) -> 0 | E83: =_xlfn.XLOOKUP(A83,H:H,K:K) -> 1 | F83: =IF(E83="","B",IF(D83=0,0,1+D83-D83)) -> 0 | H83: PCQ671 | I83: =_xlfn.XLOOKUP(H83,'Truck Utilization'!B:B,'Truck Utilization'!D:D) -> 10 | J83: 8P | K83: =IF(M83=1,"","1") -> 1 | P83: VALDOZ | R83: =VLOOKUP(Q83,'DISPATCHED (VT11)'!T$7:V$789,2,FALSE) -> 0 | S83: =VLOOKUP(Q83,'DISPATCHED (VT11)'!T$15:V$789,3,FALSE) | T83: =+COUNTIF('DISPATCHED (VT11)'!L:L,'Fleet Report'!Q83) -> 0 | V83: =IF(T83=0,0,1+T83-T83) -> 0 | AP83: =IFERROR(VLOOKUP(Q83,'Truck Utilization'!B$3:C$237,2,FALSE),"")
A84: PKO484 | B84: =IFERROR(VLOOKUP(A84,'DISPATCHED (VT11)'!T$7:V$781,2,FALSE),"") | C84: =IFERROR(VLOOKUP(A84,'DISPATCHED (VT11)'!T$7:V$781,3,FALSE),"") | D84: =+COUNTIF('DISPATCHED (VT11)'!L:L,'Fleet Report'!A84) -> 0 | E84: =_xlfn.XLOOKUP(A84,H:H,K:K) | F84: =IF(E84="","B",IF(D84=0,0,1+D84-D84)) -> B | H84: PKO484 | I84: =_xlfn.XLOOKUP(H84,'Truck Utilization'!B:B,'Truck Utilization'!D:D) -> 10 | J84: 8P | K84: =IF(M84=1,"","1") | M84: 1 | P84: VALDOZ | R84: =VLOOKUP(Q84,'DISPATCHED (VT11)'!T$7:V$789,2,FALSE) -> 0 | S84: =VLOOKUP(Q84,'DISPATCHED (VT11)'!T$15:V$789,3,FALSE) | T84: =+COUNTIF('DISPATCHED (VT11)'!L:L,'Fleet Report'!Q84) -> 0 | V84: =IF(T84=0,0,1+T84-T84) -> 0 | AP84: =IFERROR(VLOOKUP(Q84,'Truck Utilization'!B$3:C$237,2,FALSE),"")
A85: PKO522 | B85: =IFERROR(VLOOKUP(A85,'DISPATCHED (VT11)'!T$7:V$781,2,FALSE),"") -> LETRADA | C85: =IFERROR(VLOOKUP(A85,'DISPATCHED (VT11)'!T$7:V$781,3,FALSE),"") -> HOD | D85: =+COUNTIF('DISPATCHED (VT11)'!L:L,'Fleet Report'!A85) -> 1 | E85: =_xlfn.XLOOKUP(A85,H:H,K:K) -> 1 | F85: =IF(E85="","B",IF(D85=0,0,1+D85-D85)) -> 1 | H85: PKO522 | I85: =_xlfn.XLOOKUP(H85,'Truck Utilization'!B:B,'Truck Utilization'!D:D) -> 10 | J85: 8P | K85: =IF(M85=1,"","1") -> 1 | P85: VALDOZ | R85: =VLOOKUP(Q85,'DISPATCHED (VT11)'!T$7:V$789,2,FALSE) -> 0 | S85: =VLOOKUP(Q85,'DISPATCHED (VT11)'!T$15:V$789,3,FALSE) | T85: =+COUNTIF('DISPATCHED (VT11)'!L:L,'Fleet Report'!Q85) -> 0 | V85: =IF(T85=0,0,1+T85-T85) -> 0 | AP85: =IFERROR(VLOOKUP(Q85,'Truck Utilization'!B$3:C$237,2,FALSE),"")
A86: PKO542 | B86: =IFERROR(VLOOKUP(A86,'DISPATCHED (VT11)'!T$7:V$781,2,FALSE),"") | C86: =IFERROR(VLOOKUP(A86,'DISPATCHED (VT11)'!T$7:V$781,3,FALSE),"") | D86: =+COUNTIF('DISPATCHED (VT11)'!L:L,'Fleet Report'!A86) -> 0 | E86: =_xlfn.XLOOKUP(A86,H:H,K:K) -> 1 | F86: =IF(E86="","B",IF(D86=0,0,1+D86-D86)) -> 0 | H86: PKO542 | I86: =_xlfn.XLOOKUP(H86,'Truck Utilization'!B:B,'Truck Utilization'!D:D) -> 10 | J86: 8P | K86: =IF(M86=1,"","1") -> 1 | P86: VALDOZ | R86: =VLOOKUP(Q86,'DISPATCHED (VT11)'!T$7:V$789,2,FALSE) -> 0 | S86: =VLOOKUP(Q86,'DISPATCHED (VT11)'!T$15:V$789,3,FALSE) | T86: =+COUNTIF('DISPATCHED (VT11)'!L:L,'Fleet Report'!Q86) -> 0 | V86: =IF(T86=0,0,1+T86-T86) -> 0 | AP86: =IFERROR(VLOOKUP(Q86,'Truck Utilization'!B$3:C$237,2,FALSE),"")
A87: PKO621 | B87: =IFERROR(VLOOKUP(A87,'DISPATCHED (VT11)'!T$7:V$781,2,FALSE),"") | C87: =IFERROR(VLOOKUP(A87,'DISPATCHED (VT11)'!T$7:V$781,3,FALSE),"") | D87: =+COUNTIF('DISPATCHED (VT11)'!L:L,'Fleet Report'!A87) -> 0 | E87: =_xlfn.XLOOKUP(A87,H:H,K:K) -> 1 | F87: =IF(E87="","B",IF(D87=0,0,1+D87-D87)) -> 0 | H87: PKO621 | I87: =_xlfn.XLOOKUP(H87,'Truck Utilization'!B:B,'Truck Utilization'!D:D) -> 10 | J87: 8P | K87: =IF(M87=1,"","1") -> 1 | P87: VALDOZ | R87: =VLOOKUP(Q87,'DISPATCHED (VT11)'!T$7:V$789,2,FALSE) -> 0 | S87: =VLOOKUP(Q87,'DISPATCHED (VT11)'!T$15:V$789,3,FALSE) | T87: =+COUNTIF('DISPATCHED (VT11)'!L:L,'Fleet Report'!Q87) -> 0 | V87: =IF(T87=0,0,1+T87-T87) -> 0 | AP87: =IFERROR(VLOOKUP(Q87,'Truck Utilization'!B$3:C$237,2,FALSE),"")
A88: PKO641 | B88: =IFERROR(VLOOKUP(A88,'DISPATCHED (VT11)'!T$7:V$781,2,FALSE),"") | C88: =IFERROR(VLOOKUP(A88,'DISPATCHED (VT11)'!T$7:V$781,3,FALSE),"") | D88: =+COUNTIF('DISPATCHED (VT11)'!L:L,'Fleet Report'!A88) -> 0 | E88: =_xlfn.XLOOKUP(A88,H:H,K:K) -> 1 | F88: =IF(E88="","B",IF(D88=0,0,1+D88-D88)) -> 0 | H88: PKO641 | I88: =_xlfn.XLOOKUP(H88,'Truck Utilization'!B:B,'Truck Utilization'!D:D) -> 10 | J88: 8P | K88: =IF(M88=1,"","1") -> 1 | P88: VALDOZ | R88: =VLOOKUP(Q88,'DISPATCHED (VT11)'!T$7:V$789,2,FALSE) -> 0 | S88: =VLOOKUP(Q88,'DISPATCHED (VT11)'!T$15:V$789,3,FALSE) | T88: =+COUNTIF('DISPATCHED (VT11)'!L:L,'Fleet Report'!Q88) -> 0 | V88: =IF(T88=0,0,1+T88-T88) -> 0 | AP88: =IFERROR(VLOOKUP(Q88,'Truck Utilization'!B$3:C$237,2,FALSE),"")
A89: PKO931 | B89: =IFERROR(VLOOKUP(A89,'DISPATCHED (VT11)'!T$7:V$781,2,FALSE),"") | C89: =IFERROR(VLOOKUP(A89,'DISPATCHED (VT11)'!T$7:V$781,3,FALSE),"") | D89: =+COUNTIF('DISPATCHED (VT11)'!L:L,'Fleet Report'!A89) -> 0 | E89: =_xlfn.XLOOKUP(A89,H:H,K:K) -> 1 | F89: =IF(E89="","B",IF(D89=0,0,1+D89-D89)) -> 0 | H89: PKO931 | I89: =_xlfn.XLOOKUP(H89,'Truck Utilization'!B:B,'Truck Utilization'!D:D) -> 10 | J89: 8P | K89: =IF(M89=1,"","1") -> 1 | R89: =VLOOKUP(Q89,'DISPATCHED (VT11)'!T$7:V$789,2,FALSE) -> 0 | S89: =VLOOKUP(Q89,'DISPATCHED (VT11)'!T$15:V$789,3,FALSE) | T89: =+COUNTIF('DISPATCHED (VT11)'!L:L,'Fleet Report'!Q89) -> 0 | V89: =IF(T89=0,0,1+T89-T89) -> 0 | AP89: =IFERROR(VLOOKUP(Q89,'Truck Utilization'!B$3:C$237,2,FALSE),"")
A90: PKO852 | B90: =IFERROR(VLOOKUP(A90,'DISPATCHED (VT11)'!T$7:V$781,2,FALSE),"") | C90: =IFERROR(VLOOKUP(A90,'DISPATCHED (VT11)'!T$7:V$781,3,FALSE),"") | D90: =+COUNTIF('DISPATCHED (VT11)'!L:L,'Fleet Report'!A90) -> 0 | E90: =_xlfn.XLOOKUP(A90,H:H,K:K) -> 1 | F90: =IF(E90="","B",IF(D90=0,0,1+D90-D90)) -> 0 | H90: PKO852 | I90: =_xlfn.XLOOKUP(H90,'Truck Utilization'!B:B,'Truck Utilization'!D:D) -> 10 | J90: 8P | K90: =IF(M90=1,"","1") -> 1 | R90: =VLOOKUP(Q90,'DISPATCHED (VT11)'!T$7:V$789,2,FALSE) -> 0 | S90: =VLOOKUP(Q90,'DISPATCHED (VT11)'!T$15:V$789,3,FALSE) | T90: =+COUNTIF('DISPATCHED (VT11)'!L:L,'Fleet Report'!Q90) -> 0 | V90: =IF(T90=0,0,1+T90-T90) -> 0 | AP90: =IFERROR(VLOOKUP(Q90,'Truck Utilization'!B$3:C$237,2,FALSE),"")
